Workbook

Sheet Detalhamento RE - 1º Bimestre
A2: TOTAL | B2: Data | C2: Nº RE | D2: Nº OB | E2: DESCRIÇÃO | F2: DETALHAMENTO | G2: =SUM(G3:G27) -> 13499282 | H2: Nº GD
A3: Vlr Individual | B3: 45701 | C3: 2025RE00014 | D3: 2025OB00276 | E3: Folha de Pagamento | F3: GOVERNO DO ESTADO DO AMAPA | G3: 3384838.7
A4: Vlr Individual | B4: 45701 | C4: 2025RE00014 | D4: 2025OB00277 | E4: Folha de Pagamento | F4: BANCO DO BRASIL S/A | G4: 8576713.3
A5: Vlr Individual | B5: 45701 | C5: 2025RE00014 | D5: 2025OB00278 | E5: Folha de Pagamento | F5: ALLIANZ SEGUROS S.A | G5: 19.58
A6: Vlr Individual | B6: 45701 | C6: 2025RE00014 | D6: 2025OB00279 | E6: Folha de Pagamento | F6: ASPA MENSALIDADE | G6: 196
A7: Vlr Individual | B7: 45701 | C7: 2025RE00014 | D7: 2025OB00280 | E7: Folha de Pagamento | F7: ASPBRAS-ASSOC.DOS SERV.PUBLICOS BRASILEIROS. | G7: 93
A8: Vlr Individual | B8: 45701 | C8: 2025RE00014 | D8: 2025OB00281 | E8: Folha de Pagamento | F8: ASPEB | G8: 21000.86
A9: Vlr Individual | B9: 45701 | C9: 2025RE00014 | D9: 2025OB00283 | E9: Folha de Pagamento | F9: ASSEGUP MENS | G9: 210
A10: Vlr Individual | B10: 45701 | C10: 2025RE00014 | D10: 2025OB00284 | E10: Folha de Pagamento | F10: HSBC BAMERINDUS SEGUROS | G10: 9804.94
A11: Vlr Individual | B11: 45701 | C11: 2025RE00014 | D11: 2025OB00285 | E11: Folha de Pagamento | F11: BANCO BMG S/A | G11: 1224.56
A12: Vlr Individual | B12: 45701 | C12: 2025RE00014 | D12: 2025OB00286 | E12: Folha de Pagamento | F12: BANCO MASTER S.A | G12: 710726.23
A13: Vlr Individual | B13: 45701 | C13: 2025RE00014 | D13: 2025OB00288 | E13: Folha de Pagamento | F13: BANCO OLE BONSUCESSO CONSIGNADO S/A | G13: 50314.08
A14: Vlr Individual | B14: 45701 | C14: 2025RE00014 | D14: 2025OB00289 | E14: Folha de Pagamento | F14: BANCO CRUZEIRO DO SUL S/A | G14: 327.45
... A20: Vlr Individual | B20: 45701 | C20: 2025RE00014 | D20: 2025OB00297 | E20: Folha de Pagamento | F20: AGENCIA DE FOMENTO DO AMAPA S/A AFAP | G20: 2267.14
A21: Vlr Individual | B21: 45701 | C21: 2025RE00014 | D21: 2025OB00298 | E21: Folha de Pagamento | F21: R.S.P.P.ASS.PREV.PRIVADA | G21: 111.18 | H21: 2025GD00002
A22: Vlr Individual | B22: 45701 | C22: 2025RE00014 | D22: 2025OB00299 | E22: Folha de Pagamento | F22: SINSEPEAP-SIND.SERV.PUB.EDUC.AP | G22: 184954.83
A23: Vlr Individual | B23: 45701 | C23: 2025RE00014 | D23: 2025OB00300 | E23: Folha de Pagamento | F23: SINDICATO DOS EMPREG. EM EMP. DE PROC. DE DADOS... | G23: 13.09
A24: Vlr Individual | B24: 45701 | C24: 2025RE00014 | D24: 2025OB00301 | E24: Folha de Pagamento | F24: SIND. DOS SERVIDORES GRUPO GESTÃO ADM DO EST. D... | G24: 478.49
A25: Vlr Individual | B25: 45701 | C25: 2025RE00014 | D25: 2025OB00302 | E25: Folha de Pagamento | F25: SUL AMERICA SEGUROS DE VIDA E PREVIDENCIA S/A. | G25: 320.23
A26: Vlr Individual | B26: 45701 | C26: 2025RE00014 | D26: 2025OB00303 | E26: Folha de Pagamento | F26: UNIODONTO | G26: 87239
A27: Vlr Individual | B27: 45701 | C27: 2025RE00014 | D27: 2025OB00304 | E27: Folha de Pagamento | F27: PDT CONTRIBUIÇÃO | G27: 470.99
A29: TOTAL | B29: Data | C29: Nº RE | D29: Nº OB | E29: DESCRIÇÃO | F29: DETALHAMENTO | G29: =SUM(G30:G33) -> 3493620 | H29: Nº GD
A30: Vlr Individual | B30: 45701 | C30: 2025RE00015 | D30: 2025OB00282 | E30: Folha de Pagamento | F30: ASS.ASSIST.FUNC.PUBLICO MENSALIDADE | G30: 229
A31: Vlr Individual | B31: 45701 | C31: 2025RE00015 | D31: 2025OB00287 | E31: Folha de Pagamento | F31: BANCO MASTER S.A | G31: 327604.14
A32: Vlr Individual | B32: 45701 | C32: 2025RE00015 | D32: 2025OB00294 | E32: Folha de Pagamento | F32: BANCO SANTANDER BANESPA S.A | G32: 3139248.7
A33: Vlr Individual | B33: 45701 | C33: 2025RE00015 | D33: 2025OB00296 | E33: Folha de Pagamento | F33: AGENCIA DE FOMENTO DO AMAPA S/A AFAP | G33: 26538.12
A35: TOTAL | B35: Data | C35: Nº RE | D35: Nº OB | E35: DESCRIÇÃO | F35: DETALHAMENTO | G35: =SUM(G36:G43) -> 18292925 | H35: Nº GD
A36: Vlr Individual | B36: 45702 | C36: 2025RE00028 | D36: 2025OB00588 | E36: Folha de Pagamento | F36: GOVERNO DO ESTADO DO AMAPA | G36: 7619659.9
A37: Vlr Individual | B37: 45702 | C37: 2025RE00028 | D37: 2025OB00589 | E37: Folha de Pagamento | F37: SECRETARIA DA RECEITA FEDERAL DO BRASIL (MINISTÉRIO DA FAZENDA) | G37: 20585.63
A38: Vlr Individual | B38: 45702 | C38: 2025RE00028 | D38: 2025OB00590 | E38: Folha de Pagamento | F38: GOVERNO DO ESTADO DO AMAPA | G38: 3742.61
A39: Vlr Individual | B39: 45702 | C39: 2025RE00028 | D39: 2025OB00591 | E39: Folha de Pagamento | F39: AMAPÁ PREVIDÊNCIA | G39: 2779824.2
A40: Vlr Individual | B40: 45702 | C40: 2025RE00028 | D40: 2025OB00592 | E40: Folha de Pagamento | F40: AMAPÁ PREVIDÊNCIA | G40: 5031863.6
A41: Vlr Individual | B41: 45702 | C41: 2025RE00028 | D41: 2025OB00593 | E41: Folha de Pagamento | F41: SECRETARIA DA RECEITA FEDERAL DO BRASIL (MINISTÉRIO DA FAZENDA) | G41: 52204.18
A42: Vlr Individual | B42: 45702 | C42: 2025RE00028 | D42: 2025OB00594 | E42: Folha de Pagamento | F42: SECRETARIA DA RECEITA FEDERAL DO BRASIL (MINISTÉRIO DA FAZENDA) | G42: 5220.42
A43: Vlr Individual | B43: 45702 | C43: 2025RE00028 | D43: 2025OB00595 | E43: Folha de Pagamento | F43: AMAPÁ PREVIDÊNCIA | G43: 2779824.2
A45: TOTAL | B45: Data | C45: Nº RE | D45: Nº OB | E45: DESCRIÇÃO | F45: DETALHAMENTO | G45: =SUM(G46:G49) -> 5528457.6 | H45: Nº GD
A46: Vlr Individual | B46: 45705 | C46: 2025RE00031 | D46: 2025OB00597 | E46: Folha de Pagamento | F46: GOVERNO DO ESTADO DO AMAPA | G46: 496593.96
A47: Vlr Individual | B47: 45705 | C47: 2025RE00031 | D47: 2025OB00598 | E47: Folha de Pagamento | F47: AMAPÁ PREVIDÊNCIA | G47: 597619.08
A48: Vlr Individual | B48: 45705 | C48: 2025RE00031 | D48: 2025OB00599 | E48: Folha de Pagamento | F48: AMAPÁ PREVIDÊNCIA | G48: 2646092.9
A49: Vlr Individual | B49: 45705 | C49: 2025RE00031 | D49: 2025OB00600 | E49: Folha de Pagamento | F49: AMAPÁ PREVIDÊNCIA | G49: 1788151.6
A51: TOTAL | B51: Data | C51: Nº RE | D51: Nº OB | E51: DESCRIÇÃO | F51: DETALHAMENTO | G51: =SUM(G52:G52) -> 333.78 | H51: Nº GD
A52: Vlr Individual | B52: 45709 | C52: 2025RE00042 | D52: 2025OB00727 | E52: Folha de Pagamento | F52: GOVERNO DO ESTADO DO AMAPA | G52: 333.78
A54: TOTAL | B54: Data | C54: Nº RE | D54: Nº OB | E54: DESCRIÇÃO | F54: DETALHAMENTO | G54: =SUM(G55:G59) -> 324463.94 | H54: Nº GD
A55: Vlr Individual | B55: 45715 | C55: 2025RE00053 | D55: 2025OB00858 | E55: Folha de Pagamento | F55: GOVERNO DO ESTADO DO AMAPA | G55: 4199.28
A56: Vlr Individual | B56: 45715 | C56: 2025RE00053 | D56: 2025OB00859 | E56: Folha de Pagamento | F56: GOVERNO DO ESTADO DO AMAPA | G56: 84800.3
A57: Vlr Individual | B57: 45715 | C57: 2025RE00053 | D57: 2025OB00860 | E57: Folha de Pagamento | F57: GOVERNO DO ESTADO DO AMAPA | G57: 113103.55
A58: Vlr Individual | B58: 45715 | C58: 2025RE00053 | D58: 2025OB00861 | E58: Folha de Pagamento | F58: GOVERNO DO ESTADO DO AMAPA | G58: 73190.77
A59: Vlr Individual | B59: 45715 | C59: 2025RE00053 | D59: 2025OB00862 | E59: Folha de Pagamento | F59: GOVERNO DO ESTADO DO AMAPA | G59: 49170.04

Sheet Extrato 01-2025
A1: Extrato Conta Corrente
A2: Agencia | C2: =SUBTOTAL(9,C4:C99) -> 1.4322821e+08
A3: Data | B3: Historico | C3: Valor R$ | D3: Inf. | E3: Detalhamento Hist.
A4: 10/01/2025 | B4: IPVA | C4: 33292.32 | D4: C | E4: Transferência Constitucional - FUNDEB
A5: 10/01/2025 | B5: ITR | C5: 801.48 | D5: C | E5: Transferência Constitucional - FUNDEB
A6: 10/01/2025 | B6: RECEBIMENTO DE ICMS | C6: 1473123.3 | D6: C | E6: Transferência Constitucional - FUNDEB
A7: 10/01/2025 | B7: FPE/FPM | C7: 974097.66 | D7: C | E7: Transferência Constitucional - FUNDEB
A8: 10/01/2025 | B8: FPE/FPM | C8: 2264490.5 | D8: C | E8: Transferência Constitucional - FUNDEB
A9: 10/01/2025 | B9: FPE/FPM | C9: 26660819 | D9: C | E9: Transferência Constitucional - FUNDEB
A10: 10/01/2025 | B10: FPE/FPM | C10: 11459.95 | D10: C | E10: Transferência Constitucional - FUNDEB
A11: 10/01/2025 | B11: IPI/EXPORTACAO | C11: 21145.69 | D11: C | E11: IPI/EXPORTACAO - Cota Débito
A12: 10/01/2025 | B12: IPI/EXPORTACAO | C12: 12267.68 | D12: C | E12: Transferência Constitucional - FUNDEB
A13: 10/01/2025 | B13: COTA DAF-DEBITO | C13: 21145.69 | D13: D | E13: IPI/EXPORTACAO - Cota Débito
A14: 10/01/2025 | B14: BB-APLIC C.PRZ-APL.AUT | C14: 31430352 | D14: D | E14: Aplicação Financeira
A15: 13/01/2025 | B15: TED Transf.Eletr.Disponiv | C15: 1664.17 | D15: D | E15: Férias
... A93: 31/01/2025 | B93: BB-APLIC C.PRZ-APL.AUT | C93: 5462074.1 | D93: D | E93: Aplicação Financeira

Sheet Extrato 02-2025
A1: Extrato Conta Corrente
A2: Agencia | C2: =SUBTOTAL(9,C4:C80) -> 1.8573717e+08
A3: Data | B3: Historico | C3: Valor R$ | D3: Inf. | E3: Detalhamento Hist. | F3: RE
A4: 06/02/2025 | B4: Tar Lib/Ant Float Pg Div | C4: 1771 | D4: D | E4: Tarifa Bancária
A5: 06/02/2025 | B5: Resgate Automático | C5: 1771 | D5: C | E5: Resgate Automático
A6: 10/02/2025 | B6: ITCMD | C6: 52425.39 | D6: C | E6: Transferência Constitucional - FUNDEB
A7: 10/02/2025 | B7: RECEBIMENTO DE ICMS | C7: 783899.29 | D7: C | E7: Transferência Constitucional - FUNDEB
A8: 10/02/2025 | B8: ITR | C8: 1070.01 | D8: C | E8: Transferência Constitucional - FUNDEB
A9: 10/02/2025 | B9: FPE/FPM | C9: 2254096.5 | D9: C | E9: Transferência Constitucional - FUNDEB
A10: 10/02/2025 | B10: FPE/FPM | C10: 5240110.9 | D10: C | E10: Transferência Constitucional - FUNDEB
A11: 10/02/2025 | B11: FPE/FPM | C11: 59156698 | D11: C | E11: Transferência Constitucional - FUNDEB
A12: 10/02/2025 | B12: FPE/FPM | C12: 26518.78 | D12: C | E12: Transferência Constitucional - FUNDEB
A13: 10/02/2025 | B13: IPI/EXPORTACAO | C13: 24106.25 | D13: C | E13: IPI/EXPORTACAO - Cota Débito
A14: 10/02/2025 | B14: IPI/EXPORTACAO | C14: 13985.23 | D14: C | E14: Transferência Constitucional - FUNDEB
A15: 10/02/2025 | B15: COTA DAF-DEBITO | C15: 24106.25 | D15: D | E15: IPI/EXPORTACAO - Cota Débito
... A17: 13/02/2025 | B17: ORDEM BANC CANCELADA | C17: 111.18 | D17: C | E17: ORDEM BANC CANCELADA
A18: 13/02/2025 | B18: Emissão Ordem Bancária | C18: 13499282 | D18: D | E18: Folha de Pagamento | F18: 2025RE00014
A19: 13/02/2025 | B19: Emissão Ordem Bancária | C19: 3493620 | D19: D | E19: Folha de Pagamento | F19: 2025RE00015
A20: 13/02/2025 | B20: Tar Lib/Ant Float Pg Div | C20: 17.2 | D20: D | E20: Tarifa Bancária
A21: 13/02/2025 | B21: Tar Lib/Ant Float Pg Div | C21: 20.24 | D21: D | E21: Tarifa Bancária
A22: 13/02/2025 | B22: Resgate Automático | C22: 16992828 | D22: C | E22: Resgate Automático
A23: 14/02/2025 | B23: Pagamentos Diversos | C23: 10029.56 | D23: D | E23: Pagamentos Diversos
A24: 14/02/2025 | B24: Emissão Ordem Bancária | C24: 18292925 | D24: D | E24: Folha de Pagamento | F24: 2025RE00028
A25: 14/02/2025 | B25: Resgate Automático | C25: 18302954 | D25: C | E25: Resgate Automático
A26: 17/02/2025 | B26: ITCMD | C26: 52425.39 | D26: C | E26: Transferência Constitucional - FUNDEB
A27: 17/02/2025 | B27: RECEBIMENTO DE ICMS | C27: 783899.29 | D27: C | E27: Transferência Constitucional - FUNDEB
A28: 17/02/2025 | B28: Emissão Ordem Bancária | C28: 5528457.6 | D28: D | E28: Folha de Pagamento | F28: 2025RE00031
A29: 17/02/2025 | B29: Tar Lib/Ant Float Pg Div | C29: 5.09 | D29: D | E29: Tarifa Bancária
A30: 17/02/2025 | B30: Tar Lib/Ant Float Pg Div | C30: 10.02 | D30: D | E30: Tarifa Bancária
A31: 17/02/2025 | B31: Tar Lib/Ant Float Pg Div | C31: 6.73 | D31: D | E31: Tarifa Bancária
A32: 17/02/2025 | B32: Resgate Automático | C32: 4692154.7 | D32: C | E32: Resgate Automático
A33: 20/02/2025 | B33: ITR | C33: 73.24 | D33: C | E33: Transferência Constitucional - FUNDEB
A34: 20/02/2025 | B34: IPI/EXPORTACAO | C34: 10960.52 | D34: C | E34: IPI/EXPORTACAO - Cota Débito
A35: 20/02/2025 | B35: IPI/EXPORTACAO | C35: 6358.75 | D35: C | E35: Transferência Constitucional - FUNDEB
A36: 20/02/2025 | B36: FPE/FPM | C36: 225249.85 | D36: C | E36: Transferência Constitucional - FUNDEB
A37: 20/02/2025 | B37: FPE/FPM | C37: 523639.75 | D37: C | E37: Transferência Constitucional - FUNDEB
A38: 20/02/2025 | B38: FPE/FPM | C38: 5873079.8 | D38: C | E38: Transferência Constitucional - FUNDEB
A39: 20/02/2025 | B39: FPE/FPM | C39: 2649.98 | D39: C | E39: Transferência Constitucional - FUNDEB
A40: 20/02/2025 | B40: COTA DAF-DEBITO | C40: 10960.52 | D40: D | E40: IPI/EXPORTACAO - Cota Débito
A41: 20/02/2025 | B41: BB-APLIC C.PRZ-APL.AUT | C41: 6631051.4 | D41: D | E41: Aplicação Financeira
A42: 21/02/2025 | B42: Emissão Ordem Bancária | C42: 333.78 | D42: D | E42: Folha de Pagamento | F42: 2025RE00042
A43: 21/02/2025 | B43: Resgate Automático | C43: 333.78 | D43: C | E43: Resgate Automático
A44: 24/02/2025 | B44: RECEBIMENTO DE ICMS | C44: 8862577.6 | D44: C | E44: Transferência Constitucional - FUNDEB
A45: 24/02/2025 | B45: IPVA | C45: 29159.76 | D45: C | E45: Transferência Constitucional - FUNDEB
A46: 24/02/2025 | B46: IPVA | C46: 46956.35 | D46: C | E46: Transferência Constitucional - FUNDEB
A47: 24/02/2025 | B47: IPVA | C47: 197947.69 | D47: C | E47: Transferência Constitucional - FUNDEB
A48: 24/02/2025 | B48: IPVA | C48: 232597.13 | D48: C | E48: Transferência Constitucional - FUNDEB
A49: 24/02/2025 | B49: IPVA | C49: 256293.43 | D49: C | E49: Transferência Constitucional - FUNDEB
A50: 24/02/2025 | B50: BB-APLIC C.PRZ-APL.AUT | C50: 9625532 | D50: D | E50: Aplicação Financeira
A51: 26/02/2025 | B51: IPVA | C51: 292819.53 | D51: C | E51: Transferência Constitucional - FUNDEB
A52: 26/02/2025 | B52: BB-APLIC C.PRZ-APL.AUT | C52: 292819.53 | D52: D | E52: Aplicação Financeira
A53: 27/02/2025 | B53: Folha de Pagamento | C53: 32437755 | D53: D | E53: Folha de 02/2025 | F53: Regularizada em Março
A54: 27/02/2025 | B54: Folha de Pagamento | C54: 546363.75 | D54: D | E54: Folha de 02/2025 | F54: Regularizada em Março
A55: 27/02/2025 | B55: Folha de Pagamento | C55: 282543.38 | D55: D | E55: Folha de 02/2025 | F55: Regularizada em Março
A56: 27/02/2025 | B56: Folha de Pagamento | C56: 694.48 | D56: D | E56: Folha de 02/2025 | F56: Regularizada em Março
A57: 27/02/2025 | B57: Folha de Pagamento | C57: 14605.34 | D57: D | E57: Folha de 02/2025 | F57: Regularizada em Março
A58: 27/02/2025 | B58: Folha de Pagamento | C58: 551705.75 | D58: D | E58: Folha de 02/2025 | F58: Regularizada em Março
A59: 27/02/2025 | B59: Pagamentos Diversos | C59: 17450.03 | D59: D | E59: Folha de 02/2025 | F59: Regularizada em Março
A60: 27/02/2025 | B60: Emissão Ordem Bancária | C60: 324463.94 | D60: D | E60: Folha de 02/2025 | F60: Regularizada em Março
A61: 27/02/2025 | B61: Resgate Automático | C61: 34175582 | D61: C | E61: Resgate Automático
A62: 28/02/2025 | B62: IPVA | C62: 665896.3 | D62: C | E62: Transferência Constitucional - FUNDEB
A63: 28/02/2025 | B63: RECEBIMENTO DE ICMS | C63: 1774880.2 | D63: C | E63: Transferência Constitucional - FUNDEB
A64: 28/02/2025 | B64: ITR | C64: 180.75 | D64: C | E64: Transferência Constitucional - FUNDEB
A65: 28/02/2025 | B65: FPE/FPM | C65: 815681.4 | D65: C | E65: Transferência Constitucional - FUNDEB
A66: 28/02/2025 | B66: FPE/FPM | C66: 1896219.2 | D66: C | E66: Transferência Constitucional - FUNDEB
A67: 28/02/2025 | B67: FPE/FPM | C67: 21447584 | D67: C | E67: Transferência Constitucional - FUNDEB
A68: 28/02/2025 | B68: FPE/FPM | C68: 9596.19 | D68: C | E68: Transferência Constitucional - FUNDEB
A69: 28/02/2025 | B69: IPI/EXPORTACAO | C69: 7464.77 | D69: C | E69: IPI/EXPORTACAO - Cota Débito
A70: 28/02/2025 | B70: IPI/EXPORTACAO | C70: 4330.66 | D70: C | E70: Transferência Constitucional - FUNDEB
A71: 28/02/2025 | B71: COTA DAF-DEBITO | C71: 7464.77 | D71: D | E71: IPI/EXPORTACAO - Cota Débito
A72: 28/02/2025 | B72: Pagto via Auto-Atend.BB | C72: 333.78 | D72: D | E72: GRU-GUIA RECOLHIM. UNIAO | F72: 2025OB03433 | G72: Regularizado em Março
A73: 28/02/2025 | B73: Pagto via Auto-Atend.BB | C73: 333.78 | D73: D | E73: GRU-GUIA RECOLHIM. UNIAO | F73: 2025OB03434 | G73: Regularizado em Março
A74: 28/02/2025 | B74: Tar Lib/Ant Float Pg Div | C74: 1 | D74: D | E74: Tarifa Bancária
A75: 28/02/2025 | B75: BB-APLIC C.PRZ-APL.AUT | C75: 26613700 | D75: D | E75: Aplicação Financeira

Sheet REF - 1º Bimestre
D2: =SUBTOTAL(9,D4:D64) -> 90916811
A3: PD | B3: OB | C3: Credor | D3: 2 - Fevereiro | E3: Mês de Ocorrência | F3: RE | G3: GD
A4: 2025PD00318 | B4: 2025OB00292 | C4: PF0000023 - FOLHA DE PAGAMENTO | D4: 84 | E4: Extrato de Fevereiro | F4: 2025RE00014
A5: 2025PD00748 | B5: 2025OB00806 | C5: PF0000023 - FOLHA DE PAGAMENTO | D5: 333.78 | E5: Extrato de Janeiro
A6: 2025PD00693 | B6: 2025OB00805 | C6: PF0000023 - FOLHA DE PAGAMENTO | D6: 333.78 | E6: Extrato de Janeiro
A7: 2025PD00749 | B7: 2025OB00807 | C7: PF0000023 - FOLHA DE PAGAMENTO | D7: 21025.56 | E7: Extrato de Janeiro
A8: 2025PD00646 | B8: 2025OB00802 | C8: PF0000023 - FOLHA DE PAGAMENTO | D8: 265580.97 | E8: Férias
A9: 2025PD00616 | B9: 2025OB00597 | C9: PF0000023 - FOLHA DE PAGAMENTO | D9: 496593.96 | E9: Extrato de Fevereiro | F9: 2025RE00031
A10: 2025PD00650 | B10: 2025OB00808 | C10: PF0000023 - FOLHA DE PAGAMENTO | D10: 10505937 | E10: Férias
A11: 2025PD00277 | B11: 2025OB00276 | C11: PF0000023 - FOLHA DE PAGAMENTO | D11: 3384838.7 | E11: Extrato de Fevereiro | F11: 2025RE00014
A12: 2025PD00292 | B12: 2025OB00277 | C12: PF0000023 - FOLHA DE PAGAMENTO | D12: 8576713.3 | E12: Extrato de Fevereiro | F12: 2025RE00014
A13: 2025PD00302 | B13: 2025OB00278 | C13: PF0000023 - FOLHA DE PAGAMENTO | D13: 19.58 | E13: Extrato de Fevereiro | F13: 2025RE00014
A14: 2025PD00305 | B14: 2025OB00279 | C14: PF0000023 - FOLHA DE PAGAMENTO | D14: 196 | E14: Extrato de Fevereiro | F14: 2025RE00014
A15: 2025PD00306 | B15: 2025OB00280 | C15: PF0000023 - FOLHA DE PAGAMENTO | D15: 93 | E15: Extrato de Fevereiro | F15: 2025RE00014
A16: 2025PD00307 | B16: 2025OB00281 | C16: PF0000023 - FOLHA DE PAGAMENTO | D16: 21000.86 | E16: Extrato de Fevereiro | F16: 2025RE00014
A17: 2025PD00308 | B17: 2025OB00282 | C17: PF0000023 - FOLHA DE PAGAMENTO | D17: 229 | E17: Extrato de Fevereiro | F17: 2025RE00015
A18: 2025PD00309 | B18: 2025OB00283 | C18: PF0000023 - FOLHA DE PAGAMENTO | D18: 210 | E18: Extrato de Fevereiro | F18: 2025RE00014
A19: 2025PD00310 | B19: 2025OB00284 | C19: PF0000023 - FOLHA DE PAGAMENTO | D19: 9804.94 | E19: Extrato de Fevereiro | F19: 2025RE00014
A20: 2025PD00311 | B20: 2025OB00285 | C20: PF0000023 - FOLHA DE PAGAMENTO | D20: 1224.56 | E20: Extrato de Fevereiro | F20: 2025RE00014
A21: 2025PD00312 | B21: 2025OB00286 | C21: PF0000023 - FOLHA DE PAGAMENTO | D21: 710726.23 | E21: Extrato de Fevereiro | F21: 2025RE00014
A22: 2025PD00313 | B22: 2025OB00287 | C22: PF0000023 - FOLHA DE PAGAMENTO | D22: 327604.14 | E22: Extrato de Fevereiro | F22: 2025RE00015
... A31: 2025PD00323 | B31: 2025OB00297 | C31: PF0000023 - FOLHA DE PAGAMENTO | D31: 2267.14 | E31: Extrato de Fevereiro | F31: 2025RE00014
A32: 2025PD00324 | B32: 2025OB00298 | C32: PF0000023 - FOLHA DE PAGAMENTO | D32: 0 | E32: Extrato de Fevereiro | F32: 2025RE00014 | G32: 2025GD00002
A33: 2025PD00325 | B33: 2025OB00299 | C33: PF0000023 - FOLHA DE PAGAMENTO | D33: 184954.83 | E33: Extrato de Fevereiro | F33: 2025RE00014
A34: 2025PD00326 | B34: 2025OB00300 | C34: PF0000023 - FOLHA DE PAGAMENTO | D34: 13.09 | E34: Extrato de Fevereiro | F34: 2025RE00014
A35: 2025PD00327 | B35: 2025OB00301 | C35: PF0000023 - FOLHA DE PAGAMENTO | D35: 478.49 | E35: Extrato de Fevereiro | F35: 2025RE00014
A36: 2025PD00328 | B36: 2025OB00302 | C36: PF0000023 - FOLHA DE PAGAMENTO | D36: 320.23 | E36: Extrato de Fevereiro | F36: 2025RE00014
A37: 2025PD00329 | B37: 2025OB00303 | C37: PF0000023 - FOLHA DE PAGAMENTO | D37: 87239 | E37: Extrato de Fevereiro | F37: 2025RE00014
A38: 2025PD00330 | B38: 2025OB00304 | C38: PF0000023 - FOLHA DE PAGAMENTO | D38: 470.99 | E38: Extrato de Fevereiro | F38: 2025RE00014
A39: 2025PD00660 | B39: 2025OB00803 | C39: PF0000023 - FOLHA DE PAGAMENTO | D39: 36251.68 | E39: Salário de 01/2024
A40: 2025PD00824 | B40: 2025OB00727 | C40: PF0000023 - FOLHA DE PAGAMENTO | D40: 333.78 | E40: Extrato de Fevereiro | F40: 2025RE00042
A41: 2025PD00662 | B41: 2025OB00804 | C41: PF0000023 - FOLHA DE PAGAMENTO | D41: 856836.89 | E41: Salário de 01/2024
A42: 2025PD00587 | B42: 2025OB00588 | C42: PF0000023 - FOLHA DE PAGAMENTO | D42: 7619659.9 | E42: Extrato de Fevereiro | F42: 2025RE00028
A43: 2025PD00588 | B43: 2025OB00589 | C43: PF0000023 - FOLHA DE PAGAMENTO | D43: 20585.63 | E43: Extrato de Fevereiro | F43: 2025RE00028
A44: 2025PD00589 | B44: 2025OB00590 | C44: PF0000023 - FOLHA DE PAGAMENTO | D44: 3742.61 | E44: Extrato de Fevereiro | F44: 2025RE00028
A45: 2025PD00592 | B45: 2025OB00591 | C45: PF0000023 - FOLHA DE PAGAMENTO | D45: 2779824.2 | E45: Extrato de Fevereiro | F45: 2025RE00028
A46: 2025PD00593 | B46: 2025OB00592 | C46: PF0000023 - FOLHA DE PAGAMENTO | D46: 5031863.6 | E46: Extrato de Fevereiro | F46: 2025RE00028
A47: 2025PD00667 | B47: 2025OB00811 | C47: PF0000023 - FOLHA DE PAGAMENTO | D47: 9102905.2 | E47: Salário de 01/2024
A48: 2025PD00590 | B48: 2025OB00593 | C48: 00394460005887 - SECRETARIA DA RECEITA FEDERAL DO BRASIL (MINISTÉRIO DA FAZENDA) | D48: 52204.18 | E48: Extrato de Fevereiro | F48: 2025RE00028
A49: 2025PD00591 | B49: 2025OB00594 | C49: 00394460005887 - SECRETARIA DA RECEITA FEDERAL DO BRASIL (MINISTÉRIO DA FAZENDA) | D49: 5220.42 | E49: Extrato de Fevereiro | F49: 2025RE00028
A50: 2025PD00670 | B50: 2025OB00814 | C50: PF0000023 - FOLHA DE PAGAMENTO | D50: 18226.24 | E50: Salário de 01/2024
A51: 2025PD00690 | B51: 2025OB00818 | C51: PF0000023 - FOLHA DE PAGAMENTO | D51: 2441664.4 | E51: Salário de 01/2024
A52: 2025PD00594 | B52: 2025OB00595 | C52: 03281445000185 - AMAPÁ PREVIDÊNCIA | D52: 2779824.2 | E52: Extrato de Fevereiro | F52: 2025RE00028
A53: 2025PD00596 | B53: 2025OB00599 | C53: 03281445000185 - AMAPÁ PREVIDÊNCIA | D53: 2646092.9 | E53: Extrato de Fevereiro | F53: 2025RE00031
A54: 2025PD00674 | B54: 2025OB00816 | C54: PF0000023 - FOLHA DE PAGAMENTO | D54: 2312741.7 | E54: Salário de 01/2024
A55: 2025PD00668 | B55: 2025OB00812 | C55: PF0000023 - FOLHA DE PAGAMENTO | D55: 4648412.8 | E55: Salário de 01/2024
A56: 2025PD00652 | B56: 2025OB00809 | C56: PF0000023 - FOLHA DE PAGAMENTO | D56: 1234018.6 | E56: Férias
A57: 2025PD00595 | B57: 2025OB00598 | C57: 03281445000185 - AMAPÁ PREVIDÊNCIA | D57: 597619.08 | E57: Extrato de Fevereiro | F57: 2025RE00031
A58: 2025PD00669 | B58: 2025OB00813 | C58: PF0000023 - FOLHA DE PAGAMENTO | D58: 13908637 | E58: Salário de 01/2024
A59: 2025PD00653 | B59: 2025OB00810 | C59: PF0000023 - FOLHA DE PAGAMENTO | D59: 3692339.1 | E59: Férias
A60: 2025PD00763 | B60: 2025OB00819 | C60: 00394460005887 - SECRETARIA DA RECEITA FEDERAL DO BRASIL (MINISTÉRIO DA FAZENDA) | D60: 52794.41 | E60: Extrato de Janeiro
A61: 2025PD00764 | B61: 2025OB00820 | C61: 00394460005887 - SECRETARIA DA RECEITA FEDERAL DO BRASIL (MINISTÉRIO DA FAZENDA) | D61: 5279.44 | E61: Extrato de Janeiro
A62: 2025PD00672 | B62: 2025OB00815 | C62: PF0000023 - FOLHA DE PAGAMENTO | D62: 7811.25 | E62: Salário de 01/2024
A63: 2025PD00597 | B63: 2025OB00600 | C63: 03281445000185 - AMAPÁ PREVIDÊNCIA | D63: 1788151.6 | E63: Extrato de Fevereiro | F63: 2025RE00031
A64: 2025PD00675 | B64: 2025OB00817 | C64: PF0000023 - FOLHA DE PAGAMENTO | D64: 991175 | E64: Salário de 01/2024
D65: 90916811

Sheet Saldos - 01-2025
B2: CONCILIAÇÃO BANCÁRIA DO EXTRATO BANCÁRIO - JANEIRO DE 2025
B4: 1. Ingressos | E4: Valores do Mês | F4: Acumulado
B5: 1.0 IPI - EXP | E5: 59369.1 | F5: =E5 -> 59369.1
B6: 1.1 VAAR | E6: 1477881.8 | F6: =E6 -> 1477881.8
B7: 1.2 FPE/FPM | E7: 74152666 | F7: =E7 -> 74152666
B8: 1.3 ICMS | E8: 17391685 | F8: =E8 -> 17391685
B9: 1.4 IPVA | E9: 34348.74 | F9: =E9 -> 34348.74
B10: 1.5 ITCMD | E10: 20855.66 | F10: =E10 -> 20855.66
B11: 1.6 ITR | E11: 1452.04 | F11: =E11 -> 1452.04
B12: 1.7 ORDEM BANC CANCELADA | E12: 0 | F12: =E12 -> 0
B13: 1.8 RESGATE | E13: 50089950 | F13: =E13 -> 50089950
B14: 2 Total das Entradas | E14: =SUM(E5:E13) -> 1.4322821e+08 | F14: =SUM(F5:F13) -> 1.4322821e+08
B15: 3.0 (-) IPI/Cota DAF Deb | E15: -37571.82 | F15: =E15 -> -37571.82
B16: 3.1 (-) Ordem Bancária Cancelada | E16: 0 | F16: =E16 -> 0
B17: 3.2 (-) Resgastes efetuados | E17: -50089950 | F17: =E17 -> -50089950
B18: 3.3 (-) Ajuste VAAR - FNDE | E18: -164645.69 | F18: =E18 -> -164645.69
B19: 3. Total Disponibizado( 1 - 3.0- 3.1 - 3.2 -3.3 - 3.4 ) | E19: =SUM(E14:E18) -> 92936040 | F19: =SUM(F14:F18) -> 92936040
B21: 4. Saídas | E21: Valores do Mês | F21: Acumulado
B22: 4.1 Cota DAF Deb | E22: 37571.82 | F22: =E22 -> 37571.82
B23: 4.2 O.B.s Canceladas | F23: =E23 -> 0
B24: 4.3.1 Folha de Pagamento - Encargos | E24: 79099.41 | F24: =E24 -> 79099.41
B25: 4.3.2 Folha de Pagamento - Folha 01/2025 | E25: 34311367 | F25: =E25 -> 34311367
B26: 4.3.3 Folha de Pagamento - Férias | E26: 15697876 | F26: =E26 -> 15697876
B27: 4.3.4 Ajuste VAAR | E27: 164645.69 | F27: =E27 -> 164645.69
B28: 4.3.5 GRU-GUIA RECOLHIM. UNIAO | E28: 667.56 | F28: =E28 -> 667.56
B29: 4.4 Tarifa bancária | E29: 5628.71 | F29: =E29 -> 5628.71
B30: 4.5 Aplicações Efetuadas | E30: 92931352 | F30: =E30 -> 92931352
B31: 5. Total Geral das Saídas | E31: =SUM(E22:E30) -> 1.4322821e+08 | F31: =SUM(F22:F30) -> 1.4322821e+08
B32: 6.1 (-) Cota DAF Deb | E32: =-E22 -> -37571.82 | F32: =E32 -> -37571.82
B33: 6.2 (-) Aplicações Efetuadas | E33: =-E30 -> -92931352 | F33: =E33 -> -92931352
B34: 6.3 ( - ) O.B.s Canceladas | E34: =-E23 -> 0 | F34: =E34 -> 0
B35: 6.4 Tarifa bancária | E35: =-E29 -> -5628.71 | F35: =E35 -> -5628.71
B36: 6.5 (-) Pagamento Folha não regularizado
B37: 6.6 (+) Regularização de Folha e não Pago | E37: 13294.61 | F37: =E37 -> 13294.61
B38: 6.7 (-) Ajuste VAAR - FNDE | F38: =-F27 -> -164645.69
B39: Despesa Total do Mês ( confere com o relatório de execução financeira do SEAFI ) | E39: =SUM(E31:E38) -> 50266950 | F39: =SUM(F31:F38) -> 50102305
B41: CONTA INVESTIMENTO
B42: saldo Inicial | E42: 15778860
B43: Aplicação | E43: 92931352
B44: Resgaste | E44: 50089950
B45: Rendimento Bruto | E45: 251992.13
B46: Saldo Atual | E46: =E42+E43-E44+E45 -> 58872254

Sheet Cálculo Conciliação 1º Bimestre
C3: Saldo dos Pagamentos do SEAFI | D3: =SUM(D5:D9) -> 1.4604409e+08 | E3: =D3-'[1]Demonst Exec Financ Conciliado'!$J$89 -> 11470.64
C5: Extrato de Janeiro | D5: =[2]Janeiro!G1 -> 58285284
C6: SEAFI a maior | D6: 8949.47 | G6: =D6+D5 -> 58294233
C7: Extrato de Fevereiro | D7: =[2]Fevereiro!G1 -> 88938686
C8: SEAFI a menor ( regularizado em março ) | D8: -1194723.6 | E8: pago em março
C9: SEAFI a maior | D9: 5894.85 | G9: =SUM(D7:D9) -> 87749857
C11: COMPOSIÇÃO DE SALDO DO FUNDEB
C12: 1º BIMESTRE DE 2025
C14: Dsiponibilidade Financeira em 31/12/2024 | D14: 15778860 | I14: 6.1469606e+08
C15: ( + ) Ingressos = Transferências Constitucionais - janeiro-2024 | D15: 92936040
C16: ( + ) Ingressos = Transferências Constitucionais - fevereiro-2024 | D16: 1.115289e+08 | I16: =D16+D15 -> 2.0446494e+08
C17: ( + ) Ingressos = Rendimentos do FUNDEB - 1º Bimestre | D17: 901662.73 | I17: =D17+I16 -> 2.053666e+08
C18: ( - ) Pagamentos Efetuados = Relatório de Execução Financeira | D18: -90916811
C19: ( - ) Pagto Tarifa Bancária não regularizada no SEAFI | D19: ='Saldos - 02-2025'!F37 -> -7459.99
C20: ( + ) Regularização Folha - não Pago | D20: =D36 -> 13294.61 | I20: =D19+D21+D22+D23 -> -34193739
C21: ( - ) Pagamento de Folha não regularizada no mês | D21: -34175582
C22: ( - ) Pagamentos Diversos - Folha | D22: -10029.56
C23: ( - ) GRU Paga e Não Regularizada | D23: -667.56
C27: ( = ) Saldo do SIOPE | D27: =SUM(D14:D26) -> 96048208
C29: Dsiponibilidade Financeira em 28/02/2025 | D29: ='Saldos - 02-2025'!E50 -> 96048208
C31: Diferença a identificar | D31: =D27-D29 -> 0.010000035
C34: Regularização - Janeiro/2024 | D34: =D35+13294.61 -> 34324662
C35: Pagto - Janeiro/2024 | D35: 34311367
D36: =D34-D35 -> 13294.61
C38: Regularização - Fevereiro/2024
C39: Pagto - Fevereiro/2024
D40: =D38-D39 -> 0
C42: Regularização não Pago | D42: =D36+D40 -> 13294.61

Sheet Saldos - 02-2025
B2: CONCILIAÇÃO BANCÁRIA DO EXTRATO BANCÁRIO - FEVEREIRO DE 2025
B4: 1. Ingressos | E4: Valores do Mês | F4: Acumulado
B5: 1.0 IPI - EXP | E5: 67206.18 | F5: =E5+'Saldos - 01-2025'!F5 -> 126575.28
B6: 1.1 VAAR | F6: =E6+'Saldos - 01-2025'!F6 -> 1477881.8
B7: 1.2 FPE/FPM | E7: 97471124 | F7: =E7+'Saldos - 01-2025'!F7 -> 1.7162379e+08
B8: 1.3 ICMS | E8: 12205256 | F8: =E8+'Saldos - 01-2025'!F8 -> 29596941
B9: 1.4 IPVA | E9: 1721670.2 | F9: =E9+'Saldos - 01-2025'!F9 -> 1756018.9
B10: 1.5 ITCMD | E10: 104850.78 | F10: =E10+'Saldos - 01-2025'!F10 -> 125706.44
B11: 1.6 ITR | E11: 1324 | F11: =E11+'Saldos - 01-2025'!F11 -> 2776.04
B12: 1.7 ORDEM BANC CANCELADA | E12: 111.18 | F12: =E12+'Saldos - 01-2025'!F12 -> 111.18
B13: 1.8 RESGATE | E13: 74165624 | F13: =E13+'Saldos - 01-2025'!F13 -> 1.2425557e+08
B14: 2 Total das Entradas | E14: =SUM(E5:E13) -> 1.8573717e+08 | F14: =SUM(F5:F13) -> 3.2896537e+08
B15: 3.0 (-) IPI/Cota DAF Deb | E15: -42531.54 | F15: =E15+'Saldos - 01-2025'!F15 -> -80103.36
B16: 3.1 (-) Ordem Bancária Cancelada | E16: -111.18 | F16: =E16+'Saldos - 01-2025'!F16 -> -111.18
B17: 3.2 (-) Resgastes efetuados | E17: -74165624 | F17: =E17+'Saldos - 01-2025'!F17 -> -1.2425557e+08
B18: 3.3 (-) Ajuste VAAR - FNDE | E18: 0 | F18: =E18+'Saldos - 01-2025'!F18 -> -164645.69
B19: 3. Total Disponibizado( 1 - 3.0- 3.1 - 3.2 -3.3 - 3.4 ) | E19: =SUM(E14:E18) -> 1.115289e+08 | F19: =SUM(F14:F18) -> 2.0446494e+08
B21: 4. Saídas | E21: Valores do Mês | F21: Acumulado
B22: 4.1 Cota DAF Deb | E22: 42531.54 | F22: =E22+'Saldos - 01-2025'!F22 -> 80103.36
B23: 4.2 O.B.s Canceladas | F23: =E23+'Saldos - 01-2025'!F23 -> 0
B24: 4.3.1 Folha de Pagamento - Encargos e Identificados por RE | E24: 40814618 | F24: =E24+'Saldos - 01-2025'!F24 -> 40893717
B25: 4.3.2 Folha de Pagamento - Folha 01/2025 | E25: 0 | F25: =E25+'Saldos - 01-2025'!F25 -> 34311367
B26: 4.3.3 Folha de Pagamento - Folha 02/2025 | E26: 34175582 | F26: =E26 -> 34175582
B27: 4.3.4 Folha de Pagamento - Férias | E27: 0 | F27: =E27+'Saldos - 01-2025'!F26 -> 15697876
B28: 4.3.5 Ajuste VAAR | E28: 0 | F28: =E28+'Saldos - 01-2025'!F27 -> 164645.69
B29: 4.3.6 GRU-GUIA RECOLHIM. UNIAO | E29: 667.56 | F29: =E29+'Saldos - 01-2025'!F28 -> 1335.12
B30: 4.3.7 Pagamentos Diversos - Folha | E30: 10029.56 | F30: =E30 -> 10029.56
B31: 4.4 Tarifa bancária | E31: 1831.28 | F31: =E31+'Saldos - 01-2025'!F29 -> 7459.99
B32: 4.5 (-) Aplicações Efetuadas | E32: 1.1069191e+08 | F32: =E32+'Saldos - 01-2025'!F30 -> 2.0362326e+08
B33: 5. Total Geral das Saídas | E33: =SUM(E22:E32) -> 1.8573717e+08 | F33: =SUM(F22:F32) -> 3.2896537e+08
B34: 6.1 (-) Cota DAF Deb | E34: =-E22 -> -42531.54 | F34: =E34+'Saldos - 01-2025'!F32 -> -80103.36
B35: 6.2 (-) Aplicações Efetuadas | E35: =-E32 -> -1.1069191e+08 | F35: =E35+'Saldos - 01-2025'!F33 -> -2.0362326e+08
B36: 6.3 (-) O.B.s Canceladas | E36: -111.18 | F36: =E36+'Saldos - 01-2025'!F34 -> -111.18
B37: 6.4 (-) Tarifa bancária | E37: =-E31 -> -1831.28 | F37: =E37+'Saldos - 01-2025'!F35 -> -7459.99
B38: 6.5 (-) Pagamento Folha não regularizado | E38: =-E26 -> -34175582 | F38: =E38 -> -34175582
B39: 6.6 (-) Ajustes VAAR | E39: 0 | F39: =E39+'Saldos - 01-2025'!F38 -> -164645.69
B40: 6.7 (-) Pagamentos Diversos | E40: =-E30 -> -10029.56 | F40: =E40 -> -10029.56
B41: 6.7 (+) Regularização de Folha e não Pago | E41: 0 | F41: =(E41+'Saldos - 01-2025'!F37) -> 13294.61
B42: 6.8 (-) GRU Paga e Não Regularizada | E42: -667.56 | F42: =E42 -> -667.56
B43: Despesa Total do Mês ( confere com o relatório de execução financeira do SEAFI ) | E43: =SUM(E33:E42) -> 40814507 | F43: =SUM(F33:F42) -> 90916811
B45: CONTA INVESTIMENTO
B46: saldo Inicial | E46: 58872254
B47: Aplicação | E47: 1.1069191e+08
B48: Resgaste | E48: 74165624
B49: Rendimento Bruto | E49: 649670.6
B50: Saldo Atual | E50: =E46+E47-E48+E49 -> 96048208

Sheet REF - Março
D2: =SUBTOTAL(9,D4:D69) -> 34317010
A3: PD | B3: OB | C3: Credor | D3: 3 - Março | E3: Mês de Ocorrência | F3: RE | G3: GD
A4: 2025PD01304 | B4: 2025OB03433 | C4: PF0000023 - FOLHA DE PAGAMENTO | D4: 333.78 | E4: Fevereiro
A5: 2025PD01305 | B5: 2025OB03434 | C5: PF0000023 - FOLHA DE PAGAMENTO | D5: 333.78 | E5: Fevereiro
A6: 2025PD01183 | B6: 2025OB01123 | C6: PF0000023 - FOLHA DE PAGAMENTO | D6: 333.78 | F6: 2025RE00070
A7: 2025PD02593 | B7: 2025OB03435 | C7: PF0000023 - FOLHA DE PAGAMENTO | D7: 333.78 | E7: Março
A8: 2025PD02594 | B8: 2025OB03436 | C8: PF0000023 - FOLHA DE PAGAMENTO | D8: 333.78 | E8: Março
A9: 2025PD03570 | B9: 2025OB03605 | C9: PF0000023 - FOLHA DE PAGAMENTO | D9: 36928.09 | E9: Folha - 02/2025
A10: 2025PD03571 | B10: 2025OB03606 | C10: PF0000023 - FOLHA DE PAGAMENTO | D10: 861371.64 | E10: Folha - 02/2025
A11: 2025PD01035 | B11: 2025OB01014 | C11: PF0000023 - FOLHA DE PAGAMENTO | D11: 19.58 | F11: 2025RE00061
A12: 2025PD01036 | B12: 2025OB01015 | C12: PF0000023 - FOLHA DE PAGAMENTO | D12: 176 | F12: 2025RE00061
A13: 2025PD01038 | B13: 2025OB01016 | C13: PF0000023 - FOLHA DE PAGAMENTO | D13: 93 | F13: 2025RE00062
A14: 2025PD01039 | B14: 2025OB01017 | C14: PF0000023 - FOLHA DE PAGAMENTO | D14: 20848.87 | F14: 2025RE00061
A15: 2025PD01040 | B15: 2025OB01018 | C15: PF0000023 - FOLHA DE PAGAMENTO | D15: 229 | F15: 2025RE00061
A16: 2025PD01041 | B16: 2025OB01019 | C16: PF0000023 - FOLHA DE PAGAMENTO | D16: 195 | F16: 2025RE00061
A17: 2025PD01042 | B17: 2025OB01020 | C17: PF0000023 - FOLHA DE PAGAMENTO | D17: 9804.94 | F17: 2025RE00061
A18: 2025PD01043 | B18: 2025OB01021 | C18: PF0000023 - FOLHA DE PAGAMENTO | D18: 2050.26 | F18: 2025RE00061
A19: 2025PD01044 | B19: 2025OB01022 | C19: PF0000023 - FOLHA DE PAGAMENTO | D19: 726074.89 | F19: 2025RE00061
A20: 2025PD01045 | B20: 2025OB01023 | C20: PF0000023 - FOLHA DE PAGAMENTO | D20: 348118.74 | F20: 2025RE00061
A21: 2025PD01046 | B21: 2025OB01024 | C21: PF0000023 - FOLHA DE PAGAMENTO | D21: 48628.7 | F21: 2025RE00061
A22: 2025PD01048 | B22: 2025OB01025 | C22: PF0000023 - FOLHA DE PAGAMENTO | D22: 327.45 | F22: 2025RE00061
... A42: 2025PD01382 | B42: 2025OB01432 | C42: PF0000023 - FOLHA DE PAGAMENTO | D42: 19479.1 | F42: 2025RE00077
A43: 2025PD03557 | B43: 2025OB03505 | C43: PF0000023 - FOLHA DE PAGAMENTO | D43: 16792661 | E43: Folha - 02/2025
A44: 2025PD03253 | B44: 2025OB03265 | C44: PF0000023 - FOLHA DE PAGAMENTO | D44: 333.78 | E44: Março
A45: 2025PD03480 | B45: 2025OB03437 | C45: PF0000023 - FOLHA DE PAGAMENTO | D45: 37214.98 | E45: Folha - 03/2025
A46: 2025PD03481 | B46: 2025OB03438 | C46: PF0000023 - FOLHA DE PAGAMENTO | D46: 854057.43 | E46: Folha - 03/2025
A47: 2025PD03482 | B47: 2025OB03448 | C47: PF0000023 - FOLHA DE PAGAMENTO | D47: 9119273.7 | E47: Folha - 03/2025
A48: 2025PD03560 | B48: 2025OB03508 | C48: PF0000023 - FOLHA DE PAGAMENTO | D48: 13457.07 | E48: Folha - 02/2025
A49: 2025PD03485 | B49: 2025OB03451 | C49: PF0000023 - FOLHA DE PAGAMENTO | D49: 180 | E49: Folha - 03/2025
A50: 2025PD03562 | B50: 2025OB03510 | C50: PF0000023 - FOLHA DE PAGAMENTO | D50: 1991924.1 | E50: Folha - 02/2025
A51: 2025PD03486 | B51: 2025OB03452 | C51: PF0000023 - FOLHA DE PAGAMENTO | D51: 2579108.5 | E51: Folha - 03/2025
A52: 2025PD01206 | B52: 2025OB01124 | C52: 03281445000185 - AMAPÁ PREVIDÊNCIA | D52: 2761697.8 | F52: 2025RE00070
A53: 2025PD01207 | B53: 2025OB01125 | C53: 03281445000185 - AMAPÁ PREVIDÊNCIA | D53: 2705928.8 | F53: 2025RE00070
A54: 2025PD03564 | B54: 2025OB03512 | C54: PF0000023 - FOLHA DE PAGAMENTO | D54: 2232230 | E54: Folha - 02/2025
A55: 2025PD03487 | B55: 2025OB03453 | C55: PF0000023 - FOLHA DE PAGAMENTO | D55: 2206423.2 | E55: Folha - 03/2025
A56: 2025PD03558 | B56: 2025OB03506 | C56: PF0000023 - FOLHA DE PAGAMENTO | D56: 4685774.1 | E56: Folha - 02/2025
A57: 2025PD03483 | B57: 2025OB03449 | C57: PF0000023 - FOLHA DE PAGAMENTO | D57: 4652945 | E57: Folha - 03/2025
A58: 2025PD01208 | B58: 2025OB01126 | C58: 03281445000185 - AMAPÁ PREVIDÊNCIA | D58: 602213.03 | F58: 2025RE00070
A59: 2025PD01130 | B59: 2025OB01121 | C59: PF0000023 - FOLHA DE PAGAMENTO | D59: 2761697.8 | F59: 2025RE00070
A60: 2025PD01131 | B60: 2025OB01122 | C60: PF0000023 - FOLHA DE PAGAMENTO | D60: 5110039.1 | F60: 2025RE00070
A61: 2025PD03559 | B61: 2025OB03507 | C61: PF0000023 - FOLHA DE PAGAMENTO | D61: 6148689.8 | E61: Folha - 02/2025
A62: 2025PD03484 | B62: 2025OB03450 | C62: PF0000023 - FOLHA DE PAGAMENTO | D62: 13922198 | E62: Folha - 03/2025
A63: 2025PD01383 | B63: 2025OB01433 | C63: 00394460005887 - SECRETARIA DA RECEITA FEDERAL DO BRASIL (MINISTÉRIO DA FAZENDA) | D63: 49397.34 | F63: 2025RE00077
A64: 2025PD01384 | B64: 2025OB01434 | C64: 00394460005887 - SECRETARIA DA RECEITA FEDERAL DO BRASIL (MINISTÉRIO DA FAZENDA) | D64: 4939.73 | F64: 2025RE00077
A65: 2025PD03561 | B65: 2025OB03509 | C65: PF0000023 - FOLHA DE PAGAMENTO | D65: 5767.32 | E65: Folha - 02/2025
A66: 2025PD03563 | B66: 2025OB03511 | C66: PF0000023 - FOLHA DE PAGAMENTO | D66: 469000 | E66: Folha - 02/2025
A67: 2025PD01209 | B67: 2025OB01127 | C67: 03281445000185 - AMAPÁ PREVIDÊNCIA | D67: 1801897.3 | F67: 2025RE00070
A68: 2025PD03565 | B68: 2025OB03513 | C68: PF0000023 - FOLHA DE PAGAMENTO | D68: 956669.99 | E68: Folha - 02/2025
A69: 2025PD03488 | B69: 2025OB03454 | C69: PF0000023 - FOLHA DE PAGAMENTO | D69: 945609.95 | E69: Folha - 03/2025
D70: 1.0916224e+08

Sheet Detalhamento RE - 2º Bimestre
A2: TOTAL | B2: Data | C2: Nº RE | D2: Nº OB | E2: DESCRIÇÃO | F2: DETALHAMENTO | G2: =SUM(G3:G27) -> 4987406.9 | H2: Nº GD
A3: Vlr Individual | B3: 45723 | C3: 2025RE00061 | D3: 2025OB01014 | E3: Folha de Pagamento | F3: ALLIANZ SEGUROS S.A | G3: 19.58
A4: Vlr Individual | B4: 45723 | C4: 2025RE00061 | D4: 2025OB01015 | E4: Folha de Pagamento | F4: ASPA MENSALIDADE | G4: 176
A5: Vlr Individual | B5: 45723 | C5: 2025RE00061 | D5: 2025OB01017 | E5: Folha de Pagamento | F5: ASPEB | G5: 20848.87
A6: Vlr Individual | B6: 45723 | C6: 2025RE00061 | D6: 2025OB01018 | E6: Folha de Pagamento | F6: ASS.ASSIST.FUNC.PUBLICO MENSALIDADE | G6: 229
A7: Vlr Individual | B7: 45723 | C7: 2025RE00061 | D7: 2025OB01019 | E7: Folha de Pagamento | F7: ASSEGUP MENS | G7: 195
A8: Vlr Individual | B8: 45723 | C8: 2025RE00061 | D8: 2025OB01020 | E8: Folha de Pagamento | F8: HSBC BAMERINDUS SEGUROS | G8: 9804.94
A9: Vlr Individual | B9: 45723 | C9: 2025RE00061 | D9: 2025OB01021 | E9: Folha de Pagamento | F9: BANCO BMG S/A | G9: 2050.26
A10: Vlr Individual | B10: 45723 | C10: 2025RE00061 | D10: 2025OB01022 | E10: Folha de Pagamento | F10: BANCO MASTER S.A | G10: 726074.89
A11: Vlr Individual | B11: 45723 | C11: 2025RE00061 | D11: 2025OB01023 | E11: Folha de Pagamento | F11: BANCO MASTER S.A | G11: 348118.74
A12: Vlr Individual | B12: 45723 | C12: 2025RE00061 | D12: 2025OB01024 | E12: Folha de Pagamento | F12: BANCO OLE BONSUCESSO CONSIGNADO S/A | G12: 48628.7
A13: Vlr Individual | B13: 45723 | C13: 2025RE00061 | D13: 2025OB01025 | E13: Folha de Pagamento | F13: BANCO CRUZEIRO DO SUL S/A | G13: 327.45
A14: Vlr Individual | B14: 45723 | C14: 2025RE00061 | D14: 2025OB01026 | E14: Folha de Pagamento | F14: BANCO INDUSTRIAL DO BRASIL S/A - BI | G14: 393757.5
... A22: Vlr Individual | B22: 45723 | C22: 2025RE00061 | D22: 2025OB01036 | E22: Folha de Pagamento | F22: AGENCIA DE FOMENTO DO AMAPA S/A AFAP | G22: 1882.48
A23: Vlr Individual | B23: 45723 | C23: 2025RE00061 | D23: 2025OB01037 | E23: Folha de Pagamento | F23: R.S.P.P.ASS.PREV.PRIVADA | G23: 111.18 | H23: 2025GD00009
A24: Vlr Individual | B24: 45723 | C24: 2025RE00061 | D24: 2025OB01038 | E24: Folha de Pagamento | F24: SINSEPEAP-SIND.SERV.PUB.EDUC.AP | G24: 183951.72
A25: Vlr Individual | B25: 45723 | C25: 2025RE00061 | D25: 2025OB01039 | E25: Folha de Pagamento | F25: SINDICATO DOS EMPREG. EM EMP. DE PROC. DE DADOS... | G25: 13.09
A26: Vlr Individual | B26: 45723 | C26: 2025RE00061 | D26: 2025OB01041 | E26: Folha de Pagamento | F26: SUL AMERICA SEGUROS DE VIDA E PREVIDENCIA S/A. | G26: 320.23
A27: Vlr Individual | B27: 45723 | C27: 2025RE00061 | D27: 2025OB01043 | E27: Folha de Pagamento | F27: PDT CONTRIBUIÇÃO | G27: 470.99
A29: TOTAL | B29: Data | C29: Nº RE | D29: Nº OB | E29: DESCRIÇÃO | F29: DETALHAMENTO | G29: =SUM(G30:G34) -> 12139973 | H29: Nº GD
A30: Vlr Individual | B30: 45723 | C30: 2025RE00062 | D30: 2025OB01016 | E30: Folha de Pagamento | F30: ASPBRAS-ASSOC.DOS SERV.PUBLICOS BRASILEIROS. | G30: 93
A31: Vlr Individual | B31: 45723 | C31: 2025RE00062 | D31: 2025OB01029 | E31: Folha de Pagamento | F31: BANCO DO BRASIL S/A | G31: 8643454.1
A32: Vlr Individual | B32: 45723 | C32: 2025RE00062 | D32: 2025OB01031 | E32: Folha de Pagamento | F32: GOVERNO DO ESTADO DO AMAPA | G32: 3409140
A33: Vlr Individual | B33: 45723 | C33: 2025RE00062 | D33: 2025OB01040 | E33: Folha de Pagamento | F33: SIND. DOS SERVIDORES GRUPO GESTÃO ADM DO EST. DO AP - SINSGAAP | G33: 478.49
A34: Vlr Individual | B34: 45723 | C34: 2025RE00062 | D34: 2025OB01042 | E34: Folha de Pagamento | F34: UNIODONTO | G34: 86807
A36: TOTAL | B36: Data | C36: Nº RE | D36: Nº OB | E36: DESCRIÇÃO | F36: DETALHAMENTO | G36: =SUM(G37:G45) -> 23448006 | H36: Nº GD
A37: Vlr Individual | B37: 45726 | C37: 2025RE00070 | D37: 2025OB01119 | E37: Folha de Pagamento | F37: GOVERNO DO ESTADO DO AMAPA | G37: 7701836.7
A38: Vlr Individual | B38: 45726 | C38: 2025RE00070 | D38: 2025OB01120 | E38: Folha de Pagamento | F38: GOVERNO DO ESTADO DO AMAPA | G38: 2361.69
A39: Vlr Individual | B39: 45726 | C39: 2025RE00070 | D39: 2025OB01121 | E39: Folha de Pagamento | F39: AMAPÁ PREVIDÊNCIA | G39: 2761697.8
A40: Vlr Individual | B40: 45726 | C40: 2025RE00070 | D40: 2025OB01122 | E40: Folha de Pagamento | F40: AMAPÁ PREVIDÊNCIA | G40: 5110039.1
A41: Vlr Individual | B41: 45726 | C41: 2025RE00070 | D41: 2025OB01123 | E41: Folha de Pagamento | F41: GOVERNO DO ESTADO DO AMAPA | G41: 333.78
A42: Vlr Individual | B42: 45726 | C42: 2025RE00070 | D42: 2025OB01124 | E42: Folha de Pagamento | F42: AMAPÁ PREVIDÊNCIA | G42: 2761697.8
A43: Vlr Individual | B43: 45726 | C43: 2025RE00070 | D43: 2025OB01125 | E43: Folha de Pagamento | F43: AMAPÁ PREVIDÊNCIA | G43: 2705928.8
A44: Vlr Individual | B44: 45726 | C44: 2025RE00070 | D44: 2025OB01126 | E44: Folha de Pagamento | F44: AMAPÁ PREVIDÊNCIA | G44: 602213.03
A45: Vlr Individual | B45: 45726 | C45: 2025RE00070 | D45: 2025OB01127 | E45: Folha de Pagamento | F45: AMAPÁ PREVIDÊNCIA | G45: 1801897.3
A47: TOTAL | B47: Data | C47: Nº RE | D47: Nº OB | E47: DESCRIÇÃO | F47: DETALHAMENTO | G47: =SUM(G48:G50) -> 73816.17 | H47: Nº GD
A48: Vlr Individual | B48: 45730 | C48: 2025RE00077 | D48: 2025OB01432 | E48: Folha de Pagamento | F48: GOVERNO DO ESTADO DO AMAPA | G48: 19479.1
A49: Vlr Individual | B49: 45730 | C49: 2025RE00077 | D49: 2025OB01433 | E49: Folha de Pagamento | F49: AMAPÁ PREVIDÊNCIA | G49: 49397.34
A50: Vlr Individual | B50: 45730 | C50: 2025RE00077 | D50: 2025OB01434 | E50: Folha de Pagamento | F50: AMAPÁ PREVIDÊNCIA | G50: 4939.73
A52: TOTAL | B52: Data | C52: Nº RE | D52: Nº OB | E52: DESCRIÇÃO | F52: DETALHAMENTO | G52: =SUM(G53:G57) -> 320307.99 | H52: Nº GD
A53: Vlr Individual | B53: 45743 | C53: 2025RE00129 | D53: 2025OB03141 | E53: Folha de Pagamento | F53: GOVERNO DO ESTADO DO AMAPA | G53: 4199.28
A54: Vlr Individual | B54: 45743 | C54: 2025RE00129 | D54: 2025OB03142 | E54: Folha de Pagamento | F54: GOVERNO DO ESTADO DO AMAPA | G54: 84917.23
A55: Vlr Individual | B55: 45743 | C55: 2025RE00129 | D55: 2025OB03143 | E55: Folha de Pagamento | F55: GOVERNO DO ESTADO DO AMAPA | G55: 107683.65
A56: Vlr Individual | B56: 45743 | C56: 2025RE00129 | D56: 2025OB03144 | E56: Folha de Pagamento | F56: GOVERNO DO ESTADO DO AMAPA | G56: 72817.41
A57: Vlr Individual | B57: 45743 | C57: 2025RE00129 | D57: 2025OB03145 | E57: Folha de Pagamento | F57: GOVERNO DO ESTADO DO AMAPA | G57: 50690.42
A59: TOTAL | B59: Data | C59: Nº RE | D59: Nº OB | E59: DESCRIÇÃO | F59: DETALHAMENTO | G59: =SUM(G60:G70) -> 460041.44 | H59: Nº GD
A60: Vlr Individual | B60: 45750 | C60: 2025RE00144 | D60: 2025OB03568 | E60: Folha de Pagamento | F60: ALLIANZ SEGUROS S.A | G60: 19.58
A61: Vlr Individual | B61: 45750 | C61: 2025RE00144 | D61: 2025OB03569 | E61: Folha de Pagamento | F61: ASPA MENSALIDADE | G61: 176
A62: Vlr Individual | B62: 45750 | C62: 2025RE00144 | D62: 2025OB03570 | E62: Folha de Pagamento | F62: ASPBRAS-ASSOC.DOS SERV.PUBLICOS BRASILEIROS. | G62: 88
A63: Vlr Individual | B63: 45750 | C63: 2025RE00144 | D63: 2025OB03571 | E63: Folha de Pagamento | F63: ASPEB | G63: 20498.9
A64: Vlr Individual | B64: 45750 | C64: 2025RE00144 | D64: 2025OB03572 | E64: Folha de Pagamento | F64: ASS.ASSIST.FUNC.PUBLICO MENSALIDADE | G64: 229
A65: Vlr Individual | B65: 45750 | C65: 2025RE00144 | D65: 2025OB03573 | E65: Folha de Pagamento | F65: ASSEGUP MENS | G65: 180
A66: Vlr Individual | B66: 45750 | C66: 2025RE00144 | D66: 2025OB03574 | E66: Folha de Pagamento | F66: HSBC BAMERINDUS SEGUROS | G66: 9698.14
A67: Vlr Individual | B67: 45750 | C67: 2025RE00144 | D67: 2025OB03575 | E67: Folha de Pagamento | F67: BANCO BMG S/A | G67: 1763.47
A68: Vlr Individual | B68: 45750 | C68: 2025RE00144 | D68: 2025OB03576 | E68: Folha de Pagamento | F68: BANCO OLE BONSUCESSO CONSIGNADO S/A | G68: 46332.19
A69: Vlr Individual | B69: 45750 | C69: 2025RE00144 | D69: 2025OB03577 | E69: Folha de Pagamento | F69: BANCO CRUZEIRO DO SUL S/A | G69: 302.39
A70: Vlr Individual | B70: 45750 | C70: 2025RE00144 | D70: 2025OB03578 | E70: Folha de Pagamento | F70: BANCO INDUSTRIAL DO BRASIL S/A - BI | G70: 380753.77
A72: TOTAL | B72: Data | C72: Nº RE | D72: Nº OB | E72: DESCRIÇÃO | F72: DETALHAMENTO | G72: =SUM(G73:G97) -> 31900062 | H72: Nº GD
A73: Vlr Individual | B73: 45751 | C73: 2025RE00159 | D73: 2025OB03979 | E73: Folha de Pagamento | F73: BANCO PANAMERICANO S/A | G73: 745
A74: Vlr Individual | B74: 45751 | C74: 2025RE00159 | D74: 2025OB03980 | E74: Folha de Pagamento | F74: BANCO RURAL- EM LIQUIDAÇÃO EXTRAJUDICIAL | G74: 84
A75: Vlr Individual | B75: 45751 | C75: 2025RE00159 | D75: 2025OB03981 | E75: Folha de Pagamento | F75: BANCO DO BRASIL S/A | G75: 8637925.9
A76: Vlr Individual | B76: 45751 | C76: 2025RE00159 | D76: 2025OB03982 | E76: Folha de Pagamento | F76: CAPEMISA SEGURADORA DE VIDA E PRESIDENCIA S/A | G76: 4279.24
A77: Vlr Individual | B77: 45751 | C77: 2025RE00159 | D77: 2025OB03983 | E77: Folha de Pagamento | F77: GOVERNO DO ESTADO DO AMAPA | G77: 3446798.1
A78: Vlr Individual | B78: 45751 | C78: 2025RE00159 | D78: 2025OB03984 | E78: Folha de Pagamento | F78: BANCO FINASA BMC S/A | G78: 100.68
A79: Vlr Individual | B79: 45751 | C79: 2025RE00159 | D79: 2025OB03985 | E79: Folha de Pagamento | F79: BANCO SANTANDER BANESPA S.A | G79: 3124546.2
A80: Vlr Individual | B80: 45751 | C80: 2025RE00159 | D80: 2025OB03986 | E80: Folha de Pagamento | F80: BANCO MASTER S.A | G80: 346334.25
A81: Vlr Individual | B81: 45751 | C81: 2025RE00159 | D81: 2025OB03987 | E81: Folha de Pagamento | F81: BANCO MASTER S.A | G81: 358377.14
A82: Vlr Individual | B82: 45751 | C82: 2025RE00159 | D82: 2025OB03988 | E82: Folha de Pagamento | F82: AGENCIA DE FOMENTO DO AMAPA S/A AFAP | G82: 135238
A83: Vlr Individual | B83: 45751 | C83: 2025RE00159 | D83: 2025OB03990 | E83: Folha de Pagamento | F83: AGENCIA DE FOMENTO DO AMAPA S/A AFAP | G83: 2202.94
A84: Vlr Individual | B84: 45751 | C84: 2025RE00159 | D84: 2025OB03991 | E84: Folha de Pagamento | F84: R.S.P.P.ASS.PREV.PRIVADA | G84: 103.93 | H84: 2025GD00027
A85: Vlr Individual | B85: 45751 | C85: 2025RE00159 | D85: 2025OB03992 | E85: Folha de Pagamento | F85: SINSEPEAP-SIND.SERV.PUB.EDUC.AP | G85: 181029.17
A86: Vlr Individual | B86: 45751 | C86: 2025RE00159 | D86: 2025OB03993 | E86: Folha de Pagamento | F86: SINDICATO DOS EMPREG. EM EMP. DE PROC. DE DADOS... | G86: 13.09
A87: Vlr Individual | B87: 45751 | C87: 2025RE00159 | D87: 2025OB03994 | E87: Folha de Pagamento | F87: SIND. DOS SERVIDORES GRUPO GESTÃO ADM DO EST. D... | G87: 478.49
A88: Vlr Individual | B88: 45751 | C88: 2025RE00159 | D88: 2025OB03995 | E88: Folha de Pagamento | F88: SUL AMERICA SEGUROS DE VIDA E PREVIDENCIA S/A. | G88: 320.23
A89: Vlr Individual | B89: 45751 | C89: 2025RE00159 | D89: 2025OB03996 | E89: Folha de Pagamento | F89: UNIODONTO | G89: 85378.5
A90: Vlr Individual | B90: 45751 | C90: 2025RE00159 | D90: 2025OB03997 | E90: Folha de Pagamento | F90: PDT CONTRIBUIÇÃO | G90: 470.99
A91: Vlr Individual | B91: 45751 | C91: 2025RE00159 | D91: 2025OB03999 | E91: Folha de Pagamento | F91: GOVERNO DO ESTADO DO AMAPA | G91: 2414.3
A92: Vlr Individual | B92: 45751 | C92: 2025RE00159 | D92: 2025OB04000 | E92: Folha de Pagamento | F92: AMAPÁ PREVIDÊNCIA | G92: 2706694.4
A93: Vlr Individual | B93: 45751 | C93: 2025RE00159 | D93: 2025OB04001 | E93: Folha de Pagamento | F93: AMAPÁ PREVIDÊNCIA | G93: 5079916.6
A94: Vlr Individual | B94: 45751 | C94: 2025RE00159 | D94: 2025OB04002 | E94: Folha de Pagamento | F94: AMAPÁ PREVIDÊNCIA | G94: 2706694.4
A95: Vlr Individual | B95: 45751 | C95: 2025RE00159 | D95: 2025OB04003 | E95: Folha de Pagamento | F95: AMAPÁ PREVIDÊNCIA | G95: 2701804.6
A96: Vlr Individual | B96: 45751 | C96: 2025RE00159 | D96: 2025OB04004 | E96: Folha de Pagamento | F96: AMAPÁ PREVIDÊNCIA | G96: 595700.62
A97: Vlr Individual | B97: 45751 | C97: 2025RE00159 | D97: 2025OB04005 | E97: Folha de Pagamento | F97: AMAPÁ PREVIDÊNCIA | G97: 1782411.4
A99: TOTAL | B99: Data | C99: Nº RE | D99: Nº OB | E99: DESCRIÇÃO | F99: DETALHAMENTO | G99: =SUM(G100:G101) -> 7641042 | H99: Nº GD
A100: Vlr Individual | B100: 45751 | C100: 2025RE00160 | D100: 2025OB03989 | E100: Folha de Pagamento | F100: AGENCIA DE FOMENTO DO AMAPA S/A AFAP | G100: 25119.06
A101: Vlr Individual | B101: 45751 | C101: 2025RE00160 | D101: 2025OB03998 | E101: Folha de Pagamento | F101: GOVERNO DO ESTADO DO AMAPA | G101: 7615923
A103: TOTAL | B103: Data | C103: Nº RE | D103: Nº OB | E103: DESCRIÇÃO | F103: DETALHAMENTO | G103: =SUM(G104:G108) -> 331945.21 | H103: Nº GD
A104: Vlr Individual | B104: 45776 | C104: 2025RE00358 | D104: 2025OB09291 | E104: Folha de Pagamento | F104: GOVERNO DO ESTADO DO AMAPA | G104: 4434.92
A105: Vlr Individual | B105: 45776 | C105: 2025RE00358 | D105: 2025OB09292 | E105: Folha de Pagamento | F105: GOVERNO DO ESTADO DO AMAPA | G105: 86036.02
A106: Vlr Individual | B106: 45776 | C106: 2025RE00358 | D106: 2025OB09293 | E106: Folha de Pagamento | F106: GOVERNO DO ESTADO DO AMAPA | G106: 112401.94
A107: Vlr Individual | B107: 45776 | C107: 2025RE00358 | D107: 2025OB09294 | E107: Folha de Pagamento | F107: GOVERNO DO ESTADO DO AMAPA | G107: 76661.3
A108: Vlr Individual | B108: 45776 | C108: 2025RE00358 | D108: 2025OB09295 | E108: Folha de Pagamento | F108: GOVERNO DO ESTADO DO AMAPA | G108: 52411.03

Sheet Extrato 03-2025
A1: Extrato Conta Corrente
A2: Agencia | C2: =SUBTOTAL(9,C3:C78) -> 1.3530326e+08
A3: Data | B3: Historico | C3: Valor R$ | D3: Inf. | E3: Detalhamento Hist. | F3: Detalhamentos
A4: 07/03/2025 | B4: ORDEM BANC CANCELADA | C4: 111.18 | D4: C
A5: 07/03/2025 | B5: Emissão Ordem Bancária | C5: 4987406.9 | D5: D | E5: Folha de Pagamento | F5: 2025RE00061
A6: 07/03/2025 | B6: Emissão Ordem Bancária | C6: 12139973 | D6: D | E6: Folha de Pagamento | F6: 2025RE00062
A7: 07/03/2025 | B7: Resgate Automático | C7: 17127268 | D7: C | E7: Resgate Automático
A8: 10/03/2025 | B8: ITR | C8: 480.27 | D8: C | E8: Transferência Constitucional - FUNDEB
A9: 10/03/2025 | B9: FPE/FPM | C9: 970971.61 | D9: C | E9: Transferência Constitucional - FUNDEB
A10: 10/03/2025 | B10: FPE/FPM | C10: 2257223.4 | D10: C | E10: Transferência Constitucional - FUNDEB
A11: 10/03/2025 | B11: FPE/FPM | C11: 25914802 | D11: C | E11: Transferência Constitucional - FUNDEB
A12: 10/03/2025 | B12: FPE/FPM | C12: 11423.16 | D12: C | E12: Transferência Constitucional - FUNDEB
A13: 10/03/2025 | B13: IPI/EXPORTACAO | C13: 26118.74 | D13: C | E13: IPI/EXPORTACAO - Cota Débito
A14: 10/03/2025 | B14: IPI/EXPORTACAO | C14: 15152.8 | D14: C | E14: Transferência Constitucional - FUNDEB
A15: 10/03/2025 | B15: COTA DAF-DEBITO | C15: 26118.74 | D15: D | E15: IPI/EXPORTACAO - Cota Débito
A16: 10/03/2025 | B16: Emissão Ordem Bancária | C16: 23448006 | D16: D | E16: Folha de Pagamento | F16: 2025RE00070
A17: 10/03/2025 | B17: BB-APLIC C.PRZ-APL.AUT | C17: 5722047.8 | D17: D | E17: Aplicação Financeira
A18: 13/03/2025 | B18: Folha de Pagamento | C18: 2548.93 | D18: D
A19: 13/03/2025 | B19: Resgate Automático | C19: 2548.93 | D19: C | E19: Resgate Automático
A20: 14/03/2025 | B20: Emissão Ordem Bancária | C20: 73816.17 | D20: D | E20: Folha de Pagamento | F20: 2025RE00077
A21: 14/03/2025 | B21: Resgate Automático | C21: 73816.17 | D21: C | E21: Resgate Automático
A22: 18/03/2025 | B22: IPVA | C22: 513105.27 | D22: C | E22: Transferência Constitucional - FUNDEB
A23: 18/03/2025 | B23: IPVA | C23: 347235.51 | D23: C | E23: Transferência Constitucional - FUNDEB
A24: 18/03/2025 | B24: RECEBIMENTO DE ICMS | C24: 2663359.6 | D24: C | E24: Transferência Constitucional - FUNDEB
A25: 18/03/2025 | B25: RECEBIMENTO DE ICMS | C25: 1605970.9 | D25: C | E25: Transferência Constitucional - FUNDEB
A26: 18/03/2025 | B26: BB-APLIC C.PRZ-APL.AUT | C26: 5129671.2 | D26: D | E26: Aplicação Financeira
A27: 20/03/2025 | B27: ITR | C27: 49 | D27: C | E27: Transferência Constitucional - FUNDEB
A28: 20/03/2025 | B28: FPE/FPM | C28: 208080.3 | D28: C | E28: Transferência Constitucional - FUNDEB
A29: 20/03/2025 | B29: FPE/FPM | C29: 483725.54 | D29: C | E29: Transferência Constitucional - FUNDEB
A30: 20/03/2025 | B30: FPE/FPM | C30: 5579351.7 | D30: C | E30: Transferência Constitucional - FUNDEB
A31: 20/03/2025 | B31: FPE/FPM | C31: 2447.97 | D31: C | E31: Transferência Constitucional - FUNDEB
A32: 20/03/2025 | B32: IPI/EXPORTACAO | C32: 11434.81 | D32: C | E32: IPI/EXPORTACAO - Cota Débito
... A34: 20/03/2025 | B34: COTA DAF-DEBITO | C34: 11434.81 | D34: D | E34: IPI/EXPORTACAO - Cota Débito
A35: 20/03/2025 | B35: Pagto via Auto-Atend.BB | C35: 333.78 | D35: D | E35: GRU-GUIA RECOLHIM. UNIAO | F35: 2025OB03435
A36: 20/03/2025 | B36: Pagto via Auto-Atend.BB | C36: 333.78 | D36: D | E36: GRU-GUIA RECOLHIM. UNIAO | F36: 2025OB03436
A37: 20/03/2025 | B37: BB-APLIC C.PRZ-APL.AUT | C37: 6279620.8 | D37: D | E37: Aplicação Financeira
A38: 24/03/2025 | B38: IPVA | C38: 1176171.2 | D38: C | E38: Transferência Constitucional - FUNDEB
A39: 24/03/2025 | B39: RECEBIMENTO DE ICMS | C39: 7632815.7 | D39: C | E39: Transferência Constitucional - FUNDEB
A40: 24/03/2025 | B40: BB-APLIC C.PRZ-APL.AUT | C40: 8808986.9 | D40: D | E40: Aplicação Financeira
A41: 26/03/2025 | B41: Pagto via Auto-Atend.BB | C41: 333.78 | D41: D | E41: GRU-GUIA RECOLHIM. UNIAO | F41: 2025OB03607 | G41: Regularizado em Abril
A42: 26/03/2025 | B42: Pagto via Auto-Atend.BB | C42: 333.78 | D42: D | E42: GRU-GUIA RECOLHIM. UNIAO | F42: 2025OB03608 | G42: Regularizado em Abril
A43: 26/03/2025 | B43: Resgate Automático | C43: 667.56 | D43: C | E43: Resgate Automático
A44: 27/03/2025 | B44: Folha de Pagamento | C44: 32564764 | D44: D | E44: Folha - 03/2025 | F44: Folha - 03/2025
A45: 27/03/2025 | B45: Folha de Pagamento | C45: 544599.56 | D45: D | E45: Folha - 03/2025 | F45: Folha - 03/2025
A46: 27/03/2025 | B46: Folha de Pagamento | C46: 284425.26 | D46: D | E46: Folha - 03/2025 | F46: Folha - 03/2025
A47: 27/03/2025 | B47: Folha de Pagamento | C47: 694.48 | D47: D | E47: Folha - 03/2025 | F47: Folha - 03/2025
A48: 27/03/2025 | B48: Folha de Pagamento | C48: 14605.34 | D48: D | E48: Folha - 03/2025 | F48: Folha - 03/2025
A49: 27/03/2025 | B49: Folha de Pagamento | C49: 548540.88 | D49: D | E49: Folha - 03/2025 | F49: Folha - 03/2025
A50: 27/03/2025 | B50: Pagamentos Diversos | C50: 17662.03 | D50: D | E50: Folha - 03/2025 | F50: Folha - 03/2025
A51: 27/03/2025 | B51: Emissão Ordem Bancária | C51: 320307.99 | D51: D | E51: Folha - 03/2025 | F51: Folha - 03/2025
A52: 27/03/2025 | B52: Resgate Automático | C52: 34295599 | D52: C | E52: Resgate Automático
A53: 28/03/2025 | B53: IPVA | C53: 2182854.5 | D53: C | E53: Transferência Constitucional - FUNDEB
A54: 28/03/2025 | B54: RECEBIMENTO DE ICMS | C54: 3007820.3 | D54: C | E54: Transferência Constitucional - FUNDEB
A55: 28/03/2025 | B55: ITR | C55: 111.16 | D55: C | E55: Transferência Constitucional - FUNDEB
A56: 28/03/2025 | B56: FPE/FPM | C56: 990875.33 | D56: C | E56: Transferência Constitucional - FUNDEB
A57: 28/03/2025 | B57: FPE/FPM | C57: 2303493.6 | D57: C | E57: Transferência Constitucional - FUNDEB
A58: 28/03/2025 | B58: FPE/FPM | C58: 25866031 | D58: C | E58: Transferência Constitucional - FUNDEB
A59: 28/03/2025 | B59: FPE/FPM | C59: 11657.34 | D59: C | E59: Transferência Constitucional - FUNDEB
A60: 28/03/2025 | B60: IPI/EXPORTACAO | C60: 8764.56 | D60: C | E60: IPI/EXPORTACAO - Cota Débito
A61: 28/03/2025 | B61: IPI/EXPORTACAO | C61: 5084.76 | D61: C | E61: Transferência Constitucional - FUNDEB
A62: 28/03/2025 | B62: COTA DAF-DEBITO | C62: 8764.56 | D62: D | E62: IPI/EXPORTACAO - Cota Débito
A63: 28/03/2025 | B63: Pagamentos Diversos | C63: 10029.56 | D63: D | E63: Pagamentos Diversos
A64: 28/03/2025 | B64: Folha de Pagamento | C64: 3047.41 | D64: D
A65: 28/03/2025 | B65: Emissão Ordem Bancária | C65: 333.78 | D65: D | E65: Folha de Pagamento | F65: 2025OB03265
A66: 28/03/2025 | B66: Tar Lib/Ant Float Pg Div | C66: 10.47 | D66: D | E66: Tarifa Bancária
A67: 28/03/2025 | B67: Tar Lib/Ant Float Pg Div | C67: 20.05 | D67: D | E67: Tarifa Bancária
A68: 28/03/2025 | B68: BB-APLIC C.PRZ-APL.AUT | C68: 34354486 | D68: D | E68: Aplicação Financeira

Sheet Saldos - 03-2025
B2: CONCILIAÇÃO BANCÁRIA DO EXTRATO BANCÁRIO - MARÇO DE 2025
B4: 1. Ingressos | E4: Valores do Mês | F4: Acumulado
B5: 1.0 IPI - EXP | E5: 73189.58 | F5: =E5+'Saldos - 02-2025'!F5 -> 199764.86
B6: 1.1 VAAR | E6: 0 | F6: =E6+'Saldos - 02-2025'!F6 -> 1477881.8
B7: 1.2 FPE/FPM | E7: 64600083 | F7: =E7+'Saldos - 02-2025'!F7 -> 2.3622387e+08
B8: 1.3 ICMS | E8: 14909966 | F8: =E8+'Saldos - 02-2025'!F8 -> 44506908
B9: 1.4 IPVA | E9: 4219366.5 | F9: =E9+'Saldos - 02-2025'!F9 -> 5975385.4
B10: 1.5 ITCMD | E10: 0 | F10: =E10+'Saldos - 02-2025'!F10 -> 125706.44
B11: 1.6 ITR | E11: 640.43 | F11: =E11+'Saldos - 02-2025'!F11 -> 3416.47
B12: 1.7 ORDEM BANC CANCELADA | E12: 111.18 | F12: =E12+'Saldos - 02-2025'!F12 -> 222.36
B13: 1.8 RESGATE | E13: 51499900 | F13: =E13+'Saldos - 02-2025'!F13 -> 1.7575547e+08
B14: 2 Total das Entradas | E14: =SUM(E5:E13) -> 1.3530326e+08 | F14: =SUM(F5:F13) -> 4.6426863e+08
B15: 3.0 (-) IPI/Cota DAF Deb | E15: -46318.11 | F15: =E15+'Saldos - 02-2025'!F15 -> -126421.47
B16: 3.1 (-) Ordem Bancária Cancelada | E16: =-E12 -> -111.18 | F16: =E16+'Saldos - 02-2025'!F16 -> -222.36
B17: 3.2 (-) Resgastes efetuados | E17: =-E13 -> -51499900 | F17: =E17+'Saldos - 02-2025'!F17 -> -1.7575547e+08
B18: 3.3 (-) Ajuste VAAR - FNDE | F18: =E18+'Saldos - 02-2025'!F18 -> -164645.69
B19: 3. Total Disponibizado( 1 - 3.0- 3.1 - 3.2 -3.3 - 3.4 ) | E19: =SUM(E14:E18) -> 83756928 | F19: =SUM(F14:F18) -> 2.8822187e+08
B21: 4. Saídas | E21: Valores do Mês | F21: Acumulado
B22: 4.1 Cota DAF Deb | E22: 46318.11 | F22: =E22+'Saldos - 02-2025'!F22 -> 126421.47
B23: 4.2 O.B.s Canceladas | E23: 0 | F23: =E23+'Saldos - 02-2025'!F23 -> 0
B24: 4.3.1 Folha de Pagamento - Encargos e Identificados por RE | E24: 40969510 | F24: =E24+'Saldos - 02-2025'!F24 -> 81863227
B25: 4.3.2 Folha de Pagamento - Folha 01/2025 | E25: 0 | F25: =E25+'Saldos - 02-2025'!F25 -> 34311367
B26: 4.3.3 Folha de Pagamento - Folha 02/2025 | E26: 0 | F26: =E26+'Saldos - 02-2025'!F26 -> 34175582
B27: 4.3.4 Folha de Pagamento - Folha 03/2025 | E27: 33980888 | F27: =E27 -> 33980888
B28: 4.3.5 Folha de Pagamento - Férias | E28: 0 | F28: =E28+'Saldos - 02-2025'!F27 -> 15697876
B29: 4.3.6 Ajuste VAAR | F29: =E29+'Saldos - 02-2025'!F28 -> 164645.69
B30: 4.3.7 GRU-GUIA RECOLHIM. UNIAO | E30: 1668.9 | F30: =E30+'Saldos - 02-2025'!F29 -> 3004.02
B31: 4.3.8 Pagamentos Diversos - Folha | E31: 10029.56 | F31: =E31+'Saldos - 02-2025'!F30 -> 20059.12
B32: 4.4 Tarifa bancária | E32: 30.52 | F32: =E32+'Saldos - 02-2025'!F31 -> 7490.51
B33: 4.5 Aplicações Efetuadas | E33: 60294813 | F33: =E33+'Saldos - 02-2025'!F32 -> 2.6391807e+08
B34: 5. Total Geral das Saídas | E34: =SUM(E22:E33) -> 1.3530326e+08 | F34: =SUM(F22:F33) -> 4.6426863e+08 | H34: =E34-E14 -> 0
B35: 6.1 (-) Cota DAF Deb | E35: =-E22 -> -46318.11 | F35: =E35+'Saldos - 02-2025'!F34 -> -126421.47
B36: 6.2 (-) Aplicações Efetuadas | E36: =-E33 -> -60294813 | F36: =E36+'Saldos - 02-2025'!F35 -> -2.6391807e+08
B37: 6.3 (-) O.B.s Canceladas | F37: =E37+'Saldos - 02-2025'!F36 -> -111.18
B38: 6.4 (-) Tarifa bancária | E38: =-E32 -> -30.52 | F38: =E38+'Saldos - 02-2025'!F37 -> -7490.51
B39: 6.5 (-) Pagamento Folha não regularizado | F39: =E39+'Saldos - 02-2025'!F38 -> -34175582
B40: 6.6 (-) Ajustes VAAR | F40: =E40+'Saldos - 02-2025'!F39 -> -164645.69
B41: 6.7 (-) Pagamentos Diversos | E41: -10029.56 | F41: =E41+'Saldos - 02-2025'!F40 -> -20059.12
B42: 6.7 (+) Regularização de Folha e não Pago | E42: 34210176 | F42: =E42+'Saldos - 02-2025'!F41 -> 34223471
B43: 6.8 (-) GRU Paga e Não Regularizada | F43: =E43+'Saldos - 02-2025'!F42 -> -667.56
B44: Despesa Total do Mês ( confere com o relatório de execução financeira do SEAFI ) | E44: =SUM(E34:E43) -> 1.0916224e+08 | F44: =SUM(F34:F43) -> 2.0007905e+08
B46: CONTA INVESTIMENTO
B47: saldo Inicial | E47: ='Saldos - 02-2025'!E50 -> 96048208
B48: Aplicação | E48: 60294813
B49: Resgaste | E49: 51499900
B50: Rendimento Bruto | E50: 663914.5
B51: Saldo Atual | E51: =E47+E48-E49+E50 -> 1.0550704e+08

Sheet REF - Abril
D2: =SUBTOTAL(9,D3:D54) -> 35678021
A3: PD | B3: OB | C3: Credor | D3: 4 - Abril | E3: Mês de Ocorrência | F3: RE | G3: GD
A4: 2025PD03583 | B4: 2025OB03607 | C4: PF0000023 - FOLHA DE PAGAMENTO | D4: 333.78 | E4: Extrato de Março | F4: Março
A5: 2025PD03584 | B5: 2025OB03608 | C5: PF0000023 - FOLHA DE PAGAMENTO | D5: 333.78 | E5: Extrato de Abril | F5: Abril
A6: 2025PD03673 | B6: 2025OB03568 | C6: PF0000023 - FOLHA DE PAGAMENTO | D6: 19.58 | E6: Extrato de Abril | F6: 2025RE00144
A7: 2025PD03677 | B7: 2025OB03569 | C7: PF0000023 - FOLHA DE PAGAMENTO | D7: 176 | E7: Extrato de Abril | F7: 2025RE00144
A8: 2025PD03678 | B8: 2025OB03570 | C8: PF0000023 - FOLHA DE PAGAMENTO | D8: 88 | E8: Extrato de Abril | F8: 2025RE00144
A9: 2025PD03679 | B9: 2025OB03571 | C9: PF0000023 - FOLHA DE PAGAMENTO | D9: 20498.9 | E9: Extrato de Abril | F9: 2025RE00144
A10: 2025PD03680 | B10: 2025OB03572 | C10: PF0000023 - FOLHA DE PAGAMENTO | D10: 229 | E10: Extrato de Abril | F10: 2025RE00144
A11: 2025PD03681 | B11: 2025OB03573 | C11: PF0000023 - FOLHA DE PAGAMENTO | D11: 180 | E11: Extrato de Abril | F11: 2025RE00144
A12: 2025PD03682 | B12: 2025OB03574 | C12: PF0000023 - FOLHA DE PAGAMENTO | D12: 9698.14 | E12: Extrato de Abril | F12: 2025RE00144
A13: 2025PD03683 | B13: 2025OB03575 | C13: PF0000023 - FOLHA DE PAGAMENTO | D13: 1763.47 | E13: Extrato de Abril | F13: 2025RE00144
A14: 2025PD03693 | B14: 2025OB03576 | C14: PF0000023 - FOLHA DE PAGAMENTO | D14: 46332.19 | E14: Extrato de Abril | F14: 2025RE00144
A15: 2025PD03694 | B15: 2025OB03577 | C15: PF0000023 - FOLHA DE PAGAMENTO | D15: 302.39 | E15: Extrato de Abril | F15: 2025RE00144
... A38: 2025PD03838 | B38: 2025OB04001 | C38: PF0000023 - FOLHA DE PAGAMENTO | D38: 5079916.6 | E38: Extrato de Abril | F38: 2025RE00159
A39: 2025PD08332 | B39: 2025OB08957 | C39: PF0000023 - FOLHA DE PAGAMENTO | D39: 18873.57 | E39: Extrato de Abril | F39: Abril | I39: =D39+D43+D44 -> 71493.75
A40: 2025PD10009 | B40: 2025OB09825 | C40: PF0000023 - FOLHA DE PAGAMENTO | D40: 37344.32 | E40: Extrato de Abril | F40: Folha 04-2025
A41: 2025PD10020 | B41: 2025OB09826 | C41: PF0000023 - FOLHA DE PAGAMENTO | D41: 884675.77 | E41: Extrato de Abril | F41: Folha 04-2025
A42: 2025PD10024 | B42: 2025OB09829 | C42: PF0000023 - FOLHA DE PAGAMENTO | D42: 9644740.5 | E42: Extrato de Abril | F42: Folha 04-2025
A43: 2025PD08333 | B43: 2025OB08958 | C43: 00394460005887 - SECRETARIA DA RECEITA FEDERAL DO BRASIL (MINISTÉRIO DA FAZENDA) | D43: 47836.53 | E43: Extrato de Abril | F43: Abril
A44: 2025PD08334 | B44: 2025OB08959 | C44: 00394460005887 - SECRETARIA DA RECEITA FEDERAL DO BRASIL (MINISTÉRIO DA FAZENDA) | D44: 4783.65 | E44: Extrato de Abril | F44: Abril
A45: 2025PD10031 | B45: 2025OB09832 | C45: PF0000023 - FOLHA DE PAGAMENTO | D45: 1526.03 | E45: Extrato de Abril | F45: Folha 04-2025
A46: 2025PD10034 | B46: 2025OB09833 | C46: PF0000023 - FOLHA DE PAGAMENTO | D46: 2428284.1 | E46: Extrato de Abril | F46: Folha 04-2025
A47: 2025PD03845 | B47: 2025OB04002 | C47: 03281445000185 - AMAPÁ PREVIDÊNCIA | D47: 2706694.4 | E47: Extrato de Abril | F47: 2025RE00159
A48: 2025PD03848 | B48: 2025OB04003 | C48: 03281445000185 - AMAPÁ PREVIDÊNCIA | D48: 2701804.6 | E48: Extrato de Abril | F48: 2025RE00159
A49: 2025PD10038 | B49: 2025OB09834 | C49: PF0000023 - FOLHA DE PAGAMENTO | D49: 2192761.7 | E49: Extrato de Abril | F49: Folha 04-2025
A50: 2025PD10026 | B50: 2025OB09830 | C50: PF0000023 - FOLHA DE PAGAMENTO | D50: 4896872.9 | E50: Extrato de Abril | F50: Folha 04-2025
A51: 2025PD03849 | B51: 2025OB04004 | C51: 03281445000185 - AMAPÁ PREVIDÊNCIA | D51: 595700.62 | E51: Extrato de Abril | F51: 2025RE00159
... A54: 2025PD10040 | B54: 2025OB09835 | C54: PF0000023 - FOLHA DE PAGAMENTO | D54: 939755 | E54: Extrato de Abril | F54: Folha 04-2025
D55: 75751224

Sheet Extrato 04-2025
A1: Extrato Conta Corrente
A2: Agencia | C2: =SUBTOTAL(9,C3:C69) -> 1.57665e+08
A3: Data | B3: Historico | C3: Valor R$ | D3: Inf. | E3: Detalhamento Hist. | F3: Detalhamentos
A4: 03/04/2025 | B4: IPVA | C4: 250252.14 | D4: C | E4: Transferência Constitucional - FUNDEB
A5: 03/04/2025 | B5: Emissão Ordem Bancária | C5: 460041.44 | D5: D | E5: Folha de Pagamento | F5: 2025RE00144
A6: 03/04/2025 | B6: Resgate Automático | C6: 209789.3 | D6: C | E6: Resgate Automático
A7: 04/04/2025 | B7: ORDEM BANC CANCELADA | C7: 103.93 | D7: C
A8: 04/04/2025 | B8: Emissão Ordem Bancária | C8: 31900062 | D8: D | E8: Folha de Pagamento | F8: 2025RE00159
A9: 04/04/2025 | B9: Emissão Ordem Bancária | C9: 7641042 | D9: D | E9: Folha de Pagamento | F9: 2025RE00160
A10: 04/04/2025 | B10: Resgate Automático | C10: 39541000 | D10: C | E10: Resgate Automático
A11: 07/04/2025 | B11: RECEBIMENTO DE ICMS | C11: 764797.82 | D11: C | E11: Transferência Constitucional - FUNDEB
A12: 07/04/2025 | B12: BB-APLIC C.PRZ-APL.AUT | C12: 764797.82 | D12: D | E12: Aplicação Financeira
A13: 10/04/2025 | B13: ITR | C13: 310.55 | D13: C | E13: Transferência Constitucional - FUNDEB
A14: 10/04/2025 | B14: FPE/FPM | C14: 970831.98 | D14: C | E14: Transferência Constitucional - FUNDEB
A15: 10/04/2025 | B15: FPE/FPM | C15: 2256898.7 | D15: C | E15: Transferência Constitucional - FUNDEB
A16: 10/04/2025 | B16: FPE/FPM | C16: 26109923 | D16: C | E16: Transferência Constitucional - FUNDEB
A17: 10/04/2025 | B17: FPE/FPM | C17: 11421.52 | D17: C | E17: Transferência Constitucional - FUNDEB
A18: 10/04/2025 | B18: IPI/EXPORTACAO | C18: 25654.02 | D18: C | E18: IPI/EXPORTACAO - Cota Débito
A19: 10/04/2025 | B19: IPI/EXPORTACAO | C19: 14883.18 | D19: C | E19: Transferência Constitucional - FUNDEB
A20: 10/04/2025 | B20: COTA DAF-DEBITO | C20: 25654.02 | D20: D | E20: IPI/EXPORTACAO - Cota Débito
A21: 10/04/2025 | B21: BB-APLIC C.PRZ-APL.AUT | C21: 29364268 | D21: D | E21: Aplicação Financeira
... A38: 22/04/2025 | B38: BB-APLIC C.PRZ-APL.AUT | C38: 1377329.9 | D38: D | E38: Aplicação Financeira
A39: 23/04/2025 | B39: Pagto via Auto-Atend.BB | C39: 333.78 | D39: D | E39: GRU-GUIA RECOLHIM. UNIAO | F39: Regularizado em Maio
A40: 23/04/2025 | B40: Pagto via Auto-Atend.BB | C40: 333.78 | D40: D | E40: GRU-GUIA RECOLHIM. UNIAO | F40: Regularizado em Maio
A41: 23/04/2025 | B41: Resgate Automático | C41: 667.56 | D41: C | E41: Resgate Automático
A42: 28/04/2025 | B42: RECEBIMENTO DE ICMS | C42: 12072894 | D42: C | E42: Transferência Constitucional - FUNDEB
A43: 28/04/2025 | B43: IPVA | C43: 411780.79 | D43: C | E43: Transferência Constitucional - FUNDEB
A44: 28/04/2025 | B44: BB-APLIC C.PRZ-APL.AUT | C44: 12484675 | D44: D | E44: Aplicação Financeira
A45: 29/04/2025 | B45: Folha de Pagamento | C45: 33884901 | D45: D | E45: Folha 04-2025
A46: 29/04/2025 | B46: Folha de Pagamento | C46: 574797.52 | D46: D | E46: Folha 04-2025
A47: 29/04/2025 | B47: Folha de Pagamento | C47: 271057.19 | D47: D | E47: Folha 04-2025
A48: 29/04/2025 | B48: Folha de Pagamento | C48: 694.48 | D48: D | E48: Folha 04-2025
A49: 29/04/2025 | B49: Folha de Pagamento | C49: 15343.9 | D49: D | E49: Folha 04-2025
A50: 29/04/2025 | B50: Folha de Pagamento | C50: 568544.14 | D50: D | E50: Folha 04-2025
A51: 29/04/2025 | B51: Pagamentos Diversos | C51: 17012.03 | D51: D | E51: Folha 04-2025
A52: 29/04/2025 | B52: Emissão Ordem Bancária | C52: 331945.21 | D52: D | E52: Folha 04-2025 | F52: 2025RE00358
A53: 29/04/2025 | B53: Resgate Automático | C53: 35664296 | D53: C | E53: Resgate Automático
A54: 30/04/2025 | B54: ITCMD | C54: 7240.43 | D54: C | E54: Transferência Constitucional - FUNDEB
A55: 30/04/2025 | B55: IPVA | C55: 768010.78 | D55: C | E55: Transferência Constitucional - FUNDEB
A56: 30/04/2025 | B56: ITR | C56: 46.66 | D56: C | E56: Transferência Constitucional - FUNDEB
A57: 30/04/2025 | B57: RECEBIMENTO DE ICMS | C57: 431062.22 | D57: C | E57: Transferência Constitucional - FUNDEB
A58: 30/04/2025 | B58: FPE/FPM | C58: 833471.83 | D58: C | E58: Transferência Constitucional - FUNDEB
A59: 30/04/2025 | B59: FPE/FPM | C59: 1937576.9 | D59: C | E59: Transferência Constitucional - FUNDEB
A60: 30/04/2025 | B60: FPE/FPM | C60: 22024058 | D60: C | E60: Transferência Constitucional - FUNDEB
A61: 30/04/2025 | B61: FPE/FPM | C61: 9805.49 | D61: C | E61: Transferência Constitucional - FUNDEB
A62: 30/04/2025 | B62: IPI/EXPORTACAO | C62: 4298.22 | D62: C | E62: IPI/EXPORTACAO - Cota Débito
A63: 30/04/2025 | B63: IPI/EXPORTACAO | C63: 2493.61 | D63: C | E63: Transferência Constitucional - FUNDEB
A64: 30/04/2025 | B64: VAAR Complemento FUNDEB | C64: 170738.33 | D64: C | E64: Transferência Constitucional - FUNDEB
A65: 30/04/2025 | B65: COTA DAF-DEBITO | C65: 4298.22 | D65: D | E65: IPI/EXPORTACAO - Cota Débito
A66: 30/04/2025 | B66: Folha de Pagamento | C66: 54550.51 | D66: D | E66: Folha 04-2025 | F66: Regularizado em Maio
A67: 30/04/2025 | B67: BB-APLIC C.PRZ-APL.AUT | C67: 26129954 | D67: D | E67: Aplicação Financeira

Sheet Saldos - 04-2025
B2: CONCILIAÇÃO BANCÁRIA DO EXTRATO BANCÁRIO - ABRIL DE 2025
B4: 1. Ingressos | E4: Valores do Mês | F4: Acumulado
B5: 1.0 IPI - EXP | E5: 68716.47 | F5: =E5+'Saldos - 03-2025'!F5 -> 268481.33
B6: 1.1 VAAR | E6: 170738.33 | F6: =E6+'Saldos - 03-2025'!F6 -> 1648620.1
B7: 1.2 FPE/FPM | E7: 65917840 | F7: =E7+'Saldos - 03-2025'!F7 -> 3.0214171e+08
B8: 1.3 ICMS | E8: 14044831 | F8: =E8+'Saldos - 03-2025'!F8 -> 58551739
B9: 1.4 IPVA | E9: 2031296.7 | F9: =E9+'Saldos - 03-2025'!F9 -> 8006682.1
B10: 1.5 ITCMD | E10: 7240.43 | F10: =E10+'Saldos - 03-2025'!F10 -> 132946.87
B11: 1.6 ITR | E11: 439.44 | F11: =E11+'Saldos - 03-2025'!F11 -> 3855.91
B12: 1.7 ORDEM BANC CANCELADA | E12: 103.93 | F12: =E12+'Saldos - 03-2025'!F12 -> 326.29
B13: 1.8 RESGATE | E13: 75423795 | F13: =E13+'Saldos - 03-2025'!F13 -> 2.5117927e+08
B14: 2 Total das Entradas | E14: =SUM(E5:E13) -> 1.57665e+08 | F14: =SUM(F5:F13) -> 6.2193363e+08 | G14: ok
B15: 3.0 (-) IPI/Cota DAF Deb | E15: -43487.32 | F15: =E15+'Saldos - 03-2025'!F15 -> -169908.79
B16: 3.1 (-) Ordem Bancária Cancelada | E16: =-E12 -> -103.93 | F16: =E16+'Saldos - 03-2025'!F16 -> -326.29
B17: 3.2 (-) Resgastes efetuados | E17: =-E13 -> -75423795 | F17: =E17+'Saldos - 03-2025'!F17 -> -2.5117927e+08
B18: 3.3 (-) Ajuste VAAR - FNDE | E18: 0 | F18: =E18+'Saldos - 03-2025'!F18 -> -164645.69
B19: 3. Total Disponibizado( 1 - 3.0- 3.1 - 3.2 -3.3 - 3.4 ) | E19: =SUM(E14:E18) -> 82197615 | F19: =SUM(F14:F18) -> 3.7041948e+08 | G19: ok
B21: 4. Saídas | E21: Valores do Mês | F21: Acumulado
B22: 4.1 Cota DAF Deb | E22: 43487.32 | F22: =E22+'Saldos - 03-2025'!F22 -> 169908.79
B23: 4.2 O.B.s Canceladas | E23: 0 | F23: ='Saldos - 03-2025'!F23 -> 0
B24: 4.3.1 Folha de Pagamento - Encargos e Identificados por RE | E24: 40001146 | F24: =E24+'Saldos - 03-2025'!F24 -> 1.2186437e+08
B25: 4.3.2 Folha de Pagamento - Folha 01/2025 | E25: 0 | F25: =E25+'Saldos - 03-2025'!F25 -> 34311367
B26: 4.3.3 Folha de Pagamento - Folha 02/2025 | E26: 0 | F26: =E26+'Saldos - 03-2025'!F26 -> 34175582
B27: 4.3.4 Folha de Pagamento - Folha 03/2025 | E27: 0 | F27: =E27+'Saldos - 03-2025'!F27 -> 33980888
B28: 4.3.5 Folha de Pagamento - Folha 04/2025 | E28: 35798382 | F28: =E28 -> 35798382
B29: 4.3.6 Folha de Pagamento - Férias | E29: 0 | F29: =E29+'Saldos - 03-2025'!F28 -> 15697876
B30: 4.3.7 Ajuste VAAR | E30: 0 | F30: =E30+'Saldos - 03-2025'!F29 -> 164645.69
B31: 4.3.8 GRU-GUIA RECOLHIM. UNIAO | E31: 667.56 | F31: =E31+'Saldos - 03-2025'!F30 -> 3671.58
B32: 4.3.9 Pagamentos Diversos - Folha | E32: 0 | F32: =E32+'Saldos - 03-2025'!F31 -> 20059.12
B33: 4.4 Tarifa bancária | E33: 0 | F33: =E33+'Saldos - 03-2025'!F32 -> 7490.51
B34: 4.5 (-) Aplicações Efetuadas | E34: 81821318 | F34: =E34+'Saldos - 03-2025'!F33 -> 3.4573939e+08 | H34: ='Extrato 04-2025'!C2+'Extrato 03-2025'!C2+'Extrato 02-2025'!C2+'Extrato 01-2025'!C2-F35 -> 0
B35: 5. Total Geral das Saídas | E35: =SUM(E22:E34) -> 1.57665e+08 | F35: =SUM(F22:F34) -> 6.2193363e+08 | G35: ok | H35: =E35-E14 -> 0
B36: 6.1 (-) Cota DAF Deb | E36: =-E22 -> -43487.32 | F36: =E36+'Saldos - 03-2025'!F35 -> -169908.79
B37: 6.2 (-) Aplicações Efetuadas | E37: =-E34 -> -81821318 | F37: =E37+'Saldos - 03-2025'!F36 -> -3.4573939e+08
B38: 6.3 (-) O.B.s Canceladas | E38: -103.93 | F38: =E38+'Saldos - 03-2025'!F37 -> -215.11
B39: 6.4 (-) Tarifa bancária | E39: =-E33 -> 0 | F39: =E39+'Saldos - 03-2025'!F38 -> -7490.51
B40: 6.5 (-) Pagamento Folha não regularizado | E40: -48866.78 | F40: =E40+'Saldos - 03-2025'!F39 -> -34224449
B41: 6.6 (-) Ajustes VAAR | F41: =E41+'Saldos - 03-2025'!F40 -> -164645.69
B42: 6.7 (-) Pagamentos Diversos | F42: =E42+'Saldos - 03-2025'!F41 -> -20059.12
B43: 6.7 (+) Regularização de Folha e não Pago | F43: =E43+'Saldos - 03-2025'!F42 -> 34223471
B44: 6.8 (-) GRU Paga e Não Regularizada | F44: =E44+'Saldos - 03-2025'!F43 -> -667.56
B45: Despesa Total do Mês ( confere com o relatório de execução financeira do SEAFI ) | E45: =SUM(E35:E44) -> 75751224 | F45: =SUM(F35:F44) -> 2.7583028e+08 | G45: ok
B47: CONTA INVESTIMENTO
B48: saldo Inicial | E48: ='Saldos - 03-2025'!E51 -> 1.0550704e+08
B49: Aplicação | E49: 81821318
B50: Resgaste | E50: 75423795
B51: Rendimento Bruto | E51: 774482.43
B52: Saldo Atual | E52: =E48+E49-E50+E51 -> 1.1267904e+08

Sheet Cálculo Conciliação 2º Bimestre
C3: Saldo dos Pagamentos do SEAFI | D3: 1.4604409e+08 | E3: 11470.64
C5: Extrato de Janeiro | D5: 58285284
C6: SEAFI a maior | D6: 8949.47 | G6: 58294233
C7: Extrato de Fevereiro | D7: 88938686
C8: SEAFI a menor ( regularizado em março ) | D8: -1194723.6 | E8: pago em março
C9: SEAFI a maior | D9: 5894.85 | G9: 87749857
C11: COMPOSIÇÃO DE SALDO DO FUNDEB
C12: 2º BIMESTRE DE 2025
C14: Dsiponibilidade Financeira em 31/12/2024 | D14: 15778860
C15: ( + ) Ingressos = Transferências Constitucionais - janeiro-2024 | D15: 92936040
C16: ( + ) Ingressos = Transferências Constitucionais - fevereiro-2024 | D16: 1.115289e+08 | I16: 2.0446494e+08
C17: ( + ) Ingressos = Transferências Constitucionais - Março-2024 | D17: 83756928
C18: ( + ) Ingressos = Transferências Constitucionais - Abril-2024 | D18: 82197615 | I18: 3.7041948e+08
C19: ( + ) Ingressos = Rendimentos do FUNDEB - 1º Bimestre | D19: 901662.73 | I19: 2.053666e+08
C20: ( + ) Ingressos = Rendimentos do FUNDEB - 2º Bimestre | D20: 1438396.9
C21: ( - ) Pagamentos Efetuados = Relatório de Execução Financeira | D21: -2.7583028e+08
C22: ( - ) Pagto Tarifa Bancária não regularizada no SEAFI | D22: -7490.51
C23: ( - ) Pagto de Folha - não regularizado | D23: -1533.94 | I23: -29083.57
C24: ( - ) Pagamentos Diversos - Folha | D24: -20059.12
C28: ( = ) Saldo do SIOPE | D28: 1.1267904e+08 | I28: 0.0099999905
C30: Dsiponibilidade Financeira em 28/02/2025 | D30: 1.1267904e+08
C32: Diferença a identificar | D32: 0.0099999905

Sheet Extrato 05-2025
A1: Extrato Conta Corrente
A2: Agencia | C2: =SUBTOTAL(9,C4:C66) -> 1.7919817e+08
A3: Data | B3: Historico | C3: Valor R$ | D3: Inf. | E3: Histórico | F3: Detalhamentos
A4: 05/05/2025 | B4: ITCMD | C4: 1600.4 | D4: C | E4: Transferência Constitucional - FUNDEB
A5: 05/05/2025 | B5: IPVA | C5: 168934.79 | D5: C | E5: Transferência Constitucional - FUNDEB
A6: 05/05/2025 | B6: RECEBIMENTO DE ICMS | C6: 1538804.2 | D6: C | E6: Transferência Constitucional - FUNDEB
A7: 05/05/2025 | B7: BB-APLIC C.PRZ-APL.AUT | C7: 1709339.4 | D7: D | E7: Aplicação Financeira
A8: 08/05/2025 | B8: ORDEM BANC CANCELADA | C8: 103.93 | D8: C | E8: ORDEM BANC CANCELADA | F8: 2025GD00955
A9: 08/05/2025 | B9: Emissão Ordem Bancária | C9: 35161499 | D9: D | E9: Folha de Pagamento | F9: 2025RE00370
A10: 08/05/2025 | B10: Emissão Ordem Bancária | C10: 6964816.8 | D10: D | E10: Folha de Pagamento | F10: 2025RE00371
A11: 08/05/2025 | B11: Resgate Automático | C11: 42126212 | D11: C | E11: Resgate Automático
A12: 09/05/2025 | B12: ITCMD | C12: 46.36 | D12: C | E12: Transferência Constitucional - FUNDEB
A13: 09/05/2025 | B13: ITCMD | C13: 6234.01 | D13: C | E13: Transferência Constitucional - FUNDEB
A14: 09/05/2025 | B14: IPVA | C14: 58776.57 | D14: C | E14: Transferência Constitucional - FUNDEB
A15: 09/05/2025 | B15: IPVA | C15: 137612.58 | D15: C | E15: Transferência Constitucional - FUNDEB
A16: 09/05/2025 | B16: ITR | C16: 1640.13 | D16: C | E16: Transferência Constitucional - FUNDEB
A17: 09/05/2025 | B17: RECEBIMENTO DE ICMS | C17: 32178.6 | D17: C | E17: Transferência Constitucional - FUNDEB
A18: 09/05/2025 | B18: RECEBIMENTO DE ICMS | C18: 580965.71 | D18: C | E18: Transferência Constitucional - FUNDEB
A19: 09/05/2025 | B19: FPE/FPM | C19: 1492064.2 | D19: C | E19: Transferência Constitucional - FUNDEB
A20: 09/05/2025 | B20: FPE/FPM | C20: 3468610.4 | D20: C | E20: Transferência Constitucional - FUNDEB
A21: 09/05/2025 | B21: FPE/FPM | C21: 40065193 | D21: C | E21: Transferência Constitucional - FUNDEB
A22: 09/05/2025 | B22: FPE/FPM | C22: 17553.67 | D22: C | E22: Transferência Constitucional - FUNDEB
... A30: 16/05/2025 | B30: BB-APLIC C.PRZ-APL.AUT | C30: 5871461 | D30: D | E30: Aplicação Financeira
A31: 19/05/2025 | B31: Emissão Ordem Bancária | C31: 70643.92 | D31: D | E31: Folha de Pagamento | F31: 2025RE00396
A32: 19/05/2025 | B32: Resgate Automático | C32: 70643.92 | D32: C | E32: Resgate Automático
A33: 20/05/2025 | B33: ITR | C33: 106.39 | D33: C | E33: Transferência Constitucional - FUNDEB
A34: 20/05/2025 | B34: FPE/FPM | C34: 325682.9 | D34: C | E34: Transferência Constitucional - FUNDEB
A35: 20/05/2025 | B35: FPE/FPM | C35: 757116.99 | D35: C | E35: Transferência Constitucional - FUNDEB
A36: 20/05/2025 | B36: FPE/FPM | C36: 8321549.5 | D36: C | E36: Transferência Constitucional - FUNDEB
A37: 20/05/2025 | B37: FPE/FPM | C37: 3831.54 | D37: C | E37: Transferência Constitucional - FUNDEB
A38: 20/05/2025 | B38: IPI/EXPORTACAO | C38: 8636.3 | D38: C | E38: IPI/EXPORTACAO - Cota Débito
A39: 20/05/2025 | B39: IPI/EXPORTACAO | C39: 5010.36 | D39: C | E39: Transferência Constitucional - FUNDEB
A40: 20/05/2025 | B40: COTA DAF-DEBITO | C40: 8636.3 | D40: D | E40: IPI/EXPORTACAO - Cota Débito
A41: 20/05/2025 | B41: BB-APLIC C.PRZ-APL.AUT | C41: 9413297.7 | D41: D | E41: Aplicação Financeira
A42: 23/05/2025 | B42: ITCMD | C42: 15845.21 | D42: C | E42: Transferência Constitucional - FUNDEB
A43: 23/05/2025 | B43: IPVA | C43: 384474.34 | D43: C | E43: Transferência Constitucional - FUNDEB
... A48: 29/05/2025 | B48: RECEBIMENTO DE ICMS | C48: 2714578.6 | D48: C | E48: Transferência Constitucional - FUNDEB
A49: 29/05/2025 | B49: Folha de Pagamento | C49: 33983595 | D49: D | E49: Folha 05/2025 | F49: Regularizado em Junho
A50: 29/05/2025 | B50: Folha de Pagamento | C50: 570670.66 | D50: D | E50: Folha 05/2025 | F50: Regularizado em Junho
A51: 29/05/2025 | B51: Folha de Pagamento | C51: 259507.21 | D51: D | E51: Folha 05/2025 | F51: Regularizado em Junho
A52: 29/05/2025 | B52: Folha de Pagamento | C52: 694.48 | D52: D | E52: Folha 05/2025 | F52: Regularizado em Junho
A53: 29/05/2025 | B53: Folha de Pagamento | C53: 15374.74 | D53: D | E53: Folha 05/2025 | F53: Regularizado em Junho
A54: 29/05/2025 | B54: Folha de Pagamento | C54: 577241.08 | D54: D | E54: Folha 05/2025 | F54: Regularizado em Junho
A55: 29/05/2025 | B55: Pagamentos Diversos | C55: 16626.84 | D55: D | E55: Folha 05/2025 | F55: Regularizado em Junho
A56: 29/05/2025 | B56: Emissão Ordem Bancária | C56: 327994.51 | D56: D | E56: Folha 05/2025 | F56: Regularizado em Junho
A57: 29/05/2025 | B57: Resgate Automático | C57: 32849576 | D57: C | E57: Resgate Automático
A58: 30/05/2025 | B58: ITR | C58: 43.84 | D58: C | E58: Transferência Constitucional - FUNDEB
A59: 30/05/2025 | B59: FPE/FPM | C59: 995063.95 | D59: C | E59: Transferência Constitucional - FUNDEB
A60: 30/05/2025 | B60: FPE/FPM | C60: 2313230.9 | D60: C | E60: Transferência Constitucional - FUNDEB
A61: 30/05/2025 | B61: FPE/FPM | C61: 26060106 | D61: C | E61: Transferência Constitucional - FUNDEB
A62: 30/05/2025 | B62: FPE/FPM | C62: 11706.61 | D62: C | E62: Transferência Constitucional - FUNDEB
A63: 30/05/2025 | B63: IPI/EXPORTACAO | C63: 8497.14 | D63: C | E63: IPI/EXPORTACAO - Cota Débito
A64: 30/05/2025 | B64: IPI/EXPORTACAO | C64: 4929.62 | D64: C | E64: Transferência Constitucional - FUNDEB
A65: 30/05/2025 | B65: COTA DAF-DEBITO | C65: 8497.14 | D65: D | E65: IPI/EXPORTACAO - Cota Débito
A66: 30/05/2025 | B66: BB-APLIC C.PRZ-APL.AUT | C66: 29385081 | D66: D | E66: Aplicação Financeira

Sheet Saldos - 05-2025
B2: CONCILIAÇÃO BANCÁRIA DO EXTRATO BANCÁRIO - MAIO DE 2025
B4: 1. Ingressos | E4: Valores do Mês | F4: Acumulado
B5: 1.0 IPI - EXP | E5: 66759.43 | F5: =E5+'Saldos - 04-2025'!F5 -> 335240.76
B6: 1.1 VAAR | E6: 0 | F6: =E6+'Saldos - 04-2025'!F6 -> 1648620.1
B7: 1.2 FPE/FPM | E7: 83831710 | F7: =E7+'Saldos - 04-2025'!F7 -> 3.8597342e+08
B8: 1.3 ICMS | E8: 19018969 | F8: =E8+'Saldos - 04-2025'!F8 -> 77570708
B9: 1.4 IPVA | E9: 1203990.6 | F9: =E9+'Saldos - 04-2025'!F9 -> 9210672.8
B10: 1.5 ITCMD | E10: 28418.13 | F10: =E10+'Saldos - 04-2025'!F10 -> 161365
B11: 1.6 ITR | E11: 1790.36 | F11: =E11+'Saldos - 04-2025'!F11 -> 5646.27
B12: 1.7 ORDEM BANC CANCELADA | E12: 103.93 | F12: =E12+'Saldos - 04-2025'!F12 -> 430.22
B13: 1.8 RESGATE | E13: 75046432 | F13: =E13+'Saldos - 04-2025'!F13 -> 3.262257e+08
B14: 2 Total das Entradas | E14: =SUM(E5:E13) -> 1.7919817e+08 | F14: =SUM(F5:F13) -> 8.0113181e+08
B15: 3.0 (-) IPI/Cota DAF Deb | E15: -42248.78 | F15: =E15+'Saldos - 04-2025'!F15 -> -212157.57
B16: 3.1 (-) Ordem Bancária Cancelada | E16: =-E12 -> -103.93 | F16: =E16+'Saldos - 04-2025'!F16 -> -430.22
B17: 3.2 (-) Resgastes efetuados | E17: =-E13 -> -75046432 | F17: =E17+'Saldos - 04-2025'!F17 -> -3.262257e+08
B18: 3.3 (-) Ajuste VAAR - FNDE | E18: 0 | F18: =E18+'Saldos - 04-2025'!F18 -> -164645.69
B19: 3. Total Disponibizado( 1 - 3.0- 3.1 - 3.2 -3.3 - 3.4 ) | E19: =SUM(E14:E18) -> 1.0410939e+08 | F19: =SUM(F14:F18) -> 4.7452887e+08 | G19: OK
B21: 4. Saídas | E21: Valores do Mês | F21: Acumulado
B22: 4.1 Cota DAF Deb | E22: 42248.78 | F22: =E22+'Saldos - 04-2025'!F22 -> 212157.57
B23: 4.2 O.B.s Canceladas | E23: 0 | F23: =E23+'Saldos - 04-2025'!F23 -> 0
B24: 4.3.1 Folha de Pagamento e Encargos - Identificados por RE | E24: 42196960 | F24: =E24+'Saldos - 04-2025'!F24 -> 1.6406133e+08
B25: 4.3.2 Folha de Pagamento - Folha 01/2025 | E25: 0 | F25: ='Saldos - 04-2025'!F25 -> 34311367
B26: 4.3.3 Folha de Pagamento - Folha 02/2025 | E26: 0 | F26: ='Saldos - 04-2025'!F26 -> 34175582
B27: 4.3.4 Folha de Pagamento - Folha 03/2025 | E27: 0 | F27: ='Saldos - 04-2025'!F27 -> 33980888
B28: 4.3.5 Folha de Pagamento - Folha 04/2025 | E28: 0 | F28: ='Saldos - 04-2025'!F28 -> 35798382
B29: 4.3.6 Folha de Pagamento - Folha 05/2025 | E29: 35751705 | F29: =E29 -> 35751705
B30: 4.3.7 Folha de Pagamento - Férias | E30: 0 | F30: =E30+'Saldos - 04-2025'!F29 -> 15697876
B31: 4.3.8 Ajuste VAAR | E31: 0 | F31: =E31+'Saldos - 04-2025'!F30 -> 164645.69
B32: 4.3.9 GRU-GUIA RECOLHIM. UNIAO | E32: 0 | F32: =E32+'Saldos - 04-2025'!F31 -> 3671.58
B33: 4.3.10 Pagamentos Diversos - Folha | E33: 0 | F33: =E33+'Saldos - 04-2025'!F32 -> 20059.12
B34: 4.4 Tarifa bancária | E34: 0 | F34: =E34+'Saldos - 04-2025'!F33 -> 7490.51
B35: 4.5 (-) Aplicações Efetuadas | E35: 1.0120726e+08 | F35: =E35+'Saldos - 04-2025'!F34 -> 4.4694665e+08
B36: 5. Total Geral das Saídas | E36: =SUM(E22:E35) -> 1.7919817e+08 | F36: =SUM(F22:F35) -> 8.0113181e+08 | G36: OK | H36: =E36-E14 -> 0
B37: 6.1 (-) Cota DAF Deb | E37: =-E22 -> -42248.78 | F37: =E37+'Saldos - 04-2025'!F36 -> -212157.57
B38: 6.2 (-) Aplicações Efetuadas | E38: =-E35 -> -1.0120726e+08 | F38: =E38+'Saldos - 04-2025'!F37 -> -4.4694665e+08
B39: 6.3 (-) O.B.s Canceladas (2025GD00955) | E39: -103.93 | F39: =E39+'Saldos - 04-2025'!F38 -> -319.04
B40: 6.4 (-) Tarifa bancária | E40: =-E34 -> 0 | F40: =E40+'Saldos - 04-2025'!F39 -> -7490.51
B41: 6.5 (-) Pagamento Folha não regularizado | E41: =-E29 -> -35751705 | F41: =E41+'Saldos - 04-2025'!F40 -> -69976153
B42: 6.6 (-) Ajustes VAAR | E42: 0 | F42: =E42+'Saldos - 04-2025'!F41 -> -164645.69
B43: 6.7 (-) Pagamentos Diversos | E43: 0 | F43: =E43+'Saldos - 04-2025'!F42 -> -20059.12
B44: 6.7 (+) Regularização de Folha e não Pago | E44: 54550.51 | F44: =E44+'Saldos - 04-2025'!F43 -> 34278022
B45: 6.8.1 (-) GRU Paga e Não Regularizada | E45: 0 | F45: =E45+'Saldos - 04-2025'!F44 -> -667.56
B46: 6.8.2 (+) Regularização de GRU Paga em Abril | E46: 667.56 | F46: =E46 -> 667.56
B47: 6.8.3 (+) Regularização de GRU Não Paga em Maio | E47: 333.78 | F47: =E47 -> 333.78
B48: Despesa Total do Mês ( confere com o relatório de execução financeira do SEAFI ) | E48: =SUM(E36:E47) -> 42252408 | F48: =SUM(F36:F47) -> 3.1808269e+08
E49: =E48-'REF - MAIO'!D2 -> 0
B50: CONTA INVESTIMENTO
B51: saldo Inicial | E51: 1.1267904e+08
B52: Aplicação | E52: 1.0120726e+08
B53: Resgaste | E53: 75046432
B54: Rendimento Bruto | E54: 1070137.3
B55: Saldo Atual | E55: =E51+E52-E53+E54 -> 1.3991001e+08

Sheet REF - MAIO
D2: =SUBTOTAL(9,D4:D53) -> 42252408
A3: PD | B3: OB | C3: Credor | D3: 5 - Maio | E3: Mês de Ocorrência | F3: RE | G3: GD
A4: 2025PD10936 | B4: 2025OB09828 | C4: PF0000023 - FOLHA DE PAGAMENTO | D4: 333.78 | E4: Abril | F4: Extrato de Abril
A5: 2025PD10937 | B5: 2025OB09836 | C5: PF0000023 - FOLHA DE PAGAMENTO | D5: 333.78 | E5: Abril | F5: Extrato de Abril
A6: 2025PD10771 | B6: 2025OB09827 | C6: PF0000023 - FOLHA DE PAGAMENTO | D6: 333.78
A7: 2025PD11141 | B7: 2025OB10899 | C7: PF0000023 - FOLHA DE PAGAMENTO | D7: 19.58 | E7: Extrato de Maio | F7: 2025RE00371
A8: 2025PD11142 | B8: 2025OB10900 | C8: PF0000023 - FOLHA DE PAGAMENTO | D8: 176 | E8: Extrato de Maio | F8: 2025RE00370
A9: 2025PD11144 | B9: 2025OB10901 | C9: PF0000023 - FOLHA DE PAGAMENTO | D9: 88 | E9: Extrato de Maio | F9: 2025RE00371
A10: 2025PD11146 | B10: 2025OB10902 | C10: PF0000023 - FOLHA DE PAGAMENTO | D10: 20371.72 | E10: Extrato de Maio | F10: 2025RE00370
A11: 2025PD11148 | B11: 2025OB10903 | C11: PF0000023 - FOLHA DE PAGAMENTO | D11: 229 | E11: Extrato de Maio | F11: 2025RE00371
A12: 2025PD11152 | B12: 2025OB10904 | C12: PF0000023 - FOLHA DE PAGAMENTO | D12: 165 | E12: Extrato de Maio | F12: 2025RE00371
A13: 2025PD11157 | B13: 2025OB10905 | C13: PF0000023 - FOLHA DE PAGAMENTO | D13: 9384.76 | E13: Extrato de Maio | F13: 2025RE00370
A14: 2025PD11159 | B14: 2025OB10906 | C14: PF0000023 - FOLHA DE PAGAMENTO | D14: 1728.19 | E14: Extrato de Maio | F14: 2025RE00371
A15: 2025PD11175 | B15: 2025OB10907 | C15: PF0000023 - FOLHA DE PAGAMENTO | D15: 728012.77 | E15: Extrato de Maio | F15: 2025RE00370
A16: 2025PD11179 | B16: 2025OB10908 | C16: PF0000023 - FOLHA DE PAGAMENTO | D16: 374812.87 | E16: Extrato de Maio | F16: 2025RE00371
A17: 2025PD11183 | B17: 2025OB10909 | C17: PF0000023 - FOLHA DE PAGAMENTO | D17: 44612.14 | E17: Extrato de Maio | F17: 2025RE00370
A18: 2025PD11196 | B18: 2025OB10910 | C18: PF0000023 - FOLHA DE PAGAMENTO | D18: 302.39 | E18: Extrato de Maio | F18: 2025RE00370
... A29: 2025PD11228 | B29: 2025OB10921 | C29: PF0000023 - FOLHA DE PAGAMENTO | D29: 7877.86 | E29: Extrato de Maio | F29: 2025RE00371
A30: 2025PD11231 | B30: 2025OB10922 | C30: PF0000023 - FOLHA DE PAGAMENTO | D30: 0 | F30: 2025RE00370 | G30: 2025GD00955
A31: 2025PD11233 | B31: 2025OB10923 | C31: PF0000023 - FOLHA DE PAGAMENTO | D31: 177854.37 | E31: Extrato de Maio | F31: 2025RE00370
A32: 2025PD11236 | B32: 2025OB10924 | C32: PF0000023 - FOLHA DE PAGAMENTO | D32: 13.09 | E32: Extrato de Maio | F32: 2025RE00371
A33: 2025PD11238 | B33: 2025OB10925 | C33: PF0000023 - FOLHA DE PAGAMENTO | D33: 489.55 | E33: Extrato de Maio | F33: 2025RE00371
A34: 2025PD11240 | B34: 2025OB10926 | C34: PF0000023 - FOLHA DE PAGAMENTO | D34: 320.23 | E34: Extrato de Maio | F34: 2025RE00370
A35: 2025PD11242 | B35: 2025OB10927 | C35: PF0000023 - FOLHA DE PAGAMENTO | D35: 84146 | E35: Extrato de Maio | F35: 2025RE00371
A36: 2025PD11244 | B36: 2025OB10928 | C36: PF0000023 - FOLHA DE PAGAMENTO | D36: 470.99 | E36: Extrato de Maio | F36: 2025RE00370
A37: 2025PD11245 | B37: 2025OB10929 | C37: PF0000023 - FOLHA DE PAGAMENTO | D37: 8405404.1 | E37: Extrato de Maio | F37: 2025RE00370
A38: 2025PD11246 | B38: 2025OB10930 | C38: PF0000023 - FOLHA DE PAGAMENTO | D38: 2111.9 | E38: Extrato de Maio | F38: 2025RE00371
A39: 2025PD12783 | B39: 2025OB12215 | C39: PF0000023 - FOLHA DE PAGAMENTO | D39: 18647.45 | E39: Extrato de Maio | F39: 2025RE00396
A40: 2025PD11249 | B40: 2025OB10932 | C40: PF0000023 - FOLHA DE PAGAMENTO | D40: 2799173.6 | E40: Extrato de Maio | F40: 2025RE00370
A41: 2025PD11250 | B41: 2025OB10933 | C41: PF0000023 - FOLHA DE PAGAMENTO | D41: 5409359.1 | E41: Extrato de Maio | F41: 2025RE00370
A42: 2025PD11247 | B42: 2025OB10931 | C42: PF0000023 - FOLHA DE PAGAMENTO | D42: 20217.84 | E42: Extrato de Maio | F42: 2025RE00370
... A53: 2025PD11281 | B53: 2025OB10939 | C53: 03281445000185 - AMAPÁ PREVIDÊNCIA | D53: 1878992.3 | E53: Extrato de Maio | F53: 2025RE00370

Sheet Extrato 06-2025
C2: =SUBTOTAL(9,C3:C79) -> 1.8843552e+08
A3: Data | B3: Historico | C3: Valor R$ | D3: Inf. | E3: Histórico | F3: Detalhamentos
A4: 03/06/2025 | B4: ORDEM BANC CANCELADA | C4: 103.93 | D4: C | E4: ORDEM BANC CANCELADA | F4: 2025GD00978
A5: 03/06/2025 | B5: Emissão Ordem Bancária | C5: 19672891 | D5: D | E5: Folha de Pagamento | F5: 2025RE00483
A6: 03/06/2025 | B6: Emissão Ordem Bancária | C6: 23414462 | D6: D | E6: Folha de Pagamento | F6: 2025RE00484
A7: 03/06/2025 | B7: Resgate Automático | C7: 43087249 | D7: C | E7: Resgate Automático
A8: 05/06/2025 | B8: ITCMD | C8: 9190.46 | D8: C | E8: Transferência Constitucional - FUNDEB
A9: 05/06/2025 | B9: IPVA | C9: 231525.3 | D9: C | E9: Transferência Constitucional - FUNDEB
A10: 05/06/2025 | B10: RECEBIMENTO DE ICMS | C10: 805325.87 | D10: C | E10: Transferência Constitucional - FUNDEB
A11: 05/06/2025 | B11: BB-APLIC C.PRZ-APL.AUT | C11: 1046041.6 | D11: D | E11: Aplicação Financeira
A12: 09/06/2025 | B12: Folha de Pagamento | C12: 305454.84 | D12: D | E12: Folha de Pagamento | F12: Adiant. 13º Salário
A13: 09/06/2025 | B13: Folha de Pagamento | C13: 114754.3 | D13: D | E13: Folha de Pagamento | F13: Adiant. 13º Salário
A14: 09/06/2025 | B14: Folha de Pagamento | C14: 31070316 | D14: D | E14: Folha de Pagamento | F14: Adiant. 13º Salário
A15: 09/06/2025 | B15: Folha de Pagamento | C15: 170.02 | D15: D | E15: Folha de Pagamento | F15: Adiant. 13º Salário
A16: 09/06/2025 | B16: Folha de Pagamento | C16: 4649.97 | D16: D | E16: Folha de Pagamento | F16: Adiant. 13º Salário
A17: 09/06/2025 | B17: Folha de Pagamento | C17: 175176.22 | D17: D | E17: Folha de Pagamento | F17: Adiant. 13º Salário
A18: 09/06/2025 | B18: Emissão Ordem Bancária | C18: 108237.45 | D18: D | E18: Folha de Pagamento | F18: Adiant. 13º Salário
A19: 09/06/2025 | B19: Resgate Automático | C19: 31778759 | D19: C | E19: Resgate Automático
A20: 10/06/2025 | B20: ITR | C20: 151.7 | D20: C | E20: Transferência Constitucional - FUNDEB
A21: 10/06/2025 | B21: FPE/FPM | C21: 1175891 | D21: C | E21: Transferência Constitucional - FUNDEB
A22: 10/06/2025 | B22: FPE/FPM | C22: 2733600.6 | D22: C | E22: Transferência Constitucional - FUNDEB
A23: 10/06/2025 | B23: FPE/FPM | C23: 30975383 | D23: C | E23: Transferência Constitucional - FUNDEB
A24: 10/06/2025 | B24: FPE/FPM | C24: 13833.99 | D24: C | E24: Transferência Constitucional - FUNDEB
A25: 10/06/2025 | B25: IPI/EXPORTACAO | C25: 26160.65 | D25: C | E25: IPI/EXPORTACAO - Cota Débito
A26: 10/06/2025 | B26: IPI/EXPORTACAO | C26: 15177.1 | D26: C | E26: Transferência Constitucional - FUNDEB
A27: 10/06/2025 | B27: COTA DAF-DEBITO | C27: 26160.65 | D27: D | E27: IPI/EXPORTACAO - Cota Débito
A28: 10/06/2025 | B28: BB-APLIC C.PRZ-APL.AUT | C28: 34914037 | D28: D | E28: Aplicação Financeira
A29: 11/06/2025 | B29: Tar Lib/Ant Float Pg Div | C29: 7.08 | D29: D | E29: Tarifa Bancária
A30: 11/06/2025 | B30: Resgate Automático | C30: 7.08 | D30: C | E30: Resgate Automático
... A34: 12/06/2025 | B34: BB-APLIC C.PRZ-APL.AUT | C34: 1071701.4 | D34: D | E34: Aplicação Financeira
A35: 13/06/2025 | B35: Emissão Ordem Bancária | C35: 45000.24 | D35: D | E35: Folha de Pagamento | F35: 2025RE00519
A36: 13/06/2025 | B36: Resgate Automático | C36: 45000.24 | D36: C | E36: Resgate Automático
A37: 17/06/2025 | B37: Pagamentos Diversos | C37: 10385.47 | D37: D | E37: Pagamentos Diversos
A38: 17/06/2025 | B38: Emissão Ordem Bancária | C38: 68491.71 | D38: D | E38: Folha de Pagamento | F38: 2025RE00525
A39: 17/06/2025 | B39: Resgate Automático | C39: 78877.18 | D39: C | E39: Resgate Automático
A40: 18/06/2025 | B40: Tar Lib/Ant Float Pg Div | C40: 10.38 | D40: D | E40: Tarifa Bancária
A41: 18/06/2025 | B41: Resgate Automático | C41: 10.38 | D41: C | E41: Resgate Automático
A42: 20/06/2025 | B42: ITCMD | C42: 5395.75 | D42: C | E42: Transferência Constitucional - FUNDEB
A43: 20/06/2025 | B43: RECEBIMENTO DE ICMS | C43: 12357301 | D43: C | E43: Transferência Constitucional - FUNDEB
A44: 20/06/2025 | B44: IPVA | C44: 320697.23 | D44: C | E44: Transferência Constitucional - FUNDEB
A45: 20/06/2025 | B45: ITR | C45: 169.86 | D45: C | E45: Transferência Constitucional - FUNDEB
A46: 20/06/2025 | B46: FPE/FPM | C46: 817640.85 | D46: C | E46: Transferência Constitucional - FUNDEB
A47: 20/06/2025 | B47: FPE/FPM | C47: 1900774.4 | D47: C | E47: Transferência Constitucional - FUNDEB
A48: 20/06/2025 | B48: FPE/FPM | C48: 21291701 | D48: C | E48: Transferência Constitucional - FUNDEB
A49: 20/06/2025 | B49: FPE/FPM | C49: 9619.27 | D49: C | E49: Transferência Constitucional - FUNDEB
A50: 20/06/2025 | B50: IPI/EXPORTACAO | C50: 14326.08 | D50: C | E50: IPI/EXPORTACAO - Cota Débito
... A57: 26/06/2025 | B57: BB-APLIC C.PRZ-APL.AUT | C57: 3242509.4 | D57: D | E57: Aplicação Financeira
A58: 27/06/2025 | B58: Emissão Ordem Bancária | C58: 333427.64 | D58: D | E58: Folha de Pagamento | F58: Salário 06/2025
A59: 27/06/2025 | B59: Resgate Automático | C59: 333427.64 | D59: C | E59: Resgate Automático
A60: 30/06/2025 | B60: ITR | C60: 87.86 | D60: C | E60: Transferência Constitucional - FUNDEB
A61: 30/06/2025 | B61: FPE/FPM | C61: 895611.6 | D61: C | E61: Transferência Constitucional - FUNDEB
A62: 30/06/2025 | B62: FPE/FPM | C62: 2082033.5 | D62: C | E62: Transferência Constitucional - FUNDEB
A63: 30/06/2025 | B63: FPE/FPM | C63: 23229130 | D63: C | E63: Transferência Constitucional - FUNDEB
A64: 30/06/2025 | B64: FPE/FPM | C64: 10536.57 | D64: C | E64: Transferência Constitucional - FUNDEB
A65: 30/06/2025 | B65: IPI/EXPORTACAO | C65: 7610.16 | D65: C | E65: IPI/EXPORTACAO - Cota Débito
A66: 30/06/2025 | B66: IPI/EXPORTACAO | C66: 4415.05 | D66: C | E66: Transferência Constitucional - FUNDEB
A67: 30/06/2025 | B67: COTA DAF-DEBITO | C67: 7610.16 | D67: D | E67: IPI/EXPORTACAO - Cota Débito
A68: 30/06/2025 | B68: Folha de Pagamento | C68: 266376.6 | D68: D | E68: Folha de Pagamento | F68: Salário 06/2025
A69: 30/06/2025 | B69: Folha de Pagamento | C69: 563802.01 | D69: D | E69: Folha de Pagamento | F69: Salário 06/2025
A70: 30/06/2025 | B70: Folha de Pagamento | C70: 34630287 | D70: D | E70: Folha de Pagamento | F70: Salário 06/2025
A71: 30/06/2025 | B71: Folha de Pagamento | C71: 694.48 | D71: D | E71: Folha de Pagamento | F71: Salário 06/2025
A72: 30/06/2025 | B72: Folha de Pagamento | C72: 15374.74 | D72: D | E72: Folha de Pagamento | F72: Salário 06/2025
A73: 30/06/2025 | B73: Folha de Pagamento | C73: 586978.3 | D73: D | E73: Folha de Pagamento | F73: Salário 06/2025
A74: 30/06/2025 | B74: Pagamentos Diversos | C74: 14226.43 | D74: D | E74: Folha de Pagamento | F74: Salário 06/2025
A75: 30/06/2025 | B75: Emissão Ordem Bancária | C75: 333.78 | D75: D | E75: Folha de Pagamento | F75: 2025RE00611
A76: 30/06/2025 | B76: Tar Lib/Ant Float Pg Div | C76: 14.22 | D76: D | E76: Tarifa Bancária
A77: 30/06/2025 | B77: Tar Lib/Ant Float Pg Div | C77: 3.72 | D77: D | E77: Tarifa Bancária
A78: 30/06/2025 | B78: Resgate Automático | C78: 9856276.7 | D78: C | E78: Resgate Automático

Sheet REF - JUNHO
D2: =SUBTOTAL(9,D4:D67) -> 1.4716825e+08
A3: PD | B3: OB | C3: Credor | D3: 6 - Junho | E3: Mês de Ocorrência | F3: RE | G3: GD
A4: 2025PD17056 | B4: 2025OB16484 | C4: PF0000023 - FOLHA DE PAGAMENTO | D4: 36635.81 | E4: Extrato de Maio | F4: Folha 05/2025
A5: 2025PD18653 | B5: 2025OB18466 | C5: PF0000023 - FOLHA DE PAGAMENTO | D5: 333.78 | E5: Extrato de Junho | F5: 2025RE00611
A6: 2025PD17057 | B6: 2025OB16485 | C6: PF0000023 - FOLHA DE PAGAMENTO | D6: 889768.61 | E6: Extrato de Maio | F6: Folha 05/2025
A7: 2025PD15373 | B7: 2025OB15051 | C7: PF0000023 - FOLHA DE PAGAMENTO | D7: 19.58 | E7: Extrato de Junho | F7: 2025RE00483
A8: 2025PD15376 | B8: 2025OB15052 | C8: PF0000023 - FOLHA DE PAGAMENTO | D8: 176 | E8: Extrato de Junho | F8: 2025RE00483
A9: 2025PD15380 | B9: 2025OB15053 | C9: PF0000023 - FOLHA DE PAGAMENTO | D9: 88 | E9: Extrato de Junho | F9: 2025RE00484
A10: 2025PD15382 | B10: 2025OB15054 | C10: PF0000023 - FOLHA DE PAGAMENTO | D10: 20475.73 | E10: Extrato de Junho | F10: 2025RE00483
A11: 2025PD15384 | B11: 2025OB15055 | C11: PF0000023 - FOLHA DE PAGAMENTO | D11: 229 | E11: Extrato de Junho | F11: 2025RE00483
A12: 2025PD15388 | B12: 2025OB15056 | C12: PF0000023 - FOLHA DE PAGAMENTO | D12: 150 | E12: Extrato de Junho | F12: 2025RE00483
A13: 2025PD15390 | B13: 2025OB15057 | C13: PF0000023 - FOLHA DE PAGAMENTO | D13: 9189.23 | E13: Extrato de Junho | F13: 2025RE00483
A14: 2025PD15393 | B14: 2025OB15058 | C14: PF0000023 - FOLHA DE PAGAMENTO | D14: 1664.16 | E14: Extrato de Junho | F14: 2025RE00484
A15: 2025PD15395 | B15: 2025OB15059 | C15: PF0000023 - FOLHA DE PAGAMENTO | D15: 726316.13 | E15: Extrato de Junho | F15: 2025RE00483
... A67: 2025PD18794 | B67: 2025OB18519 | C67: PF0000023 - FOLHA DE PAGAMENTO | D67: 942170 | E67: Extrato de Junho | F67: Salário 06/2025

Sheet Saldos - 06-2025
B2: CONCILIAÇÃO BANCÁRIA DO EXTRATO BANCÁRIO - JUNHO DE 2025
B4: 1. Ingressos | E4: Valores do Mês | F4: Acumulado
B5: 1.0 IPI - EXP | E5: 76000.32 | F5: =E5+'Saldos - 05-2025'!F5 -> 411241.08
B6: 1.1 VAAR | E6: 0 | F6: =E6+'Saldos - 05-2025'!F6 -> 1648620.1
B7: 1.2 FPE/FPM | E7: 85135757 | F7: =E7+'Saldos - 05-2025'!F7 -> 4.7110918e+08
B8: 1.3 ICMS | E8: 16870014 | F8: =E8+'Saldos - 05-2025'!F8 -> 94440722
B9: 1.4 IPVA | E9: 1150481.3 | F9: =E9+'Saldos - 05-2025'!F9 -> 10361154
B10: 1.5 ITCMD | E10: 23151.4 | F10: =E10+'Saldos - 05-2025'!F10 -> 184516.4
B11: 1.6 ITR | E11: 409.42 | F11: =E11+'Saldos - 05-2025'!F11 -> 6055.69
B12: 1.7 ORDEM BANC CANCELADA | E12: 103.93 | F12: =E12+'Saldos - 05-2025'!F12 -> 534.15
B13: 1.8 RESGATE | E13: 85179607 | F13: =E13+'Saldos - 05-2025'!F13 -> 4.1140531e+08
B14: 2 Total das Entradas | E14: =SUM(E5:E13) -> 1.8843552e+08 | F14: =SUM(F5:F13) -> 9.8956733e+08
B15: 3.0 (-) IPI/Cota DAF Deb | E15: -48096.89 | F15: =E15+'Saldos - 05-2025'!F15 -> -260254.46
B16: 3.1 (-) Ordem Bancária Cancelada | E16: =-E12 -> -103.93 | F16: =E16+'Saldos - 05-2025'!F16 -> -534.15
B17: 3.2 (-) Resgastes efetuados | E17: =-E13 -> -85179607 | F17: =E17+'Saldos - 05-2025'!F17 -> -4.1140531e+08
B18: 3.3 (-) Ajuste VAAR - FNDE | E18: 0 | F18: =E18+'Saldos - 05-2025'!F18 -> -164645.69
B19: 3. Total Disponibizado( 1 - 3.0- 3.1 - 3.2 -3.3 - 3.4 ) | E19: =SUM(E14:E18) -> 1.0320772e+08 | F19: =SUM(F14:F18) -> 5.7773659e+08 | G19: OK
B21: 4. Saídas | E21: Valores do Mês | F21: Acumulado
B22: 4.1 Cota DAF Deb | E22: 48096.89 | F22: =E22+'Saldos - 05-2025'!F22 -> 260254.46
B23: 4.2 O.B.s Canceladas | E23: 0 | F23: =E23+'Saldos - 05-2025'!F23 -> 0
B24: 4.3.1 Folha de Pagamento e Encargos - Identificados por RE | E24: 43201179 | F24: =E24+'Saldos - 05-2025'!F24 -> 2.0726251e+08
B25: 4.3.2 Folha de Pagamento - Folha 01/2025 | E25: 0 | F25: =E25+'Saldos - 05-2025'!F25 -> 34311367
B26: 4.3.3 Folha de Pagamento - Folha 02/2025 | E26: 0 | F26: =E26+'Saldos - 05-2025'!F26 -> 34175582
B27: 4.3.4 Folha de Pagamento - Folha 03/2025 | E27: 0 | F27: =E27+'Saldos - 05-2025'!F27 -> 33980888
B28: 4.3.5 Folha de Pagamento - Folha 04/2025 | E28: 0 | F28: =E28+'Saldos - 05-2025'!F28 -> 35798382
B29: 4.3.6 Folha de Pagamento - Folha 05/2025 | E29: 0 | F29: =E29+'Saldos - 05-2025'!F29 -> 35751705
B30: 4.3.7 Folha de Pagamento - Folha 06/2025 | E30: 36411168 | F30: =E30 -> 36411168
B31: 4.3.8 Folha de Pagamento - Férias | F31: =E31+'Saldos - 05-2025'!F30 -> 15697876
B32: 4.3.8 Folha de Pagamento - Adiantamento do 13º Salário | E32: 31778759 | F32: =E32 -> 31778759
B33: 4.3.9 Ajuste VAAR | E33: 0 | F33: =E33+'Saldos - 05-2025'!F31 -> 164645.69
B34: 4.3.10 GRU-GUIA RECOLHIM. UNIAO | F34: =E34+'Saldos - 05-2025'!F32 -> 3671.58
B35: 4.3.11 Pagamentos Diversos - Folha | E35: 10385.47 | F35: =E35+'Saldos - 05-2025'!F33 -> 30444.59
B36: 4.4 Tarifa bancária | E36: 35.4 | F36: =E36+'Saldos - 05-2025'!F34 -> 7525.91
B37: 4.5 (-) Aplicações Efetuadas | E37: 76985901 | F37: =E37+'Saldos - 05-2025'!F35 -> 5.2393255e+08
B38: 5. Total Geral das Saídas | E38: =SUM(E22:E37) -> 1.8843552e+08 | F38: =SUM(F22:F37) -> 9.8956733e+08 | G38: OK | H38: =E38-E14 -> 0 | I38: =F38-F14 -> 0
B39: 6.1 (-) Cota DAF Deb | E39: =-E22 -> -48096.89 | F39: =E39+'Saldos - 05-2025'!F37 -> -260254.46
B40: 6.2 (-) Aplicações Efetuadas | E40: =-E37 -> -76985901 | F40: =E40+'Saldos - 05-2025'!F38 -> -5.2393255e+08
B41: 6.3 (-) O.B.s Canceladas (2025GD00955) | E41: =-E12 -> -103.93 | F41: =E41+'Saldos - 05-2025'!F39 -> -422.97
B42: 6.4 (-) Tarifa bancária | E42: =-E36 -> -35.4 | F42: =E42+'Saldos - 05-2025'!F40 -> -7525.91
B43: 6.5 (-) Pagamento Folha não regularizado | F43: =E43+'Saldos - 05-2025'!F41 -> -69976153
B44: 6.6 (-) Ajustes VAAR | F44: =E44+'Saldos - 05-2025'!F42 -> -164645.69
B45: 6.7 (-) Pagamentos Diversos | E45: =-E35 -> -10385.47 | F45: =E45+'Saldos - 05-2025'!F43 -> -30444.59
B46: 6.7 (+) Regularização de Folha e não Pago | E46: =35765074.17+12169.5 -> 35777244 | F46: =E46+'Saldos - 05-2025'!F44 -> 70055265
B47: 6.8.1 (-) GRU Paga e Não Regularizada | F47: =E47+'Saldos - 05-2025'!F45 -> -667.56
B48: 6.8.2 (+) Regularização de GRU Paga em Abril | F48: =E48+'Saldos - 05-2025'!F46 -> 667.56
B49: 6.8.3 (+) Regularização de GRU Não Paga em Maio | F49: =E49+'Saldos - 05-2025'!F47 -> 333.78
B50: Despesa Total do Mês ( confere com o relatório de execução financeira do SEAFI ) | E50: =SUM(E38:E49) -> 1.4716825e+08 | F50: =SUM(F38:F49) -> 4.6525093e+08
E51: =147168245.16-E50 -> 0
B52: CONTA INVESTIMENTO
B53: saldo Inicial | E53: 1.3991001e+08
B54: Aplicação | E54: 76985901
B55: Resgaste | E55: 85179607
B56: Rendimento Bruto | E56: 972555.2
B57: Saldo Atual | E57: =E53+E54-E55+E56 -> 1.3268886e+08

Sheet Cálculo Conciliação 3º Bimestre
C3: Saldo dos Pagamentos do SEAFI | D3: =SUM(D5:D9) -> 1.4604409e+08 | E3: =D3-'[1]Demonst Exec Financ Conciliado'!$J$89 -> 11470.64
C5: Extrato de Janeiro | D5: =[2]Janeiro!G1 -> 58285284
C6: SEAFI a maior | D6: 8949.47 | G6: =D6+D5 -> 58294233
C7: Extrato de Fevereiro | D7: =[2]Fevereiro!G1 -> 88938686
C8: SEAFI a menor ( regularizado em março ) | D8: -1194723.6 | E8: pago em março
C9: SEAFI a maior | D9: 5894.85 | G9: =SUM(D7:D9) -> 87749857
C11: COMPOSIÇÃO DE SALDO DO FUNDEB
C12: 3º BIMESTRE DE 2025
C14: Dsiponibilidade Financeira em 31/12/2024 | D14: 15778860
C15: ( + ) Ingressos = Transferências Constitucionais - janeiro-2025 | D15: 92936040
C16: ( + ) Ingressos = Transferências Constitucionais - fevereiro-2025 | D16: 1.115289e+08 | I16: =D16+D15 -> 2.0446494e+08
C17: ( + ) Ingressos = Transferências Constitucionais - Março-2025 | D17: 83756928
C18: ( + ) Ingressos = Transferências Constitucionais - Abril-2025 | D18: 82197615 | I18: =D18+D17+D16+D15 -> 3.7041948e+08
C19: ( + ) Ingressos = Transferências Constitucionais - Maio-2025 | D19: ='Saldos - 05-2025'!E19 -> 1.0410939e+08
C20: ( + ) Ingressos = Transferências Constitucionais - Junho-2025 | D20: ='Saldos - 06-2025'!E19 -> 1.0320772e+08 | I20: =D18+D17+D16+D15+D19+D20 -> 5.7773659e+08
C21: ( + ) Ingressos = Rendimentos do FUNDEB - 1º Bimestre | D21: 901662.73
C22: ( + ) Ingressos = Rendimentos do FUNDEB - 2º Bimestre | D22: 1438396.9
C23: ( + ) Ingressos = Rendimentos do FUNDEB - 3º Bimestre | D23: 2042692.5 | I23: =D23+D22+D21 -> 4382752.2
C24: ( - ) Pagamentos Efetuados = Relatório de Execução Financeira | D24: -4.6525093e+08
C25: ( - ) Pagto Tarifa Bancária não regularizada no SEAFI | D25: =-'Saldos - 04-2025'!F33 -> -7490.51 | I25: =D25+D28 -> -37935.1
C26: ( - ) Pagto de Folha - não regularizado | D26: 79521.49
C27: ( - ) Folha Regularizada e não Paga
C28: ( - ) Pagamentos Diversos - Folha | D28: ='Saldos - 06-2025'!F45 -> -30444.59
C31: ( = ) Saldo do SIOPE | D31: =SUM(D14:D30) -> 1.3268886e+08
C33: Dsiponibilidade Financeira em 30/06/2025 | D33: ='Saldos - 06-2025'!E57 -> 1.3268886e+08
C35: Diferença a identificar | D35: =D31-D33 -> -0.010000125

Sheet Detalhamento RE - 3º Bimestre
A2: TOTAL | B2: Data | C2: Nº RE | D2: Nº OB | E2: DESCRIÇÃO | F2: DETALHAMENTO | G2: =SUM(G3:G27) -> 35161499 | H2: Nº GD
A3: Vlr Individual | B3: 45785 | C3: 2025RE00370 | D3: 2025OB10900 | E3: Folha de Pagamento | F3: ASPA MENSALIDADE | G3: 176
A4: Vlr Individual | B4: 45785 | C4: 2025RE00370 | D4: 2025OB10902 | E4: Folha de Pagamento | F4: ASPEB | G4: 20371.72
A5: Vlr Individual | B5: 45785 | C5: 2025RE00370 | D5: 2025OB10905 | E5: Folha de Pagamento | F5: HSBC BAMERINDUS SEGUROS | G5: 9384.76
A6: Vlr Individual | B6: 45785 | C6: 2025RE00370 | D6: 2025OB10907 | E6: Folha de Pagamento | F6: BANCO MASTER S.A | G6: 728012.77
A7: Vlr Individual | B7: 45785 | C7: 2025RE00370 | D7: 2025OB10909 | E7: Folha de Pagamento | F7: BANCO OLE BONSUCESSO CONSIGNADO S/A | G7: 44612.14
A8: Vlr Individual | B8: 45785 | C8: 2025RE00370 | D8: 2025OB10910 | E8: Folha de Pagamento | F8: BANCO CRUZEIRO DO SUL S/A | G8: 302.39
A9: Vlr Individual | B9: 45785 | C9: 2025RE00370 | D9: 2025OB10911 | E9: Folha de Pagamento | F9: BANCO INDUSTRIAL DO BRASIL S/A - BI | G9: 377372.39
A10: Vlr Individual | B10: 45785 | C10: 2025RE00370 | D10: 2025OB10913 | E10: Folha de Pagamento | F10: BANCO RURAL- EM LIQUIDAÇÃO EXTRAJUDICIAL | G10: 84
A11: Vlr Individual | B11: 45785 | C11: 2025RE00370 | D11: 2025OB10914 | E11: Folha de Pagamento | F11: BANCO DO BRASIL S/A | G11: 8704419.6
A12: Vlr Individual | B12: 45785 | C12: 2025RE00370 | D12: 2025OB10915 | E12: Folha de Pagamento | F12: CAPEMISA SEGURADORA DE VIDA E PRESIDENCIA S/A | G12: 4218.36
A13: Vlr Individual | B13: 45785 | C13: 2025RE00370 | D13: 2025OB10918 | E13: Folha de Pagamento | F13: BANCO SANTANDER BANESPA S.A | G13: 3105777
A14: Vlr Individual | B14: 45785 | C14: 2025RE00370 | D14: 2025OB10920 | E14: Folha de Pagamento | F14: AGENCIA DE FOMENTO DO AMAPA S/A AFAP | G14: 24549.32
A15: Vlr Individual | B15: 45785 | C15: 2025RE00370 | D15: 2025OB10922 | E15: Folha de Pagamento | F15: R.S.P.P.ASS.PREV.PRIVADA | G15: 103.93 | H15: 2025GD00955
A16: Vlr Individual | B16: 45785 | C16: 2025RE00370 | D16: 2025OB10923 | E16: Folha de Pagamento | F16: SINSEPEAP-SIND.SERV.PUB.EDUC.AP | G16: 177854.37
A17: Vlr Individual | B17: 45785 | C17: 2025RE00370 | D17: 2025OB10926 | E17: Folha de Pagamento | F17: SUL AMERICA SEGUROS DE VIDA E PREVIDENCIA S/A. | G17: 320.23
A18: Vlr Individual | B18: 45785 | C18: 2025RE00370 | D18: 2025OB10928 | E18: Folha de Pagamento | F18: PDT CONTRIBUIÇÃO | G18: 470.99
A19: Vlr Individual | B19: 45785 | C19: 2025RE00370 | D19: 2025OB10929 | E19: Folha de Pagamento | F19: GOVERNO DO ESTADO DO AMAPA | G19: 8405404.1
A20: Vlr Individual | B20: 45785 | C20: 2025RE00370 | D20: 2025OB10931 | E20: Folha de Pagamento | F20: GOVERNO DO ESTADO DO AMAPA | G20: 20217.84
A21: Vlr Individual | B21: 45785 | C21: 2025RE00370 | D21: 2025OB10932 | E21: Folha de Pagamento | F21: AMAPÁ PREVIDÊNCIA | G21: 2799173.6
A22: Vlr Individual | B22: 45785 | C22: 2025RE00370 | D22: 2025OB10933 | E22: Folha de Pagamento | F22: AMAPÁ PREVIDÊNCIA | G22: 5409359.1
A23: Vlr Individual | B23: 45785 | C23: 2025RE00370 | D23: 2025OB10935 | E23: Folha de Pagamento | F23: AMAPÁ PREVIDÊNCIA | G23: 11584.81
A24: Vlr Individual | B24: 45785 | C24: 2025RE00370 | D24: 2025OB10936 | E24: Folha de Pagamento | F24: AMAPÁ PREVIDÊNCIA | G24: 2799173.6
A25: Vlr Individual | B25: 45785 | C25: 2025RE00370 | D25: 2025OB10938 | E25: Folha de Pagamento | F25: AMAPÁ PREVIDÊNCIA | G25: 627978.99
A26: Vlr Individual | B26: 45785 | C26: 2025RE00370 | D26: 2025OB10939 | E26: Folha de Pagamento | F26: AMAPÁ PREVIDÊNCIA | G26: 1878992.3
A27: Vlr Individual | B27: 45785 | C27: 2025RE00370 | D27: 2025OB10941 | E27: Folha de Pagamento | F27: AMAPÁ PREVIDÊNCIA | G27: 11584.81
A29: TOTAL | B29: Data | C29: Nº RE | D29: Nº OB | E29: DESCRIÇÃO | F29: DETALHAMENTO | G29: =SUM(G30:G47) -> 6964816.8 | H29: Nº GD
A30: Vlr Individual | B30: 45785 | C30: 2025RE00371 | D30: 2025OB10899 | E30: Folha de Pagamento | F30: ALLIANZ SEGUROS S.A | G30: 19.58
A31: Vlr Individual | B31: 45785 | C31: 2025RE00371 | D31: 2025OB10901 | E31: Folha de Pagamento | F31: ASPBRAS-ASSOC.DOS SERV.PUBLICOS BRASILEIROS. | G31: 88
A32: Vlr Individual | B32: 45785 | C32: 2025RE00371 | D32: 2025OB10903 | E32: Folha de Pagamento | F32: ASS.ASSIST.FUNC.PUBLICO MENSALIDADE | G32: 229
A33: Vlr Individual | B33: 45785 | C33: 2025RE00371 | D33: 2025OB10904 | E33: Folha de Pagamento | F33: ASSEGUP MENS | G33: 165
A34: Vlr Individual | B34: 45785 | C34: 2025RE00371 | D34: 2025OB10906 | E34: Folha de Pagamento | F34: BANCO BMG S/A | G34: 1728.19
A35: Vlr Individual | B35: 45785 | C35: 2025RE00371 | D35: 2025OB10908 | E35: Folha de Pagamento | F35: BANCO MASTER S.A | G35: 374812.87
A36: Vlr Individual | B36: 45785 | C36: 2025RE00371 | D36: 2025OB10912 | E36: Folha de Pagamento | F36: BANCO PANAMERICANO S/A | G36: 745
A37: Vlr Individual | B37: 45785 | C37: 2025RE00371 | D37: 2025OB10916 | E37: Folha de Pagamento | F37: GOVERNO DO ESTADO DO AMAPA | G37: 3475023.3
A38: Vlr Individual | B38: 45785 | C38: 2025RE00371 | D38: 2025OB10917 | E38: Folha de Pagamento | F38: BANCO FINASA BMC S/A | G38: 100.68
A39: Vlr Individual | B39: 45785 | C39: 2025RE00371 | D39: 2025OB10919 | E39: Folha de Pagamento | F39: AGENCIA DE FOMENTO DO AMAPA S/A AFAP | G39: 113705.76
A40: Vlr Individual | B40: 45785 | C40: 2025RE00371 | D40: 2025OB10921 | E40: Folha de Pagamento | F40: AGENCIA DE FOMENTO DO AMAPA S/A AFAP | G40: 7877.86
A41: Vlr Individual | B41: 45785 | C41: 2025RE00371 | D41: 2025OB10924 | E41: Folha de Pagamento | F41: SINDICATO DOS EMPREG. EM EMP. DE PROC. DE DADOS, INFORM. E TECNOL.D... | G41: 13.09
... A47: Vlr Individual | B47: 45785 | C47: 2025RE00371 | D47: 2025OB10940 | E47: Folha de Pagamento | F47: AMAPÁ PREVIDÊNCIA | G47: 586.63
A49: TOTAL | B49: Data | C49: Nº RE | D49: Nº OB | E49: DESCRIÇÃO | F49: DETALHAMENTO | G49: =SUM(G50:G52) -> 70643.92 | H49: Nº GD
A50: Vlr Individual | B50: 45796 | C50: 2025RE00396 | D50: 2025OB12215 | E50: Folha de Pagamento | F50: SECRETARIA DA RECEITA FEDERAL DO BRASIL (MINISTÉRIO DA FAZENDA) | G50: 18647.45
A51: Vlr Individual | B51: 45796 | C51: 2025RE00396 | D51: 2025OB12216 | E51: Folha de Pagamento | F51: SECRETARIA DA RECEITA FEDERAL DO BRASIL (MINISTÉRIO DA FAZENDA) | G51: 47269.52
A52: Vlr Individual | B52: 45796 | C52: 2025RE00396 | D52: 2025OB12217 | E52: Folha de Pagamento | F52: SECRETARIA DA RECEITA FEDERAL DO BRASIL (MINISTÉRIO DA FAZENDA) | G52: 4726.95
A54: TOTAL | B54: Data | C54: Nº RE | D54: Nº OB | E54: DESCRIÇÃO | F54: DETALHAMENTO | G54: =SUM(G55:G79) -> 19672891 | H54: Nº GD
A55: Vlr Individual | B55: 45811 | C55: 2025RE00483 | D55: 2025OB15051 | E55: Folha de Pagamento | F55: ALLIANZ SEGUROS S.A | G55: 19.58
A56: Vlr Individual | B56: 45811 | C56: 2025RE00483 | D56: 2025OB15052 | E56: Folha de Pagamento | F56: ASPA MENSALIDADE | G56: 176
A57: Vlr Individual | B57: 45811 | C57: 2025RE00483 | D57: 2025OB15054 | E57: Folha de Pagamento | F57: ASPEB | G57: 20475.73
A58: Vlr Individual | B58: 45811 | C58: 2025RE00483 | D58: 2025OB15055 | E58: Folha de Pagamento | F58: ASS.ASSIST.FUNC.PUBLICO MENSALIDADE | G58: 229
A59: Vlr Individual | B59: 45811 | C59: 2025RE00483 | D59: 2025OB15056 | E59: Folha de Pagamento | F59: ASSEGUP MENS | G59: 150
A60: Vlr Individual | B60: 45811 | C60: 2025RE00483 | D60: 2025OB15057 | E60: Folha de Pagamento | F60: HSBC BAMERINDUS SEGUROS | G60: 9189.23
A61: Vlr Individual | B61: 45811 | C61: 2025RE00483 | D61: 2025OB15059 | E61: Folha de Pagamento | F61: BANCO MASTER S.A | G61: 726316.13
A62: Vlr Individual | B62: 45811 | C62: 2025RE00483 | D62: 2025OB15060 | E62: Folha de Pagamento | F62: BANCO MASTER S.A | G62: 377425.2
A63: Vlr Individual | B63: 45811 | C63: 2025RE00483 | D63: 2025OB15062 | E63: Folha de Pagamento | F63: BANCO CRUZEIRO DO SUL S/A | G63: 302.39
A64: Vlr Individual | B64: 45811 | C64: 2025RE00483 | D64: 2025OB15064 | E64: Folha de Pagamento | F64: BANCO PANAMERICANO S/A | G64: 745
A65: Vlr Individual | B65: 45811 | C65: 2025RE00483 | D65: 2025OB15065 | E65: Folha de Pagamento | F65: BANCO RURAL- EM LIQUIDAÇÃO EXTRAJUDICIAL | G65: 84
A66: Vlr Individual | B66: 45811 | C66: 2025RE00483 | D66: 2025OB15067 | E66: Folha de Pagamento | F66: CAPEMISA SEGURADORA DE VIDA E PRESIDENCIA S/A | G66: 4218.36
... A79: Vlr Individual | B79: 45811 | C79: 2025RE00483 | D79: 2025OB15087 | E79: Folha de Pagamento | F79: AMAPÁ PREVIDÊNCIA | G79: 632935.38
A81: TOTAL | B81: Data | C81: Nº RE | D81: Nº OB | E81: DESCRIÇÃO | F81: DETALHAMENTO | G81: =SUM(G82:G94) -> 23414462 | H81: Nº GD
A82: Vlr Individual | B82: 45811 | C82: 2025RE00484 | D82: 2025OB15053 | E82: Folha de Pagamento | F82: ASPBRAS-ASSOC.DOS SERV.PUBLICOS BRASILEIROS. | G82: 88
A83: Vlr Individual | B83: 45811 | C83: 2025RE00484 | D83: 2025OB15058 | E83: Folha de Pagamento | F83: BANCO BMG S/A | G83: 1664.16
A84: Vlr Individual | B84: 45811 | C84: 2025RE00484 | D84: 2025OB15061 | E84: Folha de Pagamento | F84: BANCO OLE BONSUCESSO CONSIGNADO S/A | G84: 42269.67
A85: Vlr Individual | B85: 45811 | C85: 2025RE00484 | D85: 2025OB15063 | E85: Folha de Pagamento | F85: BANCO INDUSTRIAL DO BRASIL S/A - BI | G85: 413510.35
A86: Vlr Individual | B86: 45811 | C86: 2025RE00484 | D86: 2025OB15066 | E86: Folha de Pagamento | F86: BANCO DO BRASIL S/A | G86: 8868234
A87: Vlr Individual | B87: 45811 | C87: 2025RE00484 | D87: 2025OB15068 | E87: Folha de Pagamento | F87: GOVERNO DO ESTADO DO AMAPA | G87: 3616616.7
A88: Vlr Individual | B88: 45811 | C88: 2025RE00484 | D88: 2025OB15071 | E88: Folha de Pagamento | F88: AGENCIA DE FOMENTO DO AMAPA S/A AFAP | G88: 115787.61
A89: Vlr Individual | B89: 45811 | C89: 2025RE00484 | D89: 2025OB15074 | E89: Folha de Pagamento | F89: R.S.P.P.ASS.PREV.PRIVADA | G89: 103.93 | H89: 2025GD00978
A90: Vlr Individual | B90: 45811 | C90: 2025RE00484 | D90: 2025OB15076 | E90: Folha de Pagamento | F90: SINDICATO DOS EMPREG. EM EMP. DE PROC. DE DADOS... | G90: 13.09
A91: Vlr Individual | B91: 45811 | C91: 2025RE00484 | D91: 2025OB15079 | E91: Folha de Pagamento | F91: UNIODONTO | G91: 85902
A92: Vlr Individual | B92: 45811 | C92: 2025RE00484 | D92: 2025OB15084 | E92: Folha de Pagamento | F92: AMAPÁ PREVIDÊNCIA | G92: 5474104.3
A93: Vlr Individual | B93: 45811 | C93: 2025RE00484 | D93: 2025OB15086 | E93: Folha de Pagamento | F93: AMAPÁ PREVIDÊNCIA | G93: 2902346.2
A94: Vlr Individual | B94: 45811 | C94: 2025RE00484 | D94: 2025OB15088 | E94: Folha de Pagamento | F94: AMAPÁ PREVIDÊNCIA | G94: 1893822.4
A96: TOTAL | B96: Data | C96: Nº RE | D96: Nº OB | E96: DESCRIÇÃO | F96: DETALHAMENTO | G96: =G97 -> 45000.24 | H96: Nº GD
A97: Vlr Individual | B97: 45821 | C97: 2025RE00519 | D97: 2025OB15972 | E97: Folha de Pagamento | F97: AMAPÁ PREVIDÊNCIA | G97: 45000.24
A99: TOTAL | B99: Data | C99: Nº RE | D99: Nº OB | E99: DESCRIÇÃO | F99: DETALHAMENTO | G99: =SUM(G100:G102) -> 68491.71 | H99: Nº GD
A100: Vlr Individual | B100: 45825 | C100: 2025RE00525 | D100: 2025OB16776 | E100: Folha de Pagamento | F100: SECRETARIA DA RECEITA FEDERAL DO BRASIL (MINISTÉRIO DA FAZENDA) | G100: 18077.61
A101: Vlr Individual | B101: 45825 | C101: 2025RE00525 | D101: 2025OB16777 | E101: Folha de Pagamento | F101: SECRETARIA DA RECEITA FEDERAL DO BRASIL (MINISTÉRIO DA FAZENDA) | G101: 45831
A102: Vlr Individual | B102: 45825 | C102: 2025RE00525 | D102: 2025OB16778 | E102: Folha de Pagamento | F102: SECRETARIA DA RECEITA FEDERAL DO BRASIL (MINISTÉRIO DA FAZENDA) | G102: 4583.1
A104: TOTAL | B104: Data | C104: Nº RE | D104: Nº OB | E104: DESCRIÇÃO | F104: DETALHAMENTO | G104: =G105 -> 333.78 | H104: Nº GD
A105: Vlr Individual | B105: 45838 | C105: 2025RE00611 | D105: 2025OB18466 | E105: Folha de Pagamento | F105: GOVERNO DO ESTADO DO AMAPA | G105: 333.78

Sheet Detalhamento RE - 4º Bimestre
A2: TOTAL | B2: Data | C2: Nº RE | D2: Nº OB | E2: DESCRIÇÃO | F2: DETALHAMENTO | G2: =SUM(G3:G27) -> 38093642 | H2: Nº GD
A3: Vlr Individual | B3: 45846 | C3: 2025RE00633 | D3: 2025OB18951 | E3: Folha de Pagamento | F3: ALLIANZ SEGUROS S.A | G3: 19.58
A4: Vlr Individual | B4: 45846 | C4: 2025RE00633 | D4: 2025OB18952 | E4: Folha de Pagamento | F4: ASPA MENSALIDADE | G4: 176
A5: Vlr Individual | B5: 45846 | C5: 2025RE00633 | D5: 2025OB18953 | E5: Folha de Pagamento | F5: ASPBRAS-ASSOC.DOS SERV.PUBLICOS BRASILEIROS. | G5: 88
A6: Vlr Individual | B6: 45846 | C6: 2025RE00633 | D6: 2025OB18955 | E6: Folha de Pagamento | F6: ASS.ASSIST.FUNC.PUBLICO MENSALIDADE | G6: 239
A7: Vlr Individual | B7: 45846 | C7: 2025RE00633 | D7: 2025OB18956 | E7: Folha de Pagamento | F7: ASSEGUP MENS | G7: 150
A8: Vlr Individual | B8: 45846 | C8: 2025RE00633 | D8: 2025OB18957 | E8: Folha de Pagamento | F8: HSBC BAMERINDUS SEGUROS | G8: 9227.89
A9: Vlr Individual | B9: 45846 | C9: 2025RE00633 | D9: 2025OB18959 | E9: Folha de Pagamento | F9: BANCO MASTER S.A | G9: 763213.66
A10: Vlr Individual | B10: 45846 | C10: 2025RE00633 | D10: 2025OB18961 | E10: Folha de Pagamento | F10: BANCO OLE BONSUCESSO CONSIGNADO S/A | G10: 41814.23
A11: Vlr Individual | B11: 45846 | C11: 2025RE00633 | D11: 2025OB18963 | E11: Folha de Pagamento | F11: BANCO INDUSTRIAL DO BRASIL S/A - BI | G11: 414429.64
A12: Vlr Individual | B12: 45846 | C12: 2025RE00633 | D12: 2025OB18964 | E12: Folha de Pagamento | F12: BANCO PANAMERICANO S/A | G12: 745
A13: Vlr Individual | B13: 45846 | C13: 2025RE00633 | D13: 2025OB18965 | E13: Folha de Pagamento | F13: BANCO RURAL- EM LIQUIDAÇÃO EXTRAJUDICIAL | G13: 84
A14: Vlr Individual | B14: 45846 | C14: 2025RE00633 | D14: 2025OB18966 | E14: Folha de Pagamento | F14: BANCO DO BRASIL S/A | G14: 9022167.5
... A17: Vlr Individual | B17: 45846 | C17: 2025RE00633 | D17: 2025OB18971 | E17: Folha de Pagamento | F17: AGENCIA DE FOMENTO DO AMAPA S/A AFAP | G17: 24039.72
A18: Vlr Individual | B18: 45846 | C18: 2025RE00633 | D18: 2025OB18973 | E18: Folha de Pagamento | F18: R.S.P.P.ASS.PREV.PRIVADA | G18: 103.93 | H18: 2025GD01012
A19: Vlr Individual | B19: 45846 | C19: 2025RE00633 | D19: 2025OB18975 | E19: Folha de Pagamento | F19: SINDICATO DOS EMPREG. EM EMP. DE PROC. DE DADOS... | G19: 13.09
A20: Vlr Individual | B20: 45846 | C20: 2025RE00633 | D20: 2025OB18978 | E20: Folha de Pagamento | F20: UNIODONTO | G20: 87392.5
A21: Vlr Individual | B21: 45846 | C21: 2025RE00633 | D21: 2025OB18980 | E21: Folha de Pagamento | F21: GOVERNO DO ESTADO DO AMAPA | G21: 9142923.5
A22: Vlr Individual | B22: 45846 | C22: 2025RE00633 | D22: 2025OB18981 | E22: Folha de Pagamento | F22: GOVERNO DO ESTADO DO AMAPA | G22: 10579.73
A23: Vlr Individual | B23: 45846 | C23: 2025RE00633 | D23: 2025OB18982 | E23: Folha de Pagamento | F23: AMAPÁ PREVIDÊNCIA | G23: 2804524.4
A24: Vlr Individual | B24: 45846 | C24: 2025RE00633 | D24: 2025OB18983 | E24: Folha de Pagamento | F24: AMAPÁ PREVIDÊNCIA | G24: 5513960.6
A25: Vlr Individual | B25: 45846 | C25: 2025RE00633 | D25: 2025OB18984 | E25: Folha de Pagamento | F25: AMAPÁ PREVIDÊNCIA | G25: 2804524.4
A26: Vlr Individual | B26: 45846 | C26: 2025RE00633 | D26: 2025OB18985 | E26: Folha de Pagamento | F26: AMAPÁ PREVIDÊNCIA | G26: 2972397.5
A27: Vlr Individual | B27: 45846 | C27: 2025RE00633 | D27: 2025OB18986 | E27: Folha de Pagamento | F27: AMAPÁ PREVIDÊNCIA | G27: 636644
A29: TOTAL | B29: Data | C29: Nº RE | D29: Nº OB | E29: DESCRIÇÃO | F29: DETALHAMENTO | G29: =SUM(G30:G41) -> 5702522.3 | H29: Nº GD
A30: Vlr Individual | B30: 45846 | C30: 2025RE00634 | D30: 2025OB18954 | E30: Folha de Pagamento | F30: ASPEB | G30: 20490.5
A31: Vlr Individual | B31: 45846 | C31: 2025RE00634 | D31: 2025OB18958 | E31: Folha de Pagamento | F31: BANCO BMG S/A | G31: 1664.16
A32: Vlr Individual | B32: 45846 | C32: 2025RE00634 | D32: 2025OB18960 | E32: Folha de Pagamento | F32: BANCO MASTER S.A | G32: 406034.78
A33: Vlr Individual | B33: 45846 | C33: 2025RE00634 | D33: 2025OB18962 | E33: Folha de Pagamento | F33: BANCO CRUZEIRO DO SUL S/A | G33: 302.39
A34: Vlr Individual | B34: 45846 | C34: 2025RE00634 | D34: 2025OB18967 | E34: Folha de Pagamento | F34: CAPEMISA SEGURADORA DE VIDA E PRESIDENCIA S/A | G34: 4218.36
A35: Vlr Individual | B35: 45846 | C35: 2025RE00634 | D35: 2025OB18969 | E35: Folha de Pagamento | F35: BANCO SANTANDER BANESPA S.A | G35: 3176336.3
A36: Vlr Individual | B36: 45846 | C36: 2025RE00634 | D36: 2025OB18972 | E36: Folha de Pagamento | F36: AGENCIA DE FOMENTO DO AMAPA S/A AFAP | G36: 9639.31
A37: Vlr Individual | B37: 45846 | C37: 2025RE00634 | D37: 2025OB18974 | E37: Folha de Pagamento | F37: SINSEPEAP-SIND.SERV.PUB.EDUC.AP | G37: 177648.81
A38: Vlr Individual | B38: 45846 | C38: 2025RE00634 | D38: 2025OB18976 | E38: Folha de Pagamento | F38: SIND. DOS SERVIDORES GRUPO GESTÃO ADM DO EST. DO AP - SINSGAAP | G38: 536.78
A39: Vlr Individual | B39: 45846 | C39: 2025RE00634 | D39: 2025OB18977 | E39: Folha de Pagamento | F39: SUL AMERICA SEGUROS DE VIDA E PREVIDENCIA S/A. | G39: 320.23
A40: Vlr Individual | B40: 45846 | C40: 2025RE00634 | D40: 2025OB18979 | E40: Folha de Pagamento | F40: PDT CONTRIBUIÇÃO | G40: 411.56
A41: Vlr Individual | B41: 45846 | C41: 2025RE00634 | D41: 2025OB18987 | E41: Folha de Pagamento | F41: AMAPÁ PREVIDÊNCIA | G41: 1904919.1
A43: TOTAL | B43: Data | C43: Nº RE | D43: Nº OB | E43: DESCRIÇÃO | F43: DETALHAMENTO | G43: =SUM(G44:G47) -> 97539.73 | H43: Nº GD
A44: Vlr Individual | B44: 45847 | C44: 2025RE00638 | D44: 2025OB19019 | E44: Folha de Pagamento | F44: GOVERNO DO ESTADO DO AMAPA | G44: 23386.28 | I44: Regularizado em agosto
A45: Vlr Individual | B45: 45847 | C45: 2025RE00638 | D45: 2025OB19020 | E45: Folha de Pagamento | F45: GOVERNO DO ESTADO DO AMAPA | G45: 36476.48
A46: Vlr Individual | B46: 45847 | C46: 2025RE00638 | D46: 2025OB19021 | E46: Folha de Pagamento | F46: GOVERNO DO ESTADO DO AMAPA | G46: 22282.67
A47: Vlr Individual | B47: 45847 | C47: 2025RE00638 | D47: 2025OB19022 | E47: Folha de Pagamento | F47: GOVERNO DO ESTADO DO AMAPA | G47: 15394.3
A49: TOTAL | B49: Data | C49: Nº RE | D49: Nº OB | E49: DESCRIÇÃO | F49: DETALHAMENTO | G49: =SUM(G50:G53) -> 872518.09 | H49: Nº GD
A50: Vlr Individual | B50: 45854 | C50: 2025RE00703 | D50: 2025OB20787 | E50: Folha de Pagamento | F50: SECRETARIA DA RECEITA FEDERAL DO BRASIL (MINISTÉRIO DA FAZENDA) | G50: 18136.3
A51: Vlr Individual | B51: 45854 | C51: 2025RE00703 | D51: 2025OB20788 | E51: Folha de Pagamento | F51: GOVERNO DO ESTADO DO AMAPA | G51: 803815.31
A52: Vlr Individual | B52: 45854 | C52: 2025RE00703 | D52: 2025OB20789 | E52: Folha de Pagamento | F52: SECRETARIA DA RECEITA FEDERAL DO BRASIL (MINISTÉRIO DA FAZENDA) | G52: 45969.53
A53: Vlr Individual | B53: 45854 | C53: 2025RE00703 | D53: 2025OB20790 | E53: Folha de Pagamento | F53: SECRETARIA DA RECEITA FEDERAL DO BRASIL (MINISTÉRIO DA FAZENDA) | G53: 4596.95
A55: TOTAL | B55: Data | C55: Nº RE | D55: Nº OB | E55: DESCRIÇÃO | F55: DETALHAMENTO | G55: =SUM(G56:G60) -> 334765.03 | H55: Nº GD
A56: Vlr Individual | B56: 45867 | C56: 2025RE00726 | D56: 2025OB21385 | E56: Folha de Pagamento | F56: GOVERNO DO ESTADO DO AMAPA | G56: 4471.86 | I56: Regularizado em agosto
A57: Vlr Individual | B57: 45867 | C57: 2025RE00726 | D57: 2025OB21386 | E57: Folha de Pagamento | F57: GOVERNO DO ESTADO DO AMAPA | G57: 86359.94
A58: Vlr Individual | B58: 45867 | C58: 2025RE00726 | D58: 2025OB21387 | E58: Folha de Pagamento | F58: GOVERNO DO ESTADO DO AMAPA | G58: 111563.41
A59: Vlr Individual | B59: 45867 | C59: 2025RE00726 | D59: 2025OB21388 | E59: Folha de Pagamento | F59: GOVERNO DO ESTADO DO AMAPA | G59: 77557.56
A60: Vlr Individual | B60: 45867 | C60: 2025RE00726 | D60: 2025OB21389 | E60: Folha de Pagamento | F60: GOVERNO DO ESTADO DO AMAPA | G60: 54812.26
A62: TOTAL | B62: Data | C62: Nº RE | D62: Nº OB | E62: DESCRIÇÃO | F62: DETALHAMENTO | G62: =SUM(G63:G87) -> 25894511 | H62: Nº GD
A63: Vlr Individual | B63: 45877 | C63: 2025RE00739 | D63: 2025OB21890 | E63: Folha de Pagamento | F63: GOVERNO DO ESTADO DO AMAPA | G63: 333.78
A64: Vlr Individual | B64: 45877 | C64: 2025RE00739 | D64: 2025OB21892 | E64: Folha de Pagamento | F64: ASPA MENSALIDADE | G64: 176
A65: Vlr Individual | B65: 45877 | C65: 2025RE00739 | D65: 2025OB21893 | E65: Folha de Pagamento | F65: ASPBRAS-ASSOC.DOS SERV.PUBLICOS BRASILEIROS. | G65: 88
A66: Vlr Individual | B66: 45877 | C66: 2025RE00739 | D66: 2025OB21895 | E66: Folha de Pagamento | F66: ASS.ASSIST.FUNC.PUBLICO MENSALIDADE | G66: 239
A67: Vlr Individual | B67: 45877 | C67: 2025RE00739 | D67: 2025OB21897 | E67: Folha de Pagamento | F67: HSBC BAMERINDUS SEGUROS | G67: 9182.76
A68: Vlr Individual | B68: 45877 | C68: 2025RE00739 | D68: 2025OB21898 | E68: Folha de Pagamento | F68: BANCO BMG S/A | G68: 1664.16
A69: Vlr Individual | B69: 45877 | C69: 2025RE00739 | D69: 2025OB21900 | E69: Folha de Pagamento | F69: BANCO MASTER S.A | G69: 414561.37
A70: Vlr Individual | B70: 45877 | C70: 2025RE00739 | D70: 2025OB21902 | E70: Folha de Pagamento | F70: BANCO CRUZEIRO DO SUL S/A | G70: 302.39
A71: Vlr Individual | B71: 45877 | C71: 2025RE00739 | D71: 2025OB21903 | E71: Folha de Pagamento | F71: BANCO INDUSTRIAL DO BRASIL S/A - BI | G71: 414190.84
A72: Vlr Individual | B72: 45877 | C72: 2025RE00739 | D72: 2025OB21905 | E72: Folha de Pagamento | F72: BANCO RURAL- EM LIQUIDAÇÃO EXTRAJUDICIAL | G72: 84
A73: Vlr Individual | B73: 45877 | C73: 2025RE00739 | D73: 2025OB21906 | E73: Folha de Pagamento | F73: BANCO DO BRASIL S/A | G73: 9048631
A74: Vlr Individual | B74: 45877 | C74: 2025RE00739 | D74: 2025OB21908 | E74: Folha de Pagamento | F74: GOVERNO DO ESTADO DO AMAPA | G74: 3830023.2
... A77: Vlr Individual | B77: 45877 | C77: 2025RE00739 | D77: 2025OB21912 | E77: Folha de Pagamento | F77: AGENCIA DE FOMENTO DO AMAPA S/A AFAP | G77: 9639.31
A78: Vlr Individual | B78: 45877 | C78: 2025RE00739 | D78: 2025OB21913 | E78: Folha de Pagamento | F78: R.S.P.P.ASS.PREV.PRIVADA | G78: 103.93 | H78: 2025GD01019
A79: Vlr Individual | B79: 45877 | C79: 2025RE00739 | D79: 2025OB21915 | E79: Folha de Pagamento | F79: SINDICATO DOS EMPREG. EM EMP. DE PROC. DE DADOS... | G79: 13.09
A80: Vlr Individual | B80: 45877 | C80: 2025RE00739 | D80: 2025OB21916 | E80: Folha de Pagamento | F80: SIND. DOS SERVIDORES GRUPO GESTÃO ADM DO EST. D... | G80: 536.78
A81: Vlr Individual | B81: 45877 | C81: 2025RE00739 | D81: 2025OB21918 | E81: Folha de Pagamento | F81: UNIODONTO | G81: 88088
A82: Vlr Individual | B82: 45877 | C82: 2025RE00739 | D82: 2025OB21919 | E82: Folha de Pagamento | F82: PDT CONTRIBUIÇÃO | G82: 411.56
A83: Vlr Individual | B83: 45877 | C83: 2025RE00739 | D83: 2025OB21921 | E83: Folha de Pagamento | F83: GOVERNO DO ESTADO DO AMAPA | G83: 4185.21
A84: Vlr Individual | B84: 45877 | C84: 2025RE00739 | D84: 2025OB21923 | E84: Folha de Pagamento | F84: AMAPÁ PREVIDÊNCIA | G84: 5521912.4
A85: Vlr Individual | B85: 45877 | C85: 2025RE00739 | D85: 2025OB21924 | E85: Folha de Pagamento | F85: AMAPÁ PREVIDÊNCIA | G85: 2799689.9
A86: Vlr Individual | B86: 45877 | C86: 2025RE00739 | D86: 2025OB21925 | E86: Folha de Pagamento | F86: AMAPÁ PREVIDÊNCIA | G86: 2979396.9
A87: Vlr Individual | B87: 45877 | C87: 2025RE00739 | D87: 2025OB21926 | E87: Folha de Pagamento | F87: AMAPÁ PREVIDÊNCIA | G87: 636882.58
A89: TOTAL | B89: Data | C89: Nº RE | D89: Nº OB | E89: DESCRIÇÃO | F89: DETALHAMENTO | G89: =SUM(G90:G102) -> 18077541 | H89: Nº GD
A90: Vlr Individual | B90: 45877 | C90: 2025RE00740 | D90: 2025OB21891 | E90: Folha de Pagamento | F90: ALLIANZ SEGUROS S.A | G90: 19.58
A91: Vlr Individual | B91: 45877 | C91: 2025RE00740 | D91: 2025OB21894 | E91: Folha de Pagamento | F91: ASPEB | G91: 20418.11
A92: Vlr Individual | B92: 45877 | C92: 2025RE00740 | D92: 2025OB21896 | E92: Folha de Pagamento | F92: ASSEGUP MENS | G92: 150
A93: Vlr Individual | B93: 45877 | C93: 2025RE00740 | D93: 2025OB21899 | E93: Folha de Pagamento | F93: BANCO MASTER S.A | G93: 779949.74
A94: Vlr Individual | B94: 45877 | C94: 2025RE00740 | D94: 2025OB21901 | E94: Folha de Pagamento | F94: BANCO OLE BONSUCESSO CONSIGNADO S/A | G94: 41266.43
A95: Vlr Individual | B95: 45877 | C95: 2025RE00740 | D95: 2025OB21904 | E95: Folha de Pagamento | F95: BANCO PANAMERICANO S/A | G95: 745
A96: Vlr Individual | B96: 45877 | C96: 2025RE00740 | D96: 2025OB21907 | E96: Folha de Pagamento | F96: CAPEMISA SEGURADORA DE VIDA E PRESIDENCIA S/A | G96: 4218.36
A97: Vlr Individual | B97: 45877 | C97: 2025RE00740 | D97: 2025OB21909 | E97: Folha de Pagamento | F97: BANCO SANTANDER BANESPA S.A | G97: 3169502.4
A98: Vlr Individual | B98: 45877 | C98: 2025RE00740 | D98: 2025OB21914 | E98: Folha de Pagamento | F98: SINSEPEAP-SIND.SERV.PUB.EDUC.AP | G98: 177307.53
A99: Vlr Individual | B99: 45877 | C99: 2025RE00740 | D99: 2025OB21917 | E99: Folha de Pagamento | F99: SUL AMERICA SEGUROS DE VIDA E PREVIDENCIA S/A. | G99: 320.23
A100: Vlr Individual | B100: 45877 | C100: 2025RE00740 | D100: 2025OB21920 | E100: Folha de Pagamento | F100: GOVERNO DO ESTADO DO AMAPA | G100: 9178321.2
A101: Vlr Individual | B101: 45877 | C101: 2025RE00740 | D101: 2025OB21922 | E101: Folha de Pagamento | F101: AMAPÁ PREVIDÊNCIA | G101: 2799689.9
A102: Vlr Individual | B102: 45877 | C102: 2025RE00740 | D102: 2025OB21927 | E102: Folha de Pagamento | F102: AMAPÁ PREVIDÊNCIA | G102: 1905632.9
A104: TOTAL | B104: Data | C104: Nº RE | D104: Nº OB | E104: DESCRIÇÃO | F104: DETALHAMENTO | G104: =SUM(G105:G107) -> 67528.53 | H104: Nº GD
A105: Vlr Individual | B105: 45884 | C105: 2025RE00756 | D105: 2025OB23046 | E105: Folha de Pagamento | F105: SECRETARIA DA RECEITA FEDERAL DO BRASIL (MINISTÉRIO DA FAZENDA) | G105: 17827.7
A106: Vlr Individual | B106: 45884 | C106: 2025RE00756 | D106: 2025OB23047 | E106: Folha de Pagamento | F106: SECRETARIA DA RECEITA FEDERAL DO BRASIL (MINISTÉRIO DA FAZENDA) | G106: 45182.57
A107: Vlr Individual | B107: 45884 | C107: 2025RE00756 | D107: 2025OB23048 | E107: Folha de Pagamento | F107: SECRETARIA DA RECEITA FEDERAL DO BRASIL (MINISTÉRIO DA FAZENDA) | G107: 4518.26

Sheet Saldos - 07-2025
B2: CONCILIAÇÃO BANCÁRIA DO EXTRATO BANCÁRIO - JULHO DE 2025
B4: 1. Ingressos | E4: Valores do Mês | F4: Acumulado
B5: 1.0 IPI - EXP | E5: 65206.6 | F5: =E5+'Saldos - 06-2025'!F5 -> 476447.68
B6: 1.1 VAAR | E6: 0 | F6: =E6+'Saldos - 06-2025'!F6 -> 1648620.1
B7: 1.2 FPE/FPM | E7: 52818284 | F7: =E7+'Saldos - 06-2025'!F7 -> 5.2392746e+08
B8: 1.3 ICMS | E8: 14031057 | F8: =E8+'Saldos - 06-2025'!F8 -> 1.0847178e+08
B9: 1.4 IPVA | E9: 2597901.8 | F9: =E9+'Saldos - 06-2025'!F9 -> 12959056
B10: 1.5 ITCMD | E10: 7573.12 | F10: =E10+'Saldos - 06-2025'!F10 -> 192089.52
B11: 1.6 ITR | E11: 438.17 | F11: =E11+'Saldos - 06-2025'!F11 -> 6493.86
B12: 1.7 ORDEM BANC CANCELADA | E12: 103.93 | F12: =E12+'Saldos - 06-2025'!F12 -> 638.08
B13: 1.8 RESGATE | E13: 75048205 | F13: =E13+'Saldos - 06-2025'!F13 -> 4.8645351e+08
B14: 2 Total das Entradas | E14: =SUM(E5:E13) -> 1.4456877e+08 | F14: =SUM(F5:F13) -> 1.1341361e+09 | H14: =('Extrato 07-2025'!C2+'Extrato 06-2025'!C2+'Extrato 05-2025'!C2+'Extrato 03-2025'!C2+'Extrato 04-2025'!C2+'Extrato 02-2025'!C2+'Extrato 01-2025'!C2)-F14 -> 1.4456877e+08
B15: 3.0 (-) IPI/Cota DAF Deb | E15: -41266.06 | F15: =E15+'Saldos - 06-2025'!F15 -> -301520.52
B16: 3.1 (-) Ordem Bancária Cancelada | E16: =-E12 -> -103.93 | F16: =E16+'Saldos - 06-2025'!F16 -> -638.08
B17: 3.2 (-) Resgastes efetuados | E17: =-E13 -> -75048205 | F17: =E17+'Saldos - 06-2025'!F17 -> -4.8645351e+08
B18: 3.3 (-) Ajuste VAAR - FNDE | E18: 0 | F18: -164645.69
B19: 3. Total Disponibizado( 1 - 3.0- 3.1 - 3.2 -3.3 - 3.4 ) | E19: =SUM(E14:E18) -> 69479194 | F19: =SUM(F14:F18) -> 6.4721578e+08 | G19: OK
B21: 4. Saídas | E21: Valores do Mês | F21: Acumulado
B22: 4.1 Cota DAF Deb | E22: 41266.06 | F22: =E22+'Saldos - 06-2025'!F22 -> 301520.52
B23: 4.2 O.B.s Canceladas | E23: 103.93 | F23: =E23+'Saldos - 06-2025'!F23 -> 103.93
B24: 4.3.1 Folha de Pagamento e Encargos - Identificados por RE | E24: 44668578 | F24: =E24+'Saldos - 06-2025'!F24 -> 2.5193109e+08
B25: 4.3.2 Folha de Pagamento - Folha 01/2025 | F25: =E25+'Saldos - 06-2025'!F25 -> 34311367
B26: 4.3.3 Folha de Pagamento - Folha 02/2025 | F26: =E26+'Saldos - 06-2025'!F26 -> 34175582
B27: 4.3.4 Folha de Pagamento - Folha 03/2025 | F27: =E27+'Saldos - 06-2025'!F27 -> 33980888
B28: 4.3.5 Folha de Pagamento - Folha 04/2025 | F28: =E28+'Saldos - 06-2025'!F28 -> 35798382
B29: 4.3.6 Folha de Pagamento - Folha 05/2025 | F29: =E29+'Saldos - 06-2025'!F29 -> 35751705
B30: 4.3.7 Folha de Pagamento - Folha 06/2025 | F30: =E30+'Saldos - 06-2025'!F30 -> 36411168
B31: 4.3.8 Folha de Pagamento - Folha 07/2025 | E31: 35846110 | F31: =E31 -> 35846110
B32: 4.3.9 Folha de Pagamento - Férias | E32: 18359120 | F32: =E32+'Saldos - 06-2025'!F31 -> 34056995
B33: 4.3.10 Folha de Pagamento - Adiantamento do 13º Salário | F33: =E33+'Saldos - 06-2025'!F32 -> 31778759
B34: 4.3.11 Ajuste VAAR | F34: =E34+'Saldos - 06-2025'!F33 -> 164645.69
B35: 4.3.12 GRU-GUIA RECOLHIM. UNIAO | E35: 333.78 | F35: =E35+'Saldos - 06-2025'!F34 -> 4005.36
B36: 4.3.13 Pagamentos Diversos - Folha | E36: 10029.56 | F36: =E36+'Saldos - 06-2025'!F35 -> 40474.15
B37: 4.4 Tarifa bancária | E37: 28.8 | F37: =E37+'Saldos - 06-2025'!F36 -> 7554.71
B38: 4.5 (-) Aplicações Efetuadas | E38: 45643200 | F38: =E38+'Saldos - 06-2025'!F37 -> 5.6957575e+08
B39: 5. Total Geral das Saídas | E39: =SUM(E22:E38) -> 1.4456877e+08 | F39: =SUM(F22:F38) -> 1.1341361e+09 | G39: OK
B40: 6.1 (-) Cota DAF Deb | E40: =-E22 -> -41266.06 | F40: =E40+'Saldos - 06-2025'!F39 -> -301520.52
B41: 6.2 (-) Aplicações Efetuadas | E41: =-E38 -> -45643200 | F41: =E41+'Saldos - 06-2025'!F40 -> -5.6957575e+08
B42: 6.3 (-) O.B.s Canceladas (2025GD00955) | E42: =-E23 -> -103.93 | F42: =E42+'Saldos - 06-2025'!F41 -> -526.9
B43: 6.4 (-) Tarifa bancária | E43: =-E37 -> -28.8 | F43: =E43+'Saldos - 06-2025'!F42 -> -7554.71
B44: 6.5 (-) Pagamento Folha não regularizado | F44: =E44+'Saldos - 06-2025'!F43 -> -69976153
B45: 6.6 (-) Ajustes VAAR | F45: =E45+'Saldos - 06-2025'!F44 -> -164645.69
B46: 6.7 (-) Pagamentos Diversos | E46: -10029.56 | F46: =E46+'Saldos - 06-2025'!F45 -> -40474.15
B47: 6.7 (+) Regularização de Folha e não Pago | E47: =14537.4600000009+1748.41999999806 -> 16285.88 | F47: =E47+'Saldos - 06-2025'!F46 -> 70071551
B48: 6.8.1 (-) GRU Paga e Não Regularizada | F48: =E48+'Saldos - 06-2025'!F47 -> -667.56
B49: 6.8.2 (+) Regularização de GRU Paga em Abril | F49: =E49+'Saldos - 06-2025'!F48 -> 667.56
B50: 6.8.3 (+) Regularização de GRU Não Paga em Maio | F50: =E50+'Saldos - 06-2025'!F49 -> 333.78
B51: Despesa Total do Mês ( confere com o relatório de execução financeira do SEAFI ) | E51: =SUM(E39:E50) -> 98890427 | F51: =SUM(F39:F50) -> 5.6414136e+08
B53: CONTA INVESTIMENTO
B54: saldo Inicial | E54: 1.3268886e+08
B55: Aplicação | E55: 45643200
B56: Resgaste | E56: 75048205
B57: Rendimento Bruto | E57: 1077343.9
B58: Saldo Atual | E58: =E54+E55-E56+E57 -> 1.0436119e+08

Sheet Extrato 07-2025
C2: =SUBTOTAL(9,C4:C75) -> 2.8913754e+08
A3: Data | B3: Historico | C3: Valor R$ | D3: Inf. | E3: Histórico | F3: Detalhamentos
A4: 02/07/2025 | B4: RECEBIMENTO DE ICMS | C4: 3335.05 | D4: C | E4: Transferência Constitucional - FUNDEB
A5: 02/07/2025 | B5: IPVA | C5: 1638799.2 | D5: C | E5: Transferência Constitucional - FUNDEB
A6: 02/07/2025 | B6: BB-APLIC C.PRZ-APL.AUT | C6: 1642134.3 | D6: D | E6: Aplicação Financeira
A7: 03/07/2025 | B7: RECEBIMENTO DE ICMS | C7: 215.7 | D7: C | E7: Transferência Constitucional - FUNDEB
A8: 03/07/2025 | B8: IPVA | C8: 105994.94 | D8: C | E8: Transferência Constitucional - FUNDEB
A9: 03/07/2025 | B9: Emissão Ordem Bancária | C9: 333.78 | D9: D | E9: GRU - Pensão Alimentícia
A10: 03/07/2025 | B10: BB-APLIC C.PRZ-APL.AUT | C10: 105876.86 | D10: D | E10: Aplicação Financeira
A11: 04/07/2025 | B11: ITCMD | C11: 2282.72 | D11: C | E11: Transferência Constitucional - FUNDEB
A12: 04/07/2025 | B12: IPVA | C12: 214738.78 | D12: C | E12: Transferência Constitucional - FUNDEB
A13: 04/07/2025 | B13: RECEBIMENTO DE ICMS | C13: 1034890.9 | D13: C | E13: Transferência Constitucional - FUNDEB
A14: 04/07/2025 | B14: BB-APLIC C.PRZ-APL.AUT | C14: 1251912.4 | D14: D | E14: Aplicação Financeira
A15: 08/07/2025 | B15: ORDEM BANC CANCELADA | C15: 103.93 | D15: C | E15: OB Cancelada | F15: 2025GD01012
A16: 08/07/2025 | B16: Emissão Ordem Bancária | C16: 38093642 | D16: D | E16: Folha de Pagamento | F16: 2025RE00633
A17: 08/07/2025 | B17: Emissão Ordem Bancária | C17: 5702522.3 | D17: D | E17: Folha de Pagamento | F17: 2025RE00634
A18: 08/07/2025 | B18: Resgate Automático | C18: 43796060 | D18: C | E18: Resgate
A19: 09/07/2025 | B19: Folha de Pagamento | C19: 18071061 | D19: D | E19: Férias
A20: 09/07/2025 | B20: Folha de Pagamento | C20: 190519.35 | D20: D | E20: Férias
A21: 09/07/2025 | B21: Emissão Ordem Bancária | C21: 97539.73 | D21: D | E21: Férias
A22: 09/07/2025 | B22: Resgate Automático | C22: 18359120 | D22: C | E22: Resgate
A23: 10/07/2025 | B23: ITCMD | C23: 747.24 | D23: C | E23: Transferência Constitucional - FUNDEB
A24: 10/07/2025 | B24: RECEBIMENTO DE ICMS | C24: 457261.51 | D24: C | E24: Transferência Constitucional - FUNDEB
A25: 10/07/2025 | B25: ITCMD | C25: 896.01 | D25: C | E25: Transferência Constitucional - FUNDEB
A26: 10/07/2025 | B26: IPVA | C26: 88582.81 | D26: C | E26: Transferência Constitucional - FUNDEB
A27: 10/07/2025 | B27: IPVA | C27: 246309.68 | D27: C | E27: Transferência Constitucional - FUNDEB
A28: 10/07/2025 | B28: ITR | C28: 186.91 | D28: C | E28: Transferência Constitucional - FUNDEB
A29: 10/07/2025 | B29: RECEBIMENTO DE ICMS | C29: 269604.92 | D29: C | E29: Transferência Constitucional - FUNDEB
... A37: 10/07/2025 | B37: BB-APLIC C.PRZ-APL.AUT | C37: 18185995 | D37: D | E37: Aplicação Financeira
A38: 16/07/2025 | B38: Emissão Ordem Bancária | C38: 872518.09 | D38: D | E38: Folha de Pagamento | F38: 2025RE00703
A39: 16/07/2025 | B39: Resgate Automático | C39: 872518.09 | D39: C | E39: Resgate
A40: 17/07/2025 | B40: Pagamentos Diversos | C40: 10029.56 | D40: D
A41: 17/07/2025 | B41: Resgate Automático | C41: 10029.56 | D41: C | E41: Resgate
A42: 18/07/2025 | B42: ITR | C42: 193.64 | D42: C | E42: Transferência Constitucional - FUNDEB
A43: 18/07/2025 | B43: FPE/FPM | C43: 410601.9 | D43: C | E43: Transferência Constitucional - FUNDEB
A44: 18/07/2025 | B44: FPE/FPM | C44: 954528.74 | D44: C | E44: Transferência Constitucional - FUNDEB
A45: 18/07/2025 | B45: FPE/FPM | C45: 10506371 | D45: C | E45: Transferência Constitucional - FUNDEB
A46: 18/07/2025 | B46: FPE/FPM | C46: 4830.61 | D46: C | E46: Transferência Constitucional - FUNDEB
A47: 18/07/2025 | B47: IPI/EXPORTACAO | C47: 13606.01 | D47: C | E47: IPI/EXPORTACAO - Cota Débito
A48: 18/07/2025 | B48: IPI/EXPORTACAO | C48: 7893.54 | D48: C | E48: Transferência Constitucional - FUNDEB
A49: 18/07/2025 | B49: COTA DAF-DEBITO | C49: 13606.01 | D49: D | E49: IPI/EXPORTACAO - Cota Débito
A50: 18/07/2025 | B50: Tar Lib/Ant Float Pg Div | C50: 10.02 | D50: D | E50: Tarifa Bancária
A51: 18/07/2025 | B51: BB-APLIC C.PRZ-APL.AUT | C51: 11884409 | D51: D | E51: Aplicação Financeira
A52: 24/07/2025 | B52: ITCMD | C52: 3647.15 | D52: C | E52: Transferência Constitucional - FUNDEB
... A75: 30/07/2025 | B75: Resgate Automático | C75: 11675713 | D75: C | E75: Resgate

Sheet REF - JULHO
D3: =SUBTOTAL(9,D6:D59) -> 98890427
A5: PD | B5: OB | C5: Credor | D5: 7 - Julho | E5: Mês de Ocorrência | F5: RE | G5: GD
A6: 2025PD19018 | B6: 2025OB18726 | C6: PF0000023 - FOLHA DE PAGAMENTO | D6: 333.78 | E6: GRU - Pensão Alimentícia
A7: 2025PD19236 | B7: 2025OB18951 | C7: PF0000023 - FOLHA DE PAGAMENTO | D7: 19.58 | E7: Folha de Pagamento | F7: 2025RE00633
A8: 2025PD19237 | B8: 2025OB18952 | C8: PF0000023 - FOLHA DE PAGAMENTO | D8: 176 | E8: Folha de Pagamento | F8: 2025RE00633
A9: 2025PD19239 | B9: 2025OB18953 | C9: PF0000023 - FOLHA DE PAGAMENTO | D9: 88 | E9: Folha de Pagamento | F9: 2025RE00633
A10: 2025PD19240 | B10: 2025OB18954 | C10: PF0000023 - FOLHA DE PAGAMENTO | D10: 20490.5 | E10: Folha de Pagamento | F10: 2025RE00634
A11: 2025PD19241 | B11: 2025OB18955 | C11: PF0000023 - FOLHA DE PAGAMENTO | D11: 239 | E11: Folha de Pagamento | F11: 2025RE00633
A12: 2025PD19243 | B12: 2025OB18956 | C12: PF0000023 - FOLHA DE PAGAMENTO | D12: 150 | E12: Folha de Pagamento | F12: 2025RE00633
A13: 2025PD19244 | B13: 2025OB18957 | C13: PF0000023 - FOLHA DE PAGAMENTO | D13: 9227.89 | E13: Folha de Pagamento | F13: 2025RE00633
A14: 2025PD19245 | B14: 2025OB18958 | C14: PF0000023 - FOLHA DE PAGAMENTO | D14: 1664.16 | E14: Folha de Pagamento | F14: 2025RE00634
A15: 2025PD19246 | B15: 2025OB18959 | C15: PF0000023 - FOLHA DE PAGAMENTO | D15: 763213.66 | E15: Folha de Pagamento | F15: 2025RE00633
A16: 2025PD19247 | B16: 2025OB18960 | C16: PF0000023 - FOLHA DE PAGAMENTO | D16: 406034.78 | E16: Folha de Pagamento | F16: 2025RE00634
A17: 2025PD19248 | B17: 2025OB18961 | C17: PF0000023 - FOLHA DE PAGAMENTO | D17: 41814.23 | E17: Folha de Pagamento | F17: 2025RE00633
A18: 2025PD19250 | B18: 2025OB18962 | C18: PF0000023 - FOLHA DE PAGAMENTO | D18: 302.39 | E18: Folha de Pagamento | F18: 2025RE00634
... A39: 2025PD19289 | B39: 2025OB18981 | C39: PF0000023 - FOLHA DE PAGAMENTO | D39: 10579.73 | E39: Folha de Pagamento | F39: 2025RE00633
A40: 2025PD21503 | B40: 2025OB21819 | C40: PF0000023 - FOLHA DE PAGAMENTO | D40: 282139.72 | E40: Férias
A41: 2025PD21065 | B41: 2025OB20788 | C41: PF0000023 - FOLHA DE PAGAMENTO | D41: 803815.31 | E41: Folha de Pagamento | F41: 2025RE00703
A42: 2025PD21505 | B42: 2025OB21822 | C42: PF0000023 - FOLHA DE PAGAMENTO | D42: 12223305 | E42: Férias
A43: 2025PD22042 | B43: 2025OB21820 | C43: PF0000023 - FOLHA DE PAGAMENTO | D43: 34130.65 | E43: Folha de Julho/2025
A44: 2025PD22043 | B44: 2025OB21821 | C44: PF0000023 - FOLHA DE PAGAMENTO | D44: 906681.79 | E44: Folha de Julho/2025
A45: 2025PD22047 | B45: 2025OB21825 | C45: PF0000023 - FOLHA DE PAGAMENTO | D45: 16810128 | E45: Folha de Julho/2025
A46: 2025PD21022 | B46: 2025OB20789 | C46: 00394460005887 - SECRETARIA DA RECEITA FEDERAL DO BRASIL (MINISTÉRIO DA FAZENDA) | D46: 45969.53 | E46: Folha de Pagamento | F46: 2025RE00703
A47: 2025PD21023 | B47: 2025OB20790 | C47: 00394460005887 - SECRETARIA DA RECEITA FEDERAL DO BRASIL (MINISTÉRIO DA FAZENDA) | D47: 4596.95 | E47: Folha de Pagamento | F47: 2025RE00703
A48: 2025PD22053 | B48: 2025OB21828 | C48: PF0000023 - FOLHA DE PAGAMENTO | D48: 1288581.9 | E48: Folha de Julho/2025
A49: 2025PD22056 | B49: 2025OB21829 | C49: PF0000023 - FOLHA DE PAGAMENTO | D49: 2177889.2 | E49: Folha de Julho/2025
A50: 2025PD19292 | B50: 2025OB18984 | C50: 03281445000185 - AMAPÁ PREVIDÊNCIA | D50: 2804524.4 | E50: Folha de Pagamento | F50: 2025RE00633
A51: 2025PD19293 | B51: 2025OB18985 | C51: 03281445000185 - AMAPÁ PREVIDÊNCIA | D51: 2972397.5 | E51: Folha de Pagamento | F51: 2025RE00633
A52: 2025PD22060 | B52: 2025OB21830 | C52: PF0000023 - FOLHA DE PAGAMENTO | D52: 2186605.9 | E52: Folha de Julho/2025
A53: 2025PD21508 | B53: 2025OB21823 | C53: PF0000023 - FOLHA DE PAGAMENTO | D53: 1466743.1 | E53: Férias
A54: 2025PD22049 | B54: 2025OB21826 | C54: PF0000023 - FOLHA DE PAGAMENTO | D54: 4970062.2 | E54: Folha de Julho/2025
A55: 2025PD19295 | B55: 2025OB18986 | C55: 03281445000185 - AMAPÁ PREVIDÊNCIA | D55: 636644 | E55: Folha de Pagamento | F55: 2025RE00633
A56: 2025PD21510 | B56: 2025OB21824 | C56: PF0000023 - FOLHA DE PAGAMENTO | D56: 4388680.3 | E56: Férias
A57: 2025PD22051 | B57: 2025OB21827 | C57: PF0000023 - FOLHA DE PAGAMENTO | D57: 6549450.1 | E57: Folha de Julho/2025
A58: 2025PD19296 | B58: 2025OB18987 | C58: 03281445000185 - AMAPÁ PREVIDÊNCIA | D58: 1904919.1 | E58: Folha de Pagamento | F58: 2025RE00634
A59: 2025PD22063 | B59: 2025OB21831 | C59: PF0000023 - FOLHA DE PAGAMENTO | D59: 937116.83 | E59: Folha de Julho/2025
D60: 98890427

Sheet Saldos - 08-2025
B2: CONCILIAÇÃO BANCÁRIA DO EXTRATO BANCÁRIO - AGOSTO DE 2025
B4: 1. Ingressos | E4: Valores do Mês | F4: Acumulado
B5: 1.0 IPI - EXP | E5: 72028.1 | F5: =E5+'Saldos - 07-2025'!F5 -> 548475.78
B6: 1.1 VAAR | E6: 0 | F6: =E6+'Saldos - 07-2025'!F6 -> 1648620.1
B7: 1.2 FPE/FPM | E7: 69203598 | F7: =E7+'Saldos - 07-2025'!F7 -> 5.9313106e+08
B8: 1.3 ICMS | E8: 4569569.8 | F8: =E8+'Saldos - 07-2025'!F8 -> 1.1304135e+08
B9: 1.4 IPVA | E9: 814947.08 | F9: =E9+'Saldos - 07-2025'!F9 -> 13774003
B10: 1.5 ITCMD | E10: 29714.62 | F10: =E10+'Saldos - 07-2025'!F10 -> 221804.14
B11: 1.6 ITR | E11: 4552.23 | F11: =E11+'Saldos - 07-2025'!F11 -> 11046.09
B12: 1.7 ORDEM BANC CANCELADA | E12: 103.93 | F12: =E12+'Saldos - 07-2025'!F12 -> 742.01
B13: 1.8 RESGATE | E13: 16806471 | F13: =E13+'Saldos - 07-2025'!F13 -> 5.0325998e+08
B14: 2 Total das Entradas | E14: =SUM(E5:E13) -> 91500985 | F14: =SUM(F5:F13) -> 1.2256371e+09
B15: 3.0 (-) IPI/Cota DAF Deb | E15: -45583.07 | F15: =E15+'Saldos - 07-2025'!F15 -> -347103.59
B16: 3.1 (-) Ordem Bancária Cancelada | E16: =-E12 -> -103.93 | F16: =E16+'Saldos - 07-2025'!F16 -> -742.01
B17: 3.2 (-) Resgastes efetuados | E17: =-E13 -> -16806471 | F17: =E17+'Saldos - 07-2025'!F17 -> -5.0325998e+08
B18: 3.3 (-) Ajuste VAAR - FNDE | E18: 0 | F18: -164645.69
B19: 3. Total Disponibizado( 1 - 3.0- 3.1 - 3.2 -3.3 - 3.4 ) | E19: =SUM(E14:E18) -> 74648827 | F19: =SUM(F14:F18) -> 7.2186461e+08 | G19: OK
B21: 4. Saídas | E21: Valores do Mês | F21: Acumulado
B22: 4.1 Cota DAF Deb | E22: 45583.07 | F22: =E22+'Saldos - 07-2025'!F22 -> 347103.59
B23: 4.2 O.B.s Canceladas | F23: =E23+'Saldos - 07-2025'!F23 -> 103.93
B24: 4.3.1 Folha de Pagamento e Encargos - Identificados por RE | E24: 44039581 | F24: =E24+'Saldos - 07-2025'!F24 -> 2.9597067e+08
B25: 4.3.2 Folha de Pagamento - Folha 01/2025 | F25: =E25+'Saldos - 07-2025'!F25 -> 34311367
B26: 4.3.3 Folha de Pagamento - Folha 02/2025 | F26: =E26+'Saldos - 07-2025'!F26 -> 34175582
B27: 4.3.4 Folha de Pagamento - Folha 03/2025 | F27: =E27+'Saldos - 07-2025'!F27 -> 33980888
B28: 4.3.5 Folha de Pagamento - Folha 04/2025 | F28: =E28+'Saldos - 07-2025'!F28 -> 35798382
B29: 4.3.6 Folha de Pagamento - Folha 05/2025 | F29: =E29+'Saldos - 07-2025'!F29 -> 35751705
B30: 4.3.7 Folha de Pagamento - Folha 06/2025 | F30: =E30+'Saldos - 07-2025'!F30 -> 36411168
B31: 4.3.8 Folha de Pagamento - Folha 07/2025 | F31: =E31+'Saldos - 07-2025'!F31 -> 35846110
B32: 4.3.9 Folha de Pagamento - Folha 08/2025 | E32: 34911871 | F32: =E32 -> 34911871
B33: 4.3.10 Folha de Pagamento - Férias | F33: =E33+'Saldos - 07-2025'!F32 -> 34056995
B34: 4.3.11 Folha de Pagamento - Adiantamento do 13º Salário | F34: =E34+'Saldos - 07-2025'!F33 -> 31778759
B35: 4.3.12 Ajuste VAAR | F35: =E35+'Saldos - 07-2025'!F34 -> 164645.69
B36: 4.3.13 GRU-GUIA RECOLHIM. UNIAO | F36: =E36+'Saldos - 07-2025'!F35 -> 4005.36
B37: 4.3.14 Pagamentos Diversos - Folha | F37: =E37+'Saldos - 07-2025'!F36 -> 40474.15
B38: 4.4 Tarifa bancária | E38: 16.49 | F38: =E38+'Saldos - 07-2025'!F37 -> 7571.2
B39: 4.5 (-) Aplicações Efetuadas | E39: 12503933 | F39: =E39+'Saldos - 07-2025'!F38 -> 5.8207968e+08
B40: 5. Total Geral das Saídas | E40: =SUM(E22:E39) -> 91500985 | F40: =SUM(F22:F39) -> 1.2256371e+09 | G40: OK
B41: 6.1 (-) Cota DAF Deb | E41: =-E22 -> -45583.07 | F41: =E41+'Saldos - 07-2025'!F40 -> -347103.59
B42: 6.2 (-) Aplicações Efetuadas | E42: =-E39 -> -12503933 | F42: =E42+'Saldos - 07-2025'!F41 -> -5.8207968e+08
B43: 6.3 (-) O.B.s Canceladas | E43: -103.93 | F43: =E43+'Saldos - 07-2025'!F42 -> -630.83
B44: 6.4 (-) Tarifa bancária | E44: =-E38 -> -16.49 | F44: =E44+'Saldos - 07-2025'!F43 -> -7571.2
B45: 6.5 (-) Pagamento Folha não regularizado | F45: =E45+'Saldos - 07-2025'!F44 -> -69976153
B46: 6.6 (-) Ajustes VAAR | F46: =E46+'Saldos - 07-2025'!F45 -> -164645.69
B47: 6.7 (-) Pagamentos Diversos | F47: =E47+'Saldos - 07-2025'!F46 -> -40474.15
B48: 6.7 (+) Regularização de Folha e não Pago | E48: 12683.43 | F48: =E48+'Saldos - 07-2025'!F47 -> 70084235
B49: 6.8.1 (-) GRU Paga e Não Regularizada | F49: =E49+'Saldos - 07-2025'!F48 -> -667.56
B50: 6.8.2 (+) Regularização de GRU Paga em Abril | F50: =E50+'Saldos - 07-2025'!F49 -> 667.56
B51: 6.8.3 (+) Regularização de GRU Não Paga em Maio | F51: =E51+'Saldos - 07-2025'!F50 -> 333.78
B52: Despesa Total do Mês ( confere com o relatório de execução financeira do SEAFI ) | E52: =SUM(E40:E51) -> 78964032 | F52: =SUM(F40:F51) -> 6.4310539e+08
B54: CONTA INVESTIMENTO
B55: saldo Inicial | E55: 1.0436119e+08
B56: Aplicação | E56: 12503933
B57: Resgaste | E57: 16806471
B58: Rendimento Bruto | E58: 956265.43
B59: Saldo Atual | E59: =E55+E56-E57+E58 -> 1.0101492e+08

Sheet Extrato 08-2025
C2: =SUBTOTAL(9,C4:C58) -> 34911871
A3: Data | B3: Historico | C3: Valor R$ | D3: Inf. | E3: Histórico | F3: Detalhamentos
A4: 06/08/2025 | B4: ITCMD | C4: 22403.66 | D4: C | E4: Transferência Constitucional - FUNDEB
A5: 06/08/2025 | B5: IPVA | C5: 399686.14 | D5: C | E5: Transferência Constitucional - FUNDEB
A6: 06/08/2025 | B6: RECEBIMENTO DE ICMS | C6: 933102.97 | D6: C | E6: Transferência Constitucional - FUNDEB
A7: 06/08/2025 | B7: BB-APLIC C.PRZ-APL.AUT | C7: 1355192.8 | D7: D | E7: Aplicação Financeira
A8: 08/08/2025 | B8: ITR | C8: 201.73 | D8: C | E8: Transferência Constitucional - FUNDEB
A9: 08/08/2025 | B9: FPE/FPM | C9: 1274643 | D9: C | E9: Transferência Constitucional - FUNDEB
A10: 08/08/2025 | B10: FPE/FPM | C10: 2963169.9 | D10: C | E10: Transferência Constitucional - FUNDEB
A11: 08/08/2025 | B11: FPE/FPM | C11: 33511742 | D11: C | E11: Transferência Constitucional - FUNDEB
A12: 08/08/2025 | B12: FPE/FPM | C12: 14995.77 | D12: C | E12: Transferência Constitucional - FUNDEB
A13: 08/08/2025 | B13: IPI/EXPORTACAO | C13: 26384.57 | D13: C | E13: IPI/EXPORTACAO - Cota Débito
A14: 08/08/2025 | B14: IPI/EXPORTACAO | C14: 15307.02 | D14: C | E14: Transferência Constitucional - FUNDEB
A15: 08/08/2025 | B15: ORDEM BANC CANCELADA | C15: 103.93 | D15: C | E15: OB Cancelada | F15: 2025GD01019
A16: 08/08/2025 | B16: COTA DAF-DEBITO | C16: 26384.57 | D16: D | E16: IPI/EXPORTACAO - Cota Débito
A17: 08/08/2025 | B17: Emissão Ordem Bancária | C17: 25894511 | D17: D | E17: Folha de Pagamento | F17: 2025RE00739
A18: 08/08/2025 | B18: Emissão Ordem Bancária | C18: 18077541 | D18: D | E18: Folha de Pagamento | F18: 2025RE00740
A19: 08/08/2025 | B19: Resgate Automático | C19: 6191889 | D19: C | E19: Resgate
A20: 12/08/2025 | B20: ITCMD | C20: 2436.63 | D20: C | E20: Transferência Constitucional - FUNDEB
A21: 12/08/2025 | B21: IPVA | C21: 203809.33 | D21: C | E21: Transferência Constitucional - FUNDEB
A22: 12/08/2025 | B22: RECEBIMENTO DE ICMS | C22: 2180672 | D22: C | E22: Transferência Constitucional - FUNDEB
A23: 12/08/2025 | B23: BB-APLIC C.PRZ-APL.AUT | C23: 2386918 | D23: D | E23: Aplicação Financeira
A24: 15/08/2025 | B24: Emissão Ordem Bancária | C24: 67528.53 | D24: D | E24: Folha de Pagamento | F24: 2025RE00756
A25: 15/08/2025 | B25: Resgate Automático | C25: 67528.53 | D25: C | E25: Resgate
A26: 18/08/2025 | B26: ITCMD | C26: 4874.33 | D26: C | E26: Transferência Constitucional - FUNDEB
A27: 18/08/2025 | B27: IPVA | C27: 211451.61 | D27: C | E27: Transferência Constitucional - FUNDEB
A28: 18/08/2025 | B28: RECEBIMENTO DE ICMS | C28: 1455794.8 | D28: C | E28: Transferência Constitucional - FUNDEB
A29: 18/08/2025 | B29: BB-APLIC C.PRZ-APL.AUT | C29: 1672120.7 | D29: D | E29: Aplicação Financeira
A30: 20/08/2025 | B30: ITR | C30: 9.39 | D30: C | E30: Transferência Constitucional - FUNDEB
A31: 20/08/2025 | B31: FPE/FPM | C31: 240603.28 | D31: C | E31: Transferência Constitucional - FUNDEB
A32: 20/08/2025 | B32: FPE/FPM | C32: 559331.89 | D32: C | E32: Transferência Constitucional - FUNDEB
A33: 20/08/2025 | B33: FPE/FPM | C33: 6281143.2 | D33: C | E33: Transferência Constitucional - FUNDEB
A34: 20/08/2025 | B34: FPE/FPM | C34: 2830.59 | D34: C | E34: Transferência Constitucional - FUNDEB
A35: 20/08/2025 | B35: IPI/EXPORTACAO | C35: 9968.98 | D35: C | E35: IPI/EXPORTACAO - Cota Débito
A36: 20/08/2025 | B36: IPI/EXPORTACAO | C36: 5783.51 | D36: C | E36: Transferência Constitucional - FUNDEB
... A58: 29/08/2025 | B58: Resgate Automático | C58: 10220347 | D58: C | E58: Resgate

Sheet REF - AGOSTO
D3: =SUBTOTAL(9,D6:D54) -> 78964032
A5: PD | B5: OB | C5: Credor | D5: 8 - Agosto | E5: Mês de Ocorrência | F5: RE | G5: GD
A6: 2025PD22196 | B6: 2025OB21890 | C6: PF0000023 - FOLHA DE PAGAMENTO | D6: 333.78 | E6: Folha de Pagamento | F6: 2025RE00739
A7: 2025PD22329 | B7: 2025OB21891 | C7: PF0000023 - FOLHA DE PAGAMENTO | D7: 19.58 | E7: Folha de Pagamento | F7: 2025RE00740
A8: 2025PD22330 | B8: 2025OB21892 | C8: PF0000023 - FOLHA DE PAGAMENTO | D8: 176 | E8: Folha de Pagamento | F8: 2025RE00739
A9: 2025PD22331 | B9: 2025OB21893 | C9: PF0000023 - FOLHA DE PAGAMENTO | D9: 88 | E9: Folha de Pagamento | F9: 2025RE00739
A10: 2025PD22332 | B10: 2025OB21894 | C10: PF0000023 - FOLHA DE PAGAMENTO | D10: 20418.11 | E10: Folha de Pagamento | F10: 2025RE00740
A11: 2025PD22333 | B11: 2025OB21895 | C11: PF0000023 - FOLHA DE PAGAMENTO | D11: 239 | E11: Folha de Pagamento | F11: 2025RE00739
A12: 2025PD22334 | B12: 2025OB21896 | C12: PF0000023 - FOLHA DE PAGAMENTO | D12: 150 | E12: Folha de Pagamento | F12: 2025RE00740
A13: 2025PD22335 | B13: 2025OB21897 | C13: PF0000023 - FOLHA DE PAGAMENTO | D13: 9182.76 | E13: Folha de Pagamento | F13: 2025RE00739
A14: 2025PD22336 | B14: 2025OB21898 | C14: PF0000023 - FOLHA DE PAGAMENTO | D14: 1664.16 | E14: Folha de Pagamento | F14: 2025RE00739
A15: 2025PD22337 | B15: 2025OB21899 | C15: PF0000023 - FOLHA DE PAGAMENTO | D15: 779949.74 | E15: Folha de Pagamento | F15: 2025RE00740
A16: 2025PD22338 | B16: 2025OB21900 | C16: PF0000023 - FOLHA DE PAGAMENTO | D16: 414561.37 | E16: Folha de Pagamento | F16: 2025RE00739
A17: 2025PD22339 | B17: 2025OB21901 | C17: PF0000023 - FOLHA DE PAGAMENTO | D17: 41266.43 | E17: Folha de Pagamento | F17: 2025RE00740
... A37: 2025PD23222 | B37: 2025OB23046 | C37: PF0000023 - FOLHA DE PAGAMENTO | D37: 17827.7 | E37: Folha de Pagamento | F37: 2025RE00756
A38: 2025PD25824 | B38: 2025OB25360 | C38: PF0000023 - FOLHA DE PAGAMENTO | D38: 30539.9 | E38: Folha de Agosto/2025
A39: 2025PD25825 | B39: 2025OB25361 | C39: PF0000023 - FOLHA DE PAGAMENTO | D39: 898565.99 | E39: Folha de Agosto/2025
A40: 2025PD25826 | B40: 2025OB25362 | C40: PF0000023 - FOLHA DE PAGAMENTO | D40: 17189518 | E40: Folha de Agosto/2025
A41: 2025PD23225 | B41: 2025OB23047 | C41: 00394460005887 - SECRETARIA DA RECEITA FEDERAL DO BRASIL (MINISTÉRIO DA FAZENDA) | D41: 45182.57 | E41: Folha de Pagamento | F41: 2025RE00756
A42: 2025PD23230 | B42: 2025OB23048 | C42: 00394460005887 - SECRETARIA DA RECEITA FEDERAL DO BRASIL (MINISTÉRIO DA FAZENDA) | D42: 4518.26 | E42: Folha de Pagamento | F42: 2025RE00756
A43: 2025PD25829 | B43: 2025OB25365 | C43: PF0000023 - FOLHA DE PAGAMENTO | D43: 114772.52 | E43: Folha de Agosto/2025
A44: 2025PD25830 | B44: 2025OB25366 | C44: PF0000023 - FOLHA DE PAGAMENTO | D44: 1996484.1 | E44: Folha de Agosto/2025
A45: 2025PD22362 | B45: 2025OB21924 | C45: 03281445000185 - AMAPÁ PREVIDÊNCIA | D45: 2799689.9 | E45: Folha de Pagamento | F45: 2025RE00739
A46: 2025PD22363 | B46: 2025OB21925 | C46: 03281445000185 - AMAPÁ PREVIDÊNCIA | D46: 2979396.9 | E46: Folha de Pagamento | F46: 2025RE00739
A47: 2025PD25831 | B47: 2025OB25367 | C47: PF0000023 - FOLHA DE PAGAMENTO | D47: 2201686.7 | E47: Folha de Agosto/2025
A48: 2025PD25827 | B48: 2025OB25363 | C48: PF0000023 - FOLHA DE PAGAMENTO | D48: 4998104.6 | E48: Folha de Agosto/2025
A49: 2025PD22364 | B49: 2025OB21926 | C49: 03281445000185 - AMAPÁ PREVIDÊNCIA | D49: 636882.58 | E49: Folha de Pagamento | F49: 2025RE00739
A50: 2025PD22360 | B50: 2025OB21922 | C50: PF0000023 - FOLHA DE PAGAMENTO | D50: 2799689.9 | E50: Folha de Pagamento | F50: 2025RE00740
A51: 2025PD22361 | B51: 2025OB21923 | C51: PF0000023 - FOLHA DE PAGAMENTO | D51: 5521912.4 | E51: Folha de Pagamento | F51: 2025RE00739
A52: 2025PD25828 | B52: 2025OB25364 | C52: PF0000023 - FOLHA DE PAGAMENTO | D52: 6551303 | E52: Folha de Agosto/2025
A53: 2025PD22365 | B53: 2025OB21927 | C53: 03281445000185 - AMAPÁ PREVIDÊNCIA | D53: 1905632.9 | E53: Folha de Pagamento | F53: 2025RE00740
A54: 2025PD25832 | B54: 2025OB25368 | C54: PF0000023 - FOLHA DE PAGAMENTO | D54: 943580 | E54: Folha de Agosto/2025
D55: 78964032

Sheet Cálculo Conciliação 4º Bimestre
C3: Saldo dos Pagamentos do SEAFI | D3: =SUM(D5:D9) -> 1.4604409e+08 | E3: =D3-'[1]Demonst Exec Financ Conciliado'!$J$89 -> 11470.64
C5: Extrato de Janeiro | D5: =[2]Janeiro!G1 -> 58285284
C6: SEAFI a maior | D6: 8949.47 | G6: =D6+D5 -> 58294233
C7: Extrato de Fevereiro | D7: =[2]Fevereiro!G1 -> 88938686
C8: SEAFI a menor ( regularizado em março ) | D8: -1194723.6 | E8: pago em março
C9: SEAFI a maior | D9: 5894.85 | G9: =SUM(D7:D9) -> 87749857
C11: COMPOSIÇÃO DE SALDO DO FUNDEB
C12: 4º BIMESTRE DE 2025
C14: Dsiponibilidade Financeira em 31/12/2024 | D14: 15778860
C15: ( + ) Ingressos = Transferências Constitucionais - janeiro-2025 | D15: 92936040
C16: ( + ) Ingressos = Transferências Constitucionais - fevereiro-2025 | D16: 1.115289e+08 | I16: =D16+D15 -> 2.0446494e+08
C17: ( + ) Ingressos = Transferências Constitucionais - Março-2025 | D17: 83756928
C18: ( + ) Ingressos = Transferências Constitucionais - Abril-2025 | D18: 82197615 | I18: =D18+D17+D16+D15 -> 3.7041948e+08
C19: ( + ) Ingressos = Transferências Constitucionais - Maio-2025 | D19: ='Saldos - 05-2025'!E19 -> 1.0410939e+08
C20: ( + ) Ingressos = Transferências Constitucionais - Junho-2025 | D20: ='Saldos - 06-2025'!E19 -> 1.0320772e+08 | I20: =D18+D17+D16+D15+D19+D20 -> 5.7773659e+08
C21: ( + ) Ingressos = Transferências Constitucionais - Julho-2025 | D21: ='Saldos - 07-2025'!E19 -> 69479194
C22: ( + ) Ingressos = Transferências Constitucionais - Agosto-2025 | D22: ='Saldos - 08-2025'!E19 -> 74648827 | I22: =D22+D21+D20+D19+D18+D17+D16+D15 -> 7.2186461e+08
C23: ( + ) Ingressos = Rendimentos do FUNDEB - 1º Bimestre-2025 | D23: 901662.73
C24: ( + ) Ingressos = Rendimentos do FUNDEB - 2º Bimestre-2025 | D24: 1438396.9
C25: ( + ) Ingressos = Rendimentos do FUNDEB - 3º Bimestre-2025 | D25: 2042692.5
C26: ( + ) Ingressos = Rendimentos do FUNDEB - 4º Bimestre-2025 | D26: ='Saldos - 08-2025'!E58+'Saldos - 07-2025'!E57 -> 2033609.3 | I26: =D25+D24+D23+D26 -> 6416361.5
C27: ( - ) Pagamentos Efetuados = Relatório de Execução Financeira | D27: -6.4310539e+08
C28: ( - ) Pagto Tarifa Bancária não regularizada no SEAFI | D28: -7571.2 | I28: =D28+D31 -> -48045.35
C29: ( + ) Pagto de Folha - não regularizado | D29: 108526.2
C30: ( - ) Folha Regularizada e não Paga | I30: =D29 -> 108526.2
C31: ( - ) Pagamentos Diversos - Folha | D31: -40474.15
C34: ( = ) Saldo do SIOPE | D34: =SUM(D14:D33) -> 1.0101492e+08
C36: Dsiponibilidade Financeira em 31/08/2025 | D36: ='Saldos - 08-2025'!E59 -> 1.0101492e+08 | I36: =D36-D34 -> 0.0099999905
C38: Diferença a identificar | D38: =D34-D36 -> -0.0099999905
